{"box_data": [{"position": {"minX": 313.5, "minY": 229.125, "maxX": 400.0, "maxY": 286.5}, "class_id": 1, "box_caption": "Paper 0.878", "scores": {"class_score": 0.8779296875}, "domain": "pixel"}, {"position": {"minX": 217.75, "minY": 57.9375, "maxX": 379.75, "maxY": 175.25}, "class_id": 1, "box_caption": "Paper 0.787", "scores": {"class_score": 0.78662109375}, "domain": "pixel"}, {"position": {"minX": 230.125, "minY": 383.5, "maxX": 634.5, "maxY": 639.5}, "class_id": 6, "box_caption": "Styrofoam 0.744", "scores": {"class_score": 0.74365234375}, "domain": "pixel"}, {"position": {"minX": 383.5, "minY": 250.5, "maxX": 499.5, "maxY": 323.0}, "class_id": 7, "box_caption": "Plastic bag 0.708", "scores": {"class_score": 0.7080078125}, "domain": "pixel"}, {"position": {"minX": 211.5, "minY": 141.25, "maxX": 400.0, "maxY": 235.5}, "class_id": 1, "box_caption": "Paper 0.686", "scores": {"class_score": 0.68603515625}, "domain": "pixel"}, {"position": {"minX": 459.5, "minY": 17.875, "maxX": 616.5, "maxY": 130.125}, "class_id": 1, "box_caption": "Paper 0.622", "scores": {"class_score": 0.6220703125}, "domain": "pixel"}, {"position": {"minX": 345.5, "minY": 102.375, "maxX": 590.0, "maxY": 283.5}, "class_id": 1, "box_caption": "Paper 0.617", "scores": {"class_score": 0.6171875}, "domain": "pixel"}, {"position": {"minX": 246.25, "minY": 528.0, "maxX": 300.75, "maxY": 573.0}, "class_id": 0, "box_caption": "General trash 0.578", "scores": {"class_score": 0.57763671875}, "domain": "pixel"}, {"position": {"minX": 433.5, "minY": 79.5, "maxX": 594.5, "maxY": 146.0}, "class_id": 1, "box_caption": "Paper 0.564", "scores": {"class_score": 0.564453125}, "domain": "pixel"}, {"position": {"minX": 648.0, "minY": 255.75, "maxX": 730.0, "maxY": 296.75}, "class_id": 0, "box_caption": "General trash 0.400", "scores": {"class_score": 0.399658203125}, "domain": "pixel"}, {"position": {"minX": 777.5, "minY": 999.5, "maxX": 1040.0, "maxY": 1044.0}, "class_id": 1, "box_caption": "Paper 0.370", "scores": {"class_score": 0.3701171875}, "domain": "pixel"}, {"position": {"minX": 219.25, "minY": 57.40625, "maxX": 376.25, "maxY": 176.0}, "class_id": 2, "box_caption": "Paper pack 0.214", "scores": {"class_score": 0.2135009765625}, "domain": "pixel"}, {"position": {"minX": 439.5, "minY": 78.0625, "maxX": 489.5, "maxY": 111.1875}, "class_id": 1, "box_caption": "Paper 0.207", "scores": {"class_score": 0.207275390625}, "domain": "pixel"}, {"position": {"minX": 883.5, "minY": 1009.0, "maxX": 1044.0, "maxY": 1043.0}, "class_id": 1, "box_caption": "Paper 0.197", "scores": {"class_score": 0.1966552734375}, "domain": "pixel"}, {"position": {"minX": 307.0, "minY": 128.25, "maxX": 372.5, "maxY": 160.5}, "class_id": 1, "box_caption": "Paper 0.171", "scores": {"class_score": 0.170654296875}, "domain": "pixel"}, {"position": {"minX": 440.5, "minY": 81.375, "maxX": 518.0, "maxY": 129.0}, "class_id": 1, "box_caption": "Paper 0.152", "scores": {"class_score": 0.1517333984375}, "domain": "pixel"}, {"position": {"minX": 431.25, "minY": 49.875, "maxX": 613.0, "maxY": 157.75}, "class_id": 1, "box_caption": "Paper 0.145", "scores": {"class_score": 0.1446533203125}, "domain": "pixel"}, {"position": {"minX": 259.5, "minY": 538.0, "maxX": 304.5, "maxY": 577.0}, "class_id": 0, "box_caption": "General trash 0.143", "scores": {"class_score": 0.142822265625}, "domain": "pixel"}, {"position": {"minX": 416.5, "minY": 82.1875, "maxX": 596.5, "maxY": 183.75}, "class_id": 1, "box_caption": "Paper 0.141", "scores": {"class_score": 0.1414794921875}, "domain": "pixel"}, {"position": {"minX": 644.5, "minY": 255.625, "maxX": 729.5, "maxY": 297.5}, "class_id": 7, "box_caption": "Plastic bag 0.140", "scores": {"class_score": 0.14013671875}, "domain": "pixel"}, {"position": {"minX": 773.5, "minY": 962.0, "maxX": 1045.0, "maxY": 1038.0}, "class_id": 1, "box_caption": "Paper 0.126", "scores": {"class_score": 0.12646484375}, "domain": "pixel"}, {"position": {"minX": 439.0, "minY": 78.75, "maxX": 540.0, "maxY": 140.25}, "class_id": 1, "box_caption": "Paper 0.125", "scores": {"class_score": 0.125}, "domain": "pixel"}, {"position": {"minX": 386.0, "minY": 54.9375, "maxX": 641.0, "maxY": 294.25}, "class_id": 1, "box_caption": "Paper 0.103", "scores": {"class_score": 0.10260009765625}, "domain": "pixel"}, {"position": {"minX": 238.125, "minY": 991.5, "maxX": 363.5, "maxY": 1039.0}, "class_id": 0, "box_caption": "General trash 0.089", "scores": {"class_score": 0.08917236328125}, "domain": "pixel"}, {"position": {"minX": 451.25, "minY": 75.5, "maxX": 495.75, "maxY": 108.125}, "class_id": 1, "box_caption": "Paper 0.087", "scores": {"class_score": 0.0870361328125}, "domain": "pixel"}, {"position": {"minX": 601.0, "minY": 99.125, "maxX": 629.0, "maxY": 161.125}, "class_id": 1, "box_caption": "Paper 0.085", "scores": {"class_score": 0.0845947265625}, "domain": "pixel"}, {"position": {"minX": 236.25, "minY": 990.0, "maxX": 364.75, "maxY": 1041.0}, "class_id": 9, "box_caption": "Clothing 0.084", "scores": {"class_score": 0.084228515625}, "domain": "pixel"}, {"position": {"minX": 238.0, "minY": 990.0, "maxX": 368.5, "maxY": 1040.0}, "class_id": 5, "box_caption": "Plastic 0.079", "scores": {"class_score": 0.07928466796875}, "domain": "pixel"}, {"position": {"minX": 252.0, "minY": 532.0, "maxX": 315.0, "maxY": 579.0}, "class_id": 0, "box_caption": "General trash 0.077", "scores": {"class_score": 0.07696533203125}, "domain": "pixel"}, {"position": {"minX": 345.75, "minY": 172.25, "maxX": 564.0, "maxY": 288.5}, "class_id": 1, "box_caption": "Paper 0.077", "scores": {"class_score": 0.07666015625}, "domain": "pixel"}, {"position": {"minX": 237.25, "minY": 991.5, "maxX": 360.25, "maxY": 1038.0}, "class_id": 4, "box_caption": "Glass 0.075", "scores": {"class_score": 0.07476806640625}, "domain": "pixel"}, {"position": {"minX": 453.0, "minY": 16.875, "maxX": 633.0, "maxY": 180.625}, "class_id": 1, "box_caption": "Paper 0.075", "scores": {"class_score": 0.0745849609375}, "domain": "pixel"}, {"position": {"minX": 245.125, "minY": 533.0, "maxX": 284.0, "maxY": 565.0}, "class_id": 0, "box_caption": "General trash 0.072", "scores": {"class_score": 0.07196044921875}, "domain": "pixel"}, {"position": {"minX": 364.25, "minY": 135.25, "maxX": 406.75, "maxY": 156.0}, "class_id": 1, "box_caption": "Paper 0.072", "scores": {"class_score": 0.0718994140625}, "domain": "pixel"}, {"position": {"minX": 541.0, "minY": 112.625, "maxX": 593.0, "maxY": 146.125}, "class_id": 1, "box_caption": "Paper 0.068", "scores": {"class_score": 0.0675048828125}, "domain": "pixel"}, {"position": {"minX": 266.5, "minY": 546.5, "maxX": 301.5, "maxY": 575.5}, "class_id": 0, "box_caption": "General trash 0.066", "scores": {"class_score": 0.0655517578125}, "domain": "pixel"}, {"position": {"minX": 440.0, "minY": 81.8125, "maxX": 471.0, "maxY": 111.4375}, "class_id": 1, "box_caption": "Paper 0.063", "scores": {"class_score": 0.062744140625}, "domain": "pixel"}, {"position": {"minX": 231.875, "minY": 382.75, "maxX": 638.0, "maxY": 638.0}, "class_id": 0, "box_caption": "General trash 0.061", "scores": {"class_score": 0.061187744140625}, "domain": "pixel"}, {"position": {"minX": 322.25, "minY": 134.375, "maxX": 404.25, "maxY": 160.375}, "class_id": 1, "box_caption": "Paper 0.057", "scores": {"class_score": 0.057159423828125}, "domain": "pixel"}, {"position": {"minX": 242.625, "minY": 511.75, "maxX": 315.0, "maxY": 596.0}, "class_id": 0, "box_caption": "General trash 0.056", "scores": {"class_score": 0.056365966796875}, "domain": "pixel"}, {"position": {"minX": 893.5, "minY": 979.5, "maxX": 1046.0, "maxY": 1027.0}, "class_id": 1, "box_caption": "Paper 0.053", "scores": {"class_score": 0.05322265625}, "domain": "pixel"}, {"position": {"minX": 952.5, "minY": 1012.0, "maxX": 1044.0, "maxY": 1042.0}, "class_id": 1, "box_caption": "Paper 0.053", "scores": {"class_score": 0.05322265625}, "domain": "pixel"}, {"position": {"minX": 374.5, "minY": 134.25, "maxX": 406.5, "maxY": 151.75}, "class_id": 1, "box_caption": "Paper 0.052", "scores": {"class_score": 0.05242919921875}, "domain": "pixel"}, {"position": {"minX": 314.0, "minY": 129.625, "maxX": 370.0, "maxY": 161.125}, "class_id": 0, "box_caption": "General trash 0.052", "scores": {"class_score": 0.052276611328125}, "domain": "pixel"}, {"position": {"minX": 350.75, "minY": 130.25, "maxX": 404.75, "maxY": 155.5}, "class_id": 1, "box_caption": "Paper 0.051", "scores": {"class_score": 0.05126953125}, "domain": "pixel"}, {"position": {"minX": 350.75, "minY": 136.125, "maxX": 405.75, "maxY": 157.875}, "class_id": 0, "box_caption": "General trash 0.051", "scores": {"class_score": 0.05120849609375}, "domain": "pixel"}, {"position": {"minX": 216.75, "minY": 56.78125, "maxX": 378.25, "maxY": 176.5}, "class_id": 0, "box_caption": "General trash 0.050", "scores": {"class_score": 0.050140380859375}, "domain": "pixel"}, {"position": {"minX": 775.0, "minY": 1005.0, "maxX": 1043.0, "maxY": 1047.0}, "class_id": 0, "box_caption": "General trash 0.048", "scores": {"class_score": 0.048492431640625}, "domain": "pixel"}, {"position": {"minX": 431.5, "minY": 381.0, "maxX": 631.5, "maxY": 598.5}, "class_id": 6, "box_caption": "Styrofoam 0.048", "scores": {"class_score": 0.048431396484375}, "domain": "pixel"}, {"position": {"minX": 238.25, "minY": 993.0, "maxX": 331.75, "maxY": 1039.0}, "class_id": 7, "box_caption": "Plastic bag 0.047", "scores": {"class_score": 0.047119140625}, "domain": "pixel"}, {"position": {"minX": 391.0, "minY": 105.4375, "maxX": 601.5, "maxY": 239.5}, "class_id": 1, "box_caption": "Paper 0.047", "scores": {"class_score": 0.04705810546875}, "domain": "pixel"}, {"position": {"minX": 924.0, "minY": 1005.0, "maxX": 1038.0, "maxY": 1040.0}, "class_id": 1, "box_caption": "Paper 0.043", "scores": {"class_score": 0.043212890625}, "domain": "pixel"}, {"position": {"minX": 465.0, "minY": 76.5625, "maxX": 505.5, "maxY": 107.9375}, "class_id": 1, "box_caption": "Paper 0.042", "scores": {"class_score": 0.042083740234375}, "domain": "pixel"}, {"position": {"minX": 777.5, "minY": 999.5, "maxX": 1040.0, "maxY": 1044.0}, "class_id": 7, "box_caption": "Plastic bag 0.040", "scores": {"class_score": 0.040374755859375}, "domain": "pixel"}, {"position": {"minX": 335.75, "minY": 114.75, "maxX": 398.75, "maxY": 152.5}, "class_id": 1, "box_caption": "Paper 0.039", "scores": {"class_score": 0.039093017578125}, "domain": "pixel"}, {"position": {"minX": 439.25, "minY": 109.9375, "maxX": 546.0, "maxY": 138.125}, "class_id": 1, "box_caption": "Paper 0.039", "scores": {"class_score": 0.038970947265625}, "domain": "pixel"}, {"position": {"minX": 521.0, "minY": 40.5, "maxX": 638.0, "maxY": 420.25}, "class_id": 1, "box_caption": "Paper 0.037", "scores": {"class_score": 0.037109375}, "domain": "pixel"}, {"position": {"minX": 443.25, "minY": 78.4375, "maxX": 528.0, "maxY": 114.1875}, "class_id": 1, "box_caption": "Paper 0.037", "scores": {"class_score": 0.036651611328125}, "domain": "pixel"}, {"position": {"minX": 521.0, "minY": 102.75, "maxX": 590.0, "maxY": 143.5}, "class_id": 1, "box_caption": "Paper 0.037", "scores": {"class_score": 0.036590576171875}, "domain": "pixel"}, {"position": {"minX": 380.75, "minY": 251.0, "maxX": 494.25, "maxY": 321.0}, "class_id": 1, "box_caption": "Paper 0.034", "scores": {"class_score": 0.033935546875}, "domain": "pixel"}, {"position": {"minX": 567.0, "minY": 107.6875, "maxX": 619.0, "maxY": 155.25}, "class_id": 1, "box_caption": "Paper 0.034", "scores": {"class_score": 0.03387451171875}, "domain": "pixel"}, {"position": {"minX": 222.5, "minY": 62.3125, "maxX": 430.5, "maxY": 219.75}, "class_id": 1, "box_caption": "Paper 0.033", "scores": {"class_score": 0.033294677734375}, "domain": "pixel"}, {"position": {"minX": 436.0, "minY": 63.875, "maxX": 577.5, "maxY": 133.75}, "class_id": 1, "box_caption": "Paper 0.033", "scores": {"class_score": 0.03314208984375}, "domain": "pixel"}, {"position": {"minX": 238.125, "minY": 991.5, "maxX": 363.5, "maxY": 1039.0}, "class_id": 3, "box_caption": "Metal 0.033", "scores": {"class_score": 0.032958984375}, "domain": "pixel"}, {"position": {"minX": 867.0, "minY": 1007.0, "maxX": 1038.0, "maxY": 1043.0}, "class_id": 7, "box_caption": "Plastic bag 0.033", "scores": {"class_score": 0.032806396484375}, "domain": "pixel"}, {"position": {"minX": 259.0, "minY": 138.375, "maxX": 421.5, "maxY": 247.125}, "class_id": 1, "box_caption": "Paper 0.033", "scores": {"class_score": 0.032684326171875}, "domain": "pixel"}, {"position": {"minX": 216.75, "minY": 56.78125, "maxX": 378.25, "maxY": 176.5}, "class_id": 7, "box_caption": "Plastic bag 0.032", "scores": {"class_score": 0.032440185546875}, "domain": "pixel"}, {"position": {"minX": 238.5, "minY": 993.0, "maxX": 313.0, "maxY": 1040.0}, "class_id": 0, "box_caption": "General trash 0.032", "scores": {"class_score": 0.031890869140625}, "domain": "pixel"}, {"position": {"minX": 867.0, "minY": 1007.0, "maxX": 1038.0, "maxY": 1043.0}, "class_id": 0, "box_caption": "General trash 0.032", "scores": {"class_score": 0.03179931640625}, "domain": "pixel"}, {"position": {"minX": 343.0, "minY": 136.5, "maxX": 405.0, "maxY": 160.25}, "class_id": 7, "box_caption": "Plastic bag 0.032", "scores": {"class_score": 0.03155517578125}, "domain": "pixel"}, {"position": {"minX": 503.25, "minY": 92.5, "maxX": 604.0, "maxY": 151.0}, "class_id": 1, "box_caption": "Paper 0.031", "scores": {"class_score": 0.031341552734375}, "domain": "pixel"}, {"position": {"minX": 251.0, "minY": 87.5625, "maxX": 423.0, "maxY": 199.0}, "class_id": 1, "box_caption": "Paper 0.031", "scores": {"class_score": 0.0310211181640625}, "domain": "pixel"}, {"position": {"minX": 447.0, "minY": 88.5, "maxX": 615.0, "maxY": 166.5}, "class_id": 1, "box_caption": "Paper 0.030", "scores": {"class_score": 0.029754638671875}, "domain": "pixel"}, {"position": {"minX": 237.75, "minY": 369.25, "maxX": 1065.0, "maxY": 1052.0}, "class_id": 6, "box_caption": "Styrofoam 0.029", "scores": {"class_score": 0.028961181640625}, "domain": "pixel"}, {"position": {"minX": 449.5, "minY": 81.1875, "maxX": 483.5, "maxY": 109.6875}, "class_id": 1, "box_caption": "Paper 0.028", "scores": {"class_score": 0.02813720703125}, "domain": "pixel"}, {"position": {"minX": 708.0, "minY": 1007.0, "maxX": 996.0, "maxY": 1045.0}, "class_id": 1, "box_caption": "Paper 0.028", "scores": {"class_score": 0.027740478515625}, "domain": "pixel"}, {"position": {"minX": 495.75, "minY": 14.3125, "maxX": 620.0, "maxY": 45.625}, "class_id": 1, "box_caption": "Paper 0.027", "scores": {"class_score": 0.027435302734375}, "domain": "pixel"}, {"position": {"minX": 485.25, "minY": 91.1875, "maxX": 586.0, "maxY": 141.375}, "class_id": 1, "box_caption": "Paper 0.027", "scores": {"class_score": 0.027008056640625}, "domain": "pixel"}, {"position": {"minX": 847.0, "minY": 978.0, "maxX": 1049.0, "maxY": 1042.0}, "class_id": 1, "box_caption": "Paper 0.026", "scores": {"class_score": 0.0258636474609375}, "domain": "pixel"}, {"position": {"minX": 378.5, "minY": 396.0, "maxX": 619.0, "maxY": 585.5}, "class_id": 0, "box_caption": "General trash 0.025", "scores": {"class_score": 0.0253448486328125}, "domain": "pixel"}, {"position": {"minX": 293.5, "minY": 128.0, "maxX": 408.0, "maxY": 218.5}, "class_id": 1, "box_caption": "Paper 0.025", "scores": {"class_score": 0.02496337890625}, "domain": "pixel"}, {"position": {"minX": 244.0, "minY": 483.5, "maxX": 413.0, "maxY": 635.5}, "class_id": 0, "box_caption": "General trash 0.024", "scores": {"class_score": 0.02392578125}, "domain": "pixel"}, {"position": {"minX": 381.5, "minY": 250.0, "maxX": 502.5, "maxY": 319.0}, "class_id": 0, "box_caption": "General trash 0.024", "scores": {"class_score": 0.023895263671875}, "domain": "pixel"}, {"position": {"minX": 388.25, "minY": 604.5, "maxX": 415.25, "maxY": 630.5}, "class_id": 0, "box_caption": "General trash 0.024", "scores": {"class_score": 0.0237884521484375}, "domain": "pixel"}, {"position": {"minX": 502.0, "minY": 78.875, "maxX": 616.0, "maxY": 192.875}, "class_id": 1, "box_caption": "Paper 0.024", "scores": {"class_score": 0.0236968994140625}, "domain": "pixel"}, {"position": {"minX": 24.8125, "minY": 13.96875, "maxX": 244.5, "maxY": 109.875}, "class_id": 1, "box_caption": "Paper 0.023", "scores": {"class_score": 0.023468017578125}, "domain": "pixel"}, {"position": {"minX": 477.25, "minY": 111.1875, "maxX": 549.0, "maxY": 139.875}, "class_id": 1, "box_caption": "Paper 0.023", "scores": {"class_score": 0.023284912109375}, "domain": "pixel"}, {"position": {"minX": 564.5, "minY": 40.375, "maxX": 627.5, "maxY": 294.5}, "class_id": 1, "box_caption": "Paper 0.023", "scores": {"class_score": 0.0229644775390625}, "domain": "pixel"}, {"position": {"minX": 774.0, "minY": 976.0, "maxX": 1045.0, "maxY": 1042.0}, "class_id": 0, "box_caption": "General trash 0.023", "scores": {"class_score": 0.02288818359375}, "domain": "pixel"}, {"position": {"minX": 322.25, "minY": 134.375, "maxX": 404.25, "maxY": 160.375}, "class_id": 0, "box_caption": "General trash 0.022", "scores": {"class_score": 0.0218353271484375}, "domain": "pixel"}, {"position": {"minX": 253.875, "minY": 156.0, "maxX": 355.75, "maxY": 235.0}, "class_id": 1, "box_caption": "Paper 0.021", "scores": {"class_score": 0.021392822265625}, "domain": "pixel"}, {"position": {"minX": 345.25, "minY": 88.25, "maxX": 375.75, "maxY": 123.875}, "class_id": 1, "box_caption": "Paper 0.021", "scores": {"class_score": 0.0211029052734375}, "domain": "pixel"}, {"position": {"minX": 343.5, "minY": 96.375, "maxX": 383.0, "maxY": 135.75}, "class_id": 1, "box_caption": "Paper 0.021", "scores": {"class_score": 0.02081298828125}, "domain": "pixel"}, {"position": {"minX": 251.625, "minY": 137.0, "maxX": 339.5, "maxY": 188.0}, "class_id": 1, "box_caption": "Paper 0.020", "scores": {"class_score": 0.019744873046875}, "domain": "pixel"}, {"position": {"minX": 513.5, "minY": 14.078125, "maxX": 615.5, "maxY": 33.5}, "class_id": 1, "box_caption": "Paper 0.019", "scores": {"class_score": 0.0194091796875}, "domain": "pixel"}, {"position": {"minX": 464.75, "minY": 16.875, "maxX": 636.5, "maxY": 275.5}, "class_id": 1, "box_caption": "Paper 0.019", "scores": {"class_score": 0.01934814453125}, "domain": "pixel"}, {"position": {"minX": 233.0, "minY": 423.25, "maxX": 434.5, "maxY": 632.5}, "class_id": 0, "box_caption": "General trash 0.019", "scores": {"class_score": 0.01910400390625}, "domain": "pixel"}, {"position": {"minX": 240.125, "minY": 993.5, "maxX": 315.0, "maxY": 1038.0}, "class_id": 5, "box_caption": "Plastic 0.019", "scores": {"class_score": 0.0185546875}, "domain": "pixel"}, {"position": {"minX": 468.0, "minY": 79.625, "maxX": 570.0, "maxY": 137.625}, "class_id": 1, "box_caption": "Paper 0.018", "scores": {"class_score": 0.0184326171875}, "domain": "pixel"}, {"position": {"minX": 83.6875, "minY": 17.96875, "maxX": 199.0, "maxY": 109.5}, "class_id": 0, "box_caption": "General trash 0.018", "scores": {"class_score": 0.01806640625}, "domain": "pixel"}, {"position": {"minX": 232.5, "minY": 974.5, "maxX": 422.5, "maxY": 1040.0}, "class_id": 4, "box_caption": "Glass 0.018", "scores": {"class_score": 0.0180511474609375}, "domain": "pixel"}, {"position": {"minX": 232.75, "minY": 519.5, "maxX": 297.75, "maxY": 564.5}, "class_id": 0, "box_caption": "General trash 0.018", "scores": {"class_score": 0.0177459716796875}, "domain": "pixel"}, {"position": {"minX": 293.75, "minY": 108.4375, "maxX": 374.75, "maxY": 165.375}, "class_id": 1, "box_caption": "Paper 0.018", "scores": {"class_score": 0.017730712890625}, "domain": "pixel"}, {"position": {"minX": 231.875, "minY": 471.75, "maxX": 368.0, "maxY": 597.0}, "class_id": 0, "box_caption": "General trash 0.018", "scores": {"class_score": 0.0176544189453125}, "domain": "pixel"}, {"position": {"minX": 488.0, "minY": 14.921875, "maxX": 618.0, "maxY": 66.375}, "class_id": 1, "box_caption": "Paper 0.018", "scores": {"class_score": 0.0175933837890625}, "domain": "pixel"}, {"position": {"minX": 646.0, "minY": 255.5, "maxX": 729.0, "maxY": 295.5}, "class_id": 6, "box_caption": "Styrofoam 0.018", "scores": {"class_score": 0.0175628662109375}, "domain": "pixel"}, {"position": {"minX": 454.5, "minY": 76.3125, "maxX": 485.0, "maxY": 103.4375}, "class_id": 1, "box_caption": "Paper 0.018", "scores": {"class_score": 0.01751708984375}, "domain": "pixel"}, {"position": {"minX": 252.0, "minY": 525.0, "maxX": 358.0, "maxY": 625.0}, "class_id": 0, "box_caption": "General trash 0.018", "scores": {"class_score": 0.0175018310546875}, "domain": "pixel"}, {"position": {"minX": 890.5, "minY": 1012.0, "maxX": 999.5, "maxY": 1040.0}, "class_id": 1, "box_caption": "Paper 0.017", "scores": {"class_score": 0.0169219970703125}, "domain": "pixel"}, {"position": {"minX": 486.0, "minY": 16.25, "maxX": 633.0, "maxY": 90.125}, "class_id": 1, "box_caption": "Paper 0.017", "scores": {"class_score": 0.0169219970703125}, "domain": "pixel"}, {"position": {"minX": 235.625, "minY": 489.0, "maxX": 634.0, "maxY": 670.0}, "class_id": 0, "box_caption": "General trash 0.017", "scores": {"class_score": 0.01678466796875}, "domain": "pixel"}, {"position": {"minX": 468.0, "minY": 77.75, "maxX": 501.5, "maxY": 106.75}, "class_id": 0, "box_caption": "General trash 0.017", "scores": {"class_score": 0.016754150390625}, "domain": "pixel"}, {"position": {"minX": 588.5, "minY": 96.25, "maxX": 626.5, "maxY": 155.625}, "class_id": 1, "box_caption": "Paper 0.017", "scores": {"class_score": 0.016693115234375}, "domain": "pixel"}, {"position": {"minX": 553.0, "minY": 5.5, "maxX": 619.0, "maxY": 358.5}, "class_id": 1, "box_caption": "Paper 0.016", "scores": {"class_score": 0.0164031982421875}, "domain": "pixel"}, {"position": {"minX": 379.75, "minY": 127.125, "maxX": 410.75, "maxY": 149.625}, "class_id": 1, "box_caption": "Paper 0.016", "scores": {"class_score": 0.0160675048828125}, "domain": "pixel"}, {"position": {"minX": 558.0, "minY": 113.125, "maxX": 600.0, "maxY": 153.625}, "class_id": 1, "box_caption": "Paper 0.016", "scores": {"class_score": 0.0160675048828125}, "domain": "pixel"}, {"position": {"minX": 532.0, "minY": -59.75, "maxX": 1024.0, "maxY": 801.0}, "class_id": 6, "box_caption": "Styrofoam 0.016", "scores": {"class_score": 0.0159454345703125}, "domain": "pixel"}, {"position": {"minX": 323.5, "minY": 131.75, "maxX": 360.5, "maxY": 158.75}, "class_id": 1, "box_caption": "Paper 0.016", "scores": {"class_score": 0.0157623291015625}, "domain": "pixel"}, {"position": {"minX": 238.75, "minY": 474.5, "maxX": 502.25, "maxY": 643.5}, "class_id": 0, "box_caption": "General trash 0.016", "scores": {"class_score": 0.015716552734375}, "domain": "pixel"}, {"position": {"minX": 554.0, "minY": 14.7578125, "maxX": 617.0, "maxY": 32.0625}, "class_id": 1, "box_caption": "Paper 0.016", "scores": {"class_score": 0.0155792236328125}, "domain": "pixel"}, {"position": {"minX": 282.75, "minY": 143.75, "maxX": 306.25, "maxY": 176.25}, "class_id": 1, "box_caption": "Paper 0.015", "scores": {"class_score": 0.0154571533203125}, "domain": "pixel"}, {"position": {"minX": 233.25, "minY": 382.25, "maxX": 634.0, "maxY": 637.0}, "class_id": 7, "box_caption": "Plastic bag 0.015", "scores": {"class_score": 0.01514434814453125}, "domain": "pixel"}, {"position": {"minX": 592.5, "minY": 107.75, "maxX": 623.5, "maxY": 166.0}, "class_id": 1, "box_caption": "Paper 0.015", "scores": {"class_score": 0.0147552490234375}, "domain": "pixel"}, {"position": {"minX": 279.25, "minY": 78.625, "maxX": 402.75, "maxY": 168.375}, "class_id": 1, "box_caption": "Paper 0.014", "scores": {"class_score": 0.0144805908203125}, "domain": "pixel"}, {"position": {"minX": 544.0, "minY": 125.25, "maxX": 590.0, "maxY": 153.25}, "class_id": 1, "box_caption": "Paper 0.014", "scores": {"class_score": 0.01425933837890625}, "domain": "pixel"}, {"position": {"minX": 402.5, "minY": 604.0, "maxX": 439.0, "maxY": 629.0}, "class_id": 0, "box_caption": "General trash 0.014", "scores": {"class_score": 0.013885498046875}, "domain": "pixel"}, {"position": {"minX": 237.75, "minY": 369.25, "maxX": 1065.0, "maxY": 1052.0}, "class_id": 0, "box_caption": "General trash 0.014", "scores": {"class_score": 0.0138397216796875}, "domain": "pixel"}, {"position": {"minX": 261.75, "minY": 144.625, "maxX": 310.75, "maxY": 179.875}, "class_id": 1, "box_caption": "Paper 0.014", "scores": {"class_score": 0.01380157470703125}, "domain": "pixel"}, {"position": {"minX": 298.75, "minY": 15.46875, "maxX": 507.25, "maxY": 100.875}, "class_id": 1, "box_caption": "Paper 0.014", "scores": {"class_score": 0.01361083984375}, "domain": "pixel"}, {"position": {"minX": 244.375, "minY": 514.5, "maxX": 288.25, "maxY": 556.5}, "class_id": 0, "box_caption": "General trash 0.014", "scores": {"class_score": 0.01352691650390625}, "domain": "pixel"}, {"position": {"minX": 445.5, "minY": 63.75, "maxX": 626.5, "maxY": 393.75}, "class_id": 1, "box_caption": "Paper 0.013", "scores": {"class_score": 0.01331329345703125}, "domain": "pixel"}, {"position": {"minX": 238.25, "minY": 993.0, "maxX": 331.75, "maxY": 1039.0}, "class_id": 1, "box_caption": "Paper 0.013", "scores": {"class_score": 0.013214111328125}, "domain": "pixel"}, {"position": {"minX": 308.0, "minY": 124.6875, "maxX": 406.5, "maxY": 161.75}, "class_id": 1, "box_caption": "Paper 0.013", "scores": {"class_score": 0.01312255859375}, "domain": "pixel"}, {"position": {"minX": 228.75, "minY": 980.0, "maxX": 361.25, "maxY": 1041.0}, "class_id": 7, "box_caption": "Plastic bag 0.013", "scores": {"class_score": 0.01306915283203125}, "domain": "pixel"}, {"position": {"minX": 453.5, "minY": 95.9375, "maxX": 560.0, "maxY": 140.125}, "class_id": 1, "box_caption": "Paper 0.013", "scores": {"class_score": 0.01294708251953125}, "domain": "pixel"}, {"position": {"minX": 267.75, "minY": 521.5, "maxX": 404.75, "maxY": 639.5}, "class_id": 0, "box_caption": "General trash 0.013", "scores": {"class_score": 0.0128631591796875}, "domain": "pixel"}, {"position": {"minX": 346.5, "minY": 158.5, "maxX": 573.0, "maxY": 280.5}, "class_id": 0, "box_caption": "General trash 0.013", "scores": {"class_score": 0.01284027099609375}, "domain": "pixel"}, {"position": {"minX": 646.5, "minY": 246.0, "maxX": 729.5, "maxY": 322.0}, "class_id": 0, "box_caption": "General trash 0.013", "scores": {"class_score": 0.0128173828125}, "domain": "pixel"}, {"position": {"minX": 285.0, "minY": 148.0, "maxX": 457.0, "maxY": 286.0}, "class_id": 1, "box_caption": "Paper 0.013", "scores": {"class_score": 0.01273345947265625}, "domain": "pixel"}, {"position": {"minX": 240.5, "minY": 63.625, "maxX": 348.0, "maxY": 169.375}, "class_id": 1, "box_caption": "Paper 0.013", "scores": {"class_score": 0.01271820068359375}, "domain": "pixel"}, {"position": {"minX": 433.75, "minY": 78.75, "maxX": 593.5, "maxY": 146.25}, "class_id": 0, "box_caption": "General trash 0.013", "scores": {"class_score": 0.01261138916015625}, "domain": "pixel"}, {"position": {"minX": 531.0, "minY": 102.625, "maxX": 604.0, "maxY": 385.0}, "class_id": 1, "box_caption": "Paper 0.013", "scores": {"class_score": 0.01259613037109375}, "domain": "pixel"}, {"position": {"minX": 671.5, "minY": 948.5, "maxX": 1042.0, "maxY": 1041.0}, "class_id": 1, "box_caption": "Paper 0.012", "scores": {"class_score": 0.012481689453125}, "domain": "pixel"}, {"position": {"minX": 345.0, "minY": 99.5, "maxX": 589.0, "maxY": 285.0}, "class_id": 7, "box_caption": "Plastic bag 0.012", "scores": {"class_score": 0.0122222900390625}, "domain": "pixel"}, {"position": {"minX": 601.0, "minY": 99.125, "maxX": 629.0, "maxY": 161.125}, "class_id": 7, "box_caption": "Plastic bag 0.012", "scores": {"class_score": 0.01207733154296875}, "domain": "pixel"}, {"position": {"minX": 540.5, "minY": 122.375, "maxX": 577.5, "maxY": 147.625}, "class_id": 1, "box_caption": "Paper 0.012", "scores": {"class_score": 0.0119781494140625}, "domain": "pixel"}, {"position": {"minX": 557.5, "minY": 83.875, "maxX": 628.5, "maxY": 207.625}, "class_id": 1, "box_caption": "Paper 0.012", "scores": {"class_score": 0.0119476318359375}, "domain": "pixel"}, {"position": {"minX": 493.0, "minY": 16.53125, "maxX": 646.0, "maxY": 144.375}, "class_id": 1, "box_caption": "Paper 0.012", "scores": {"class_score": 0.01190185546875}, "domain": "pixel"}, {"position": {"minX": 264.25, "minY": 541.5, "maxX": 328.25, "maxY": 583.5}, "class_id": 0, "box_caption": "General trash 0.012", "scores": {"class_score": 0.0117950439453125}, "domain": "pixel"}, {"position": {"minX": 233.25, "minY": 382.25, "maxX": 634.0, "maxY": 637.0}, "class_id": 1, "box_caption": "Paper 0.012", "scores": {"class_score": 0.01177215576171875}, "domain": "pixel"}, {"position": {"minX": 257.5, "minY": 407.5, "maxX": 482.5, "maxY": 639.5}, "class_id": 6, "box_caption": "Styrofoam 0.012", "scores": {"class_score": 0.011749267578125}, "domain": "pixel"}, {"position": {"minX": 233.25, "minY": 382.25, "maxX": 634.0, "maxY": 637.0}, "class_id": 5, "box_caption": "Plastic 0.012", "scores": {"class_score": 0.01168060302734375}, "domain": "pixel"}, {"position": {"minX": 255.125, "minY": 527.0, "maxX": 291.0, "maxY": 566.0}, "class_id": 0, "box_caption": "General trash 0.011", "scores": {"class_score": 0.01137542724609375}, "domain": "pixel"}, {"position": {"minX": 417.25, "minY": 62.3125, "maxX": 528.0, "maxY": 136.5}, "class_id": 1, "box_caption": "Paper 0.011", "scores": {"class_score": 0.011322021484375}, "domain": "pixel"}, {"position": {"minX": 341.5, "minY": 136.125, "maxX": 396.5, "maxY": 159.125}, "class_id": 1, "box_caption": "Paper 0.011", "scores": {"class_score": 0.01120758056640625}, "domain": "pixel"}, {"position": {"minX": 646.0, "minY": 255.5, "maxX": 729.0, "maxY": 295.5}, "class_id": 1, "box_caption": "Paper 0.011", "scores": {"class_score": 0.01110076904296875}, "domain": "pixel"}, {"position": {"minX": 267.75, "minY": 147.5, "maxX": 304.75, "maxY": 175.0}, "class_id": 1, "box_caption": "Paper 0.011", "scores": {"class_score": 0.01105499267578125}, "domain": "pixel"}, {"position": {"minX": 128.75, "minY": 19.65625, "maxX": 155.0, "maxY": 106.125}, "class_id": 0, "box_caption": "General trash 0.011", "scores": {"class_score": 0.0109710693359375}, "domain": "pixel"}, {"position": {"minX": 300.5, "minY": 108.0, "maxX": 408.5, "maxY": 179.0}, "class_id": 1, "box_caption": "Paper 0.011", "scores": {"class_score": 0.010894775390625}, "domain": "pixel"}, {"position": {"minX": 457.5, "minY": 72.25, "maxX": 541.5, "maxY": 124.0}, "class_id": 1, "box_caption": "Paper 0.011", "scores": {"class_score": 0.01085662841796875}, "domain": "pixel"}, {"position": {"minX": 366.75, "minY": 388.0, "maxX": 543.5, "maxY": 620.5}, "class_id": 0, "box_caption": "General trash 0.011", "scores": {"class_score": 0.0107269287109375}, "domain": "pixel"}, {"position": {"minX": 376.5, "minY": 135.625, "maxX": 405.5, "maxY": 154.625}, "class_id": 7, "box_caption": "Plastic bag 0.011", "scores": {"class_score": 0.010711669921875}, "domain": "pixel"}, {"position": {"minX": 235.5, "minY": 946.0, "maxX": 382.5, "maxY": 1035.0}, "class_id": 4, "box_caption": "Glass 0.011", "scores": {"class_score": 0.0106658935546875}, "domain": "pixel"}, {"position": {"minX": 537.5, "minY": 10.25, "maxX": 677.5, "maxY": 407.5}, "class_id": 1, "box_caption": "Paper 0.011", "scores": {"class_score": 0.0106658935546875}, "domain": "pixel"}, {"position": {"minX": 279.75, "minY": 97.1875, "maxX": 538.0, "maxY": 277.75}, "class_id": 1, "box_caption": "Paper 0.011", "scores": {"class_score": 0.01058197021484375}, "domain": "pixel"}, {"position": {"minX": 365.0, "minY": 128.5, "maxX": 411.5, "maxY": 143.5}, "class_id": 1, "box_caption": "Paper 0.011", "scores": {"class_score": 0.01055145263671875}, "domain": "pixel"}, {"position": {"minX": 869.0, "minY": 1009.5, "maxX": 1038.0, "maxY": 1046.0}, "class_id": 2, "box_caption": "Paper pack 0.010", "scores": {"class_score": 0.01047515869140625}, "domain": "pixel"}, {"position": {"minX": 345.0, "minY": 108.6875, "maxX": 411.5, "maxY": 141.75}, "class_id": 1, "box_caption": "Paper 0.010", "scores": {"class_score": 0.01043701171875}, "domain": "pixel"}, {"position": {"minX": 497.75, "minY": 19.96875, "maxX": 604.0, "maxY": 113.75}, "class_id": 1, "box_caption": "Paper 0.010", "scores": {"class_score": 0.0104217529296875}, "domain": "pixel"}, {"position": {"minX": 775.0, "minY": 1005.0, "maxX": 1043.0, "maxY": 1047.0}, "class_id": 2, "box_caption": "Paper pack 0.010", "scores": {"class_score": 0.01035308837890625}, "domain": "pixel"}, {"position": {"minX": 947.0, "minY": 987.5, "maxX": 1040.0, "maxY": 1021.5}, "class_id": 1, "box_caption": "Paper 0.010", "scores": {"class_score": 0.01010894775390625}, "domain": "pixel"}, {"position": {"minX": 232.5, "minY": 974.5, "maxX": 422.5, "maxY": 1040.0}, "class_id": 5, "box_caption": "Plastic 0.010", "scores": {"class_score": 0.00991058349609375}, "domain": "pixel"}, {"position": {"minX": 208.625, "minY": 169.0, "maxX": 357.0, "maxY": 238.5}, "class_id": 1, "box_caption": "Paper 0.010", "scores": {"class_score": 0.00974273681640625}, "domain": "pixel"}, {"position": {"minX": 927.0, "minY": 1012.5, "maxX": 1015.0, "maxY": 1039.0}, "class_id": 1, "box_caption": "Paper 0.010", "scores": {"class_score": 0.00972747802734375}, "domain": "pixel"}, {"position": {"minX": 235.5, "minY": 946.0, "maxX": 382.5, "maxY": 1035.0}, "class_id": 5, "box_caption": "Plastic 0.010", "scores": {"class_score": 0.00972747802734375}, "domain": "pixel"}, {"position": {"minX": 237.75, "minY": 970.0, "maxX": 370.75, "maxY": 1035.0}, "class_id": 0, "box_caption": "General trash 0.010", "scores": {"class_score": 0.0096282958984375}, "domain": "pixel"}, {"position": {"minX": 608.5, "minY": 96.6875, "maxX": 627.5, "maxY": 144.125}, "class_id": 1, "box_caption": "Paper 0.010", "scores": {"class_score": 0.00958251953125}, "domain": "pixel"}, {"position": {"minX": 545.5, "minY": 49.1875, "maxX": 634.5, "maxY": 176.75}, "class_id": 1, "box_caption": "Paper 0.010", "scores": {"class_score": 0.0095367431640625}, "domain": "pixel"}, {"position": {"minX": 893.5, "minY": 979.5, "maxX": 1046.0, "maxY": 1027.0}, "class_id": 0, "box_caption": "General trash 0.009", "scores": {"class_score": 0.0094146728515625}, "domain": "pixel"}, {"position": {"minX": 364.0, "minY": 395.0, "maxX": 623.0, "maxY": 630.0}, "class_id": 6, "box_caption": "Styrofoam 0.009", "scores": {"class_score": 0.00940704345703125}, "domain": "pixel"}, {"position": {"minX": 295.0, "minY": 148.75, "maxX": 395.0, "maxY": 236.25}, "class_id": 1, "box_caption": "Paper 0.009", "scores": {"class_score": 0.00933837890625}, "domain": "pixel"}, {"position": {"minX": 582.0, "minY": 95.8125, "maxX": 631.0, "maxY": 181.0}, "class_id": 1, "box_caption": "Paper 0.009", "scores": {"class_score": 0.00914764404296875}, "domain": "pixel"}, {"position": {"minX": 290.75, "minY": 589.5, "maxX": 559.0, "maxY": 631.5}, "class_id": 0, "box_caption": "General trash 0.009", "scores": {"class_score": 0.00908660888671875}, "domain": "pixel"}, {"position": {"minX": 241.375, "minY": 500.5, "maxX": 344.75, "maxY": 582.5}, "class_id": 0, "box_caption": "General trash 0.009", "scores": {"class_score": 0.0090789794921875}, "domain": "pixel"}, {"position": {"minX": 216.75, "minY": 57.3125, "maxX": 377.75, "maxY": 176.25}, "class_id": 6, "box_caption": "Styrofoam 0.009", "scores": {"class_score": 0.00907135009765625}, "domain": "pixel"}, {"position": {"minX": 773.5, "minY": 962.0, "maxX": 1045.0, "maxY": 1038.0}, "class_id": 7, "box_caption": "Plastic bag 0.009", "scores": {"class_score": 0.009033203125}, "domain": "pixel"}, {"position": {"minX": 219.25, "minY": 57.40625, "maxX": 376.25, "maxY": 176.0}, "class_id": 5, "box_caption": "Plastic 0.009", "scores": {"class_score": 0.00897979736328125}, "domain": "pixel"}, {"position": {"minX": 344.25, "minY": 121.0, "maxX": 415.25, "maxY": 143.5}, "class_id": 1, "box_caption": "Paper 0.009", "scores": {"class_score": 0.00897216796875}, "domain": "pixel"}, {"position": {"minX": 349.5, "minY": 109.4375, "maxX": 611.5, "maxY": 335.75}, "class_id": 0, "box_caption": "General trash 0.009", "scores": {"class_score": 0.008819580078125}, "domain": "pixel"}, {"position": {"minX": 237.75, "minY": 369.25, "maxX": 1065.0, "maxY": 1052.0}, "class_id": 1, "box_caption": "Paper 0.009", "scores": {"class_score": 0.00872802734375}, "domain": "pixel"}, {"position": {"minX": 363.5, "minY": 32.875, "maxX": 515.0, "maxY": 109.5}, "class_id": 1, "box_caption": "Paper 0.009", "scores": {"class_score": 0.008514404296875}, "domain": "pixel"}, {"position": {"minX": 686.0, "minY": 994.0, "maxX": 1032.0, "maxY": 1042.0}, "class_id": 0, "box_caption": "General trash 0.009", "scores": {"class_score": 0.008514404296875}, "domain": "pixel"}, {"position": {"minX": 380.25, "minY": 602.5, "maxX": 414.75, "maxY": 636.5}, "class_id": 0, "box_caption": "General trash 0.008", "scores": {"class_score": 0.00849151611328125}, "domain": "pixel"}, {"position": {"minX": 530.5, "minY": 38.875, "maxX": 619.5, "maxY": 302.0}, "class_id": 1, "box_caption": "Paper 0.008", "scores": {"class_score": 0.00848388671875}, "domain": "pixel"}, {"position": {"minX": 381.75, "minY": 251.5, "maxX": 497.25, "maxY": 320.5}, "class_id": 5, "box_caption": "Plastic 0.008", "scores": {"class_score": 0.00846099853515625}, "domain": "pixel"}, {"position": {"minX": 962.0, "minY": 1013.5, "maxX": 1019.0, "maxY": 1040.0}, "class_id": 1, "box_caption": "Paper 0.008", "scores": {"class_score": 0.00838470458984375}, "domain": "pixel"}, {"position": {"minX": 986.5, "minY": 1013.0, "maxX": 1044.0, "maxY": 1043.0}, "class_id": 1, "box_caption": "Paper 0.008", "scores": {"class_score": 0.0083465576171875}, "domain": "pixel"}, {"position": {"minX": 275.5, "minY": 141.5, "maxX": 312.5, "maxY": 176.5}, "class_id": 1, "box_caption": "Paper 0.008", "scores": {"class_score": 0.00832366943359375}, "domain": "pixel"}, {"position": {"minX": 869.0, "minY": 1017.0, "maxX": 1043.0, "maxY": 1051.0}, "class_id": 1, "box_caption": "Paper 0.008", "scores": {"class_score": 0.00827789306640625}, "domain": "pixel"}, {"position": {"minX": 246.25, "minY": 528.0, "maxX": 300.75, "maxY": 573.0}, "class_id": 7, "box_caption": "Plastic bag 0.008", "scores": {"class_score": 0.00826263427734375}, "domain": "pixel"}, {"position": {"minX": 306.75, "minY": 533.0, "maxX": 434.25, "maxY": 641.0}, "class_id": 0, "box_caption": "General trash 0.008", "scores": {"class_score": 0.00811004638671875}, "domain": "pixel"}, {"position": {"minX": 343.0, "minY": 173.25, "maxX": 554.5, "maxY": 281.25}, "class_id": 7, "box_caption": "Plastic bag 0.008", "scores": {"class_score": 0.00800323486328125}, "domain": "pixel"}, {"position": {"minX": 915.0, "minY": 942.0, "maxX": 1042.0, "maxY": 1039.0}, "class_id": 1, "box_caption": "Paper 0.008", "scores": {"class_score": 0.00798797607421875}, "domain": "pixel"}, {"position": {"minX": 606.0, "minY": 75.625, "maxX": 626.0, "maxY": 149.25}, "class_id": 1, "box_caption": "Paper 0.008", "scores": {"class_score": 0.00797271728515625}, "domain": "pixel"}, {"position": {"minX": 601.0, "minY": 99.1875, "maxX": 627.0, "maxY": 160.125}, "class_id": 0, "box_caption": "General trash 0.008", "scores": {"class_score": 0.007965087890625}, "domain": "pixel"}, {"position": {"minX": 361.0, "minY": 88.1875, "maxX": 512.5, "maxY": 223.5}, "class_id": 1, "box_caption": "Paper 0.008", "scores": {"class_score": 0.00792694091796875}, "domain": "pixel"}, {"position": {"minX": 530.5, "minY": 42.0, "maxX": 696.5, "maxY": 425.5}, "class_id": 0, "box_caption": "General trash 0.008", "scores": {"class_score": 0.0078277587890625}, "domain": "pixel"}, {"position": {"minX": 332.0, "minY": 82.8125, "maxX": 376.0, "maxY": 130.625}, "class_id": 1, "box_caption": "Paper 0.008", "scores": {"class_score": 0.007785797119140625}, "domain": "pixel"}, {"position": {"minX": 217.0, "minY": 56.8125, "maxX": 378.5, "maxY": 176.75}, "class_id": 3, "box_caption": "Metal 0.008", "scores": {"class_score": 0.007785797119140625}, "domain": "pixel"}, {"position": {"minX": 572.5, "minY": 125.3125, "maxX": 590.5, "maxY": 150.75}, "class_id": 1, "box_caption": "Paper 0.008", "scores": {"class_score": 0.007720947265625}, "domain": "pixel"}, {"position": {"minX": 298.75, "minY": 90.8125, "maxX": 381.25, "maxY": 157.25}, "class_id": 1, "box_caption": "Paper 0.008", "scores": {"class_score": 0.0076446533203125}, "domain": "pixel"}, {"position": {"minX": 323.0, "minY": 402.75, "maxX": 468.5, "maxY": 630.0}, "class_id": 0, "box_caption": "General trash 0.008", "scores": {"class_score": 0.007587432861328125}, "domain": "pixel"}, {"position": {"minX": 566.5, "minY": 112.75, "maxX": 592.5, "maxY": 151.25}, "class_id": 1, "box_caption": "Paper 0.008", "scores": {"class_score": 0.007518768310546875}, "domain": "pixel"}, {"position": {"minX": 373.75, "minY": 133.25, "maxX": 409.25, "maxY": 153.0}, "class_id": 0, "box_caption": "General trash 0.008", "scores": {"class_score": 0.007511138916015625}, "domain": "pixel"}, {"position": {"minX": 471.0, "minY": 77.625, "maxX": 499.0, "maxY": 101.25}, "class_id": 1, "box_caption": "Paper 0.007", "scores": {"class_score": 0.00746917724609375}, "domain": "pixel"}, {"position": {"minX": 232.75, "minY": 394.5, "maxX": 518.0, "maxY": 611.0}, "class_id": 0, "box_caption": "General trash 0.007", "scores": {"class_score": 0.0074310302734375}, "domain": "pixel"}, {"position": {"minX": 335.75, "minY": 91.25, "maxX": 391.75, "maxY": 141.5}, "class_id": 1, "box_caption": "Paper 0.007", "scores": {"class_score": 0.007396697998046875}, "domain": "pixel"}, {"position": {"minX": 323.5, "minY": 131.75, "maxX": 360.5, "maxY": 158.75}, "class_id": 0, "box_caption": "General trash 0.007", "scores": {"class_score": 0.00734710693359375}, "domain": "pixel"}, {"position": {"minX": 394.25, "minY": 606.5, "maxX": 421.25, "maxY": 628.5}, "class_id": 0, "box_caption": "General trash 0.007", "scores": {"class_score": 0.00731658935546875}, "domain": "pixel"}, {"position": {"minX": 237.875, "minY": 945.5, "maxX": 360.0, "maxY": 1038.0}, "class_id": 7, "box_caption": "Plastic bag 0.007", "scores": {"class_score": 0.007213592529296875}, "domain": "pixel"}, {"position": {"minX": 482.75, "minY": 26.46875, "maxX": 588.0, "maxY": 137.25}, "class_id": 1, "box_caption": "Paper 0.007", "scores": {"class_score": 0.007205963134765625}, "domain": "pixel"}, {"position": {"minX": 311.75, "minY": 129.875, "maxX": 370.75, "maxY": 160.375}, "class_id": 7, "box_caption": "Plastic bag 0.007", "scores": {"class_score": 0.0070953369140625}, "domain": "pixel"}, {"position": {"minX": 363.25, "minY": 258.75, "maxX": 458.75, "maxY": 321.75}, "class_id": 7, "box_caption": "Plastic bag 0.007", "scores": {"class_score": 0.007030487060546875}, "domain": "pixel"}, {"position": {"minX": 325.0, "minY": 73.3125, "maxX": 380.0, "maxY": 141.75}, "class_id": 1, "box_caption": "Paper 0.007", "scores": {"class_score": 0.00701904296875}, "domain": "pixel"}, {"position": {"minX": 527.0, "minY": 138.875, "maxX": 902.0, "maxY": 538.0}, "class_id": 6, "box_caption": "Styrofoam 0.007", "scores": {"class_score": 0.007007598876953125}, "domain": "pixel"}, {"position": {"minX": 471.75, "minY": 82.875, "maxX": 500.25, "maxY": 108.0}, "class_id": 1, "box_caption": "Paper 0.007", "scores": {"class_score": 0.0067596435546875}, "domain": "pixel"}, {"position": {"minX": 561.0, "minY": 110.875, "maxX": 593.0, "maxY": 139.875}, "class_id": 1, "box_caption": "Paper 0.007", "scores": {"class_score": 0.006732940673828125}, "domain": "pixel"}, {"position": {"minX": 238.125, "minY": 57.09375, "maxX": 378.0, "maxY": 124.875}, "class_id": 1, "box_caption": "Paper 0.007", "scores": {"class_score": 0.006717681884765625}, "domain": "pixel"}, {"position": {"minX": 263.5, "minY": 137.75, "maxX": 305.0, "maxY": 176.25}, "class_id": 0, "box_caption": "General trash 0.007", "scores": {"class_score": 0.006710052490234375}, "domain": "pixel"}, {"position": {"minX": 883.5, "minY": 1015.0, "maxX": 998.5, "maxY": 1043.0}, "class_id": 7, "box_caption": "Plastic bag 0.007", "scores": {"class_score": 0.006649017333984375}, "domain": "pixel"}, {"position": {"minX": 234.25, "minY": 103.625, "maxX": 384.25, "maxY": 190.375}, "class_id": 1, "box_caption": "Paper 0.007", "scores": {"class_score": 0.00664520263671875}, "domain": "pixel"}, {"position": {"minX": 439.0, "minY": 78.75, "maxX": 540.0, "maxY": 140.25}, "class_id": 0, "box_caption": "General trash 0.007", "scores": {"class_score": 0.006633758544921875}, "domain": "pixel"}, {"position": {"minX": 352.5, "minY": 137.875, "maxX": 404.5, "maxY": 162.375}, "class_id": 1, "box_caption": "Paper 0.007", "scores": {"class_score": 0.0066070556640625}, "domain": "pixel"}, {"position": {"minX": 752.5, "minY": 996.5, "maxX": 1040.0, "maxY": 1045.0}, "class_id": 5, "box_caption": "Plastic 0.007", "scores": {"class_score": 0.006542205810546875}, "domain": "pixel"}, {"position": {"minX": 523.0, "minY": 158.0, "maxX": 588.0, "maxY": 397.0}, "class_id": 1, "box_caption": "Paper 0.007", "scores": {"class_score": 0.006504058837890625}, "domain": "pixel"}, {"position": {"minX": 247.5, "minY": 153.625, "maxX": 280.5, "maxY": 175.875}, "class_id": 7, "box_caption": "Plastic bag 0.006", "scores": {"class_score": 0.006450653076171875}, "domain": "pixel"}, {"position": {"minX": 177.5, "minY": 450.5, "maxX": 644.5, "maxY": 776.5}, "class_id": 0, "box_caption": "General trash 0.006", "scores": {"class_score": 0.006351470947265625}, "domain": "pixel"}, {"position": {"minX": 539.0, "minY": 104.6875, "maxX": 596.0, "maxY": 179.0}, "class_id": 1, "box_caption": "Paper 0.006", "scores": {"class_score": 0.00634765625}, "domain": "pixel"}, {"position": {"minX": 775.0, "minY": 1005.0, "maxX": 1043.0, "maxY": 1047.0}, "class_id": 6, "box_caption": "Styrofoam 0.006", "scores": {"class_score": 0.00632476806640625}, "domain": "pixel"}, {"position": {"minX": 872.0, "minY": 1009.0, "maxX": 1039.0, "maxY": 1043.0}, "class_id": 5, "box_caption": "Plastic 0.006", "scores": {"class_score": 0.0063018798828125}, "domain": "pixel"}, {"position": {"minX": 235.0, "minY": 959.0, "maxX": 374.5, "maxY": 1040.0}, "class_id": 9, "box_caption": "Clothing 0.006", "scores": {"class_score": 0.00628662109375}, "domain": "pixel"}, {"position": {"minX": 343.0, "minY": 190.125, "maxX": 543.5, "maxY": 310.75}, "class_id": 0, "box_caption": "General trash 0.006", "scores": {"class_score": 0.0062713623046875}, "domain": "pixel"}, {"position": {"minX": 860.5, "minY": 978.5, "maxX": 1047.0, "maxY": 1028.0}, "class_id": 7, "box_caption": "Plastic bag 0.006", "scores": {"class_score": 0.006259918212890625}, "domain": "pixel"}, {"position": {"minX": 398.5, "minY": 262.75, "maxX": 543.0, "maxY": 316.75}, "class_id": 7, "box_caption": "Plastic bag 0.006", "scores": {"class_score": 0.006256103515625}, "domain": "pixel"}, {"position": {"minX": 573.0, "minY": 110.625, "maxX": 598.0, "maxY": 154.375}, "class_id": 1, "box_caption": "Paper 0.006", "scores": {"class_score": 0.006160736083984375}, "domain": "pixel"}, {"position": {"minX": 451.5, "minY": 77.125, "maxX": 510.0, "maxY": 110.0}, "class_id": 0, "box_caption": "General trash 0.006", "scores": {"class_score": 0.006160736083984375}, "domain": "pixel"}, {"position": {"minX": 372.0, "minY": 607.0, "maxX": 411.5, "maxY": 640.0}, "class_id": 0, "box_caption": "General trash 0.006", "scores": {"class_score": 0.006145477294921875}, "domain": "pixel"}, {"position": {"minX": 883.5, "minY": 1015.0, "maxX": 998.5, "maxY": 1043.0}, "class_id": 0, "box_caption": "General trash 0.006", "scores": {"class_score": 0.00614166259765625}, "domain": "pixel"}, {"position": {"minX": 678.0, "minY": 257.0, "maxX": 731.0, "maxY": 291.5}, "class_id": 0, "box_caption": "General trash 0.006", "scores": {"class_score": 0.006137847900390625}, "domain": "pixel"}, {"position": {"minX": 581.5, "minY": 195.5, "maxX": 599.5, "maxY": 227.0}, "class_id": 1, "box_caption": "Paper 0.006", "scores": {"class_score": 0.006130218505859375}, "domain": "pixel"}, {"position": {"minX": 314.0, "minY": 136.0, "maxX": 402.5, "maxY": 202.5}, "class_id": 1, "box_caption": "Paper 0.006", "scores": {"class_score": 0.006122589111328125}, "domain": "pixel"}, {"position": {"minX": 240.125, "minY": 993.5, "maxX": 315.0, "maxY": 1038.0}, "class_id": 4, "box_caption": "Glass 0.006", "scores": {"class_score": 0.00611114501953125}, "domain": "pixel"}, {"position": {"minX": 459.5, "minY": 18.15625, "maxX": 615.5, "maxY": 131.125}, "class_id": 0, "box_caption": "General trash 0.006", "scores": {"class_score": 0.00608062744140625}, "domain": "pixel"}, {"position": {"minX": 309.75, "minY": 133.0, "maxX": 385.25, "maxY": 168.5}, "class_id": 1, "box_caption": "Paper 0.006", "scores": {"class_score": 0.00603485107421875}, "domain": "pixel"}, {"position": {"minX": 280.0, "minY": 142.25, "maxX": 307.0, "maxY": 176.75}, "class_id": 0, "box_caption": "General trash 0.006", "scores": {"class_score": 0.006031036376953125}, "domain": "pixel"}, {"position": {"minX": 467.5, "minY": 572.0, "maxX": 498.0, "maxY": 597.0}, "class_id": 0, "box_caption": "General trash 0.006", "scores": {"class_score": 0.00592803955078125}, "domain": "pixel"}, {"position": {"minX": 688.5, "minY": 994.5, "maxX": 961.5, "maxY": 1040.0}, "class_id": 1, "box_caption": "Paper 0.006", "scores": {"class_score": 0.005916595458984375}, "domain": "pixel"}, {"position": {"minX": 232.0, "minY": 430.5, "maxX": 385.0, "maxY": 580.5}, "class_id": 0, "box_caption": "General trash 0.006", "scores": {"class_score": 0.005878448486328125}, "domain": "pixel"}, {"position": {"minX": 237.25, "minY": 991.5, "maxX": 360.25, "maxY": 1038.0}, "class_id": 8, "box_caption": "Battery 0.006", "scores": {"class_score": 0.00586700439453125}, "domain": "pixel"}, {"position": {"minX": 24.625, "minY": 14.09375, "maxX": 245.125, "maxY": 108.875}, "class_id": 0, "box_caption": "General trash 0.006", "scores": {"class_score": 0.00582122802734375}, "domain": "pixel"}, {"position": {"minX": 337.25, "minY": 389.0, "maxX": 511.75, "maxY": 623.5}, "class_id": 6, "box_caption": "Styrofoam 0.006", "scores": {"class_score": 0.005809783935546875}, "domain": "pixel"}, {"position": {"minX": 669.0, "minY": 261.25, "maxX": 738.0, "maxY": 296.75}, "class_id": 0, "box_caption": "General trash 0.006", "scores": {"class_score": 0.005786895751953125}, "domain": "pixel"}, {"position": {"minX": 238.75, "minY": 992.0, "maxX": 362.75, "maxY": 1039.0}, "class_id": 2, "box_caption": "Paper pack 0.006", "scores": {"class_score": 0.00572967529296875}, "domain": "pixel"}, {"position": {"minX": 239.75, "minY": 519.0, "maxX": 321.25, "maxY": 570.0}, "class_id": 0, "box_caption": "General trash 0.006", "scores": {"class_score": 0.005718231201171875}, "domain": "pixel"}, {"position": {"minX": 240.125, "minY": 993.5, "maxX": 315.0, "maxY": 1038.0}, "class_id": 9, "box_caption": "Clothing 0.006", "scores": {"class_score": 0.005702972412109375}, "domain": "pixel"}, {"position": {"minX": 850.0, "minY": 958.5, "maxX": 1054.0, "maxY": 1026.0}, "class_id": 1, "box_caption": "Paper 0.006", "scores": {"class_score": 0.005695343017578125}, "domain": "pixel"}, {"position": {"minX": 575.5, "minY": 116.5, "maxX": 605.5, "maxY": 286.5}, "class_id": 1, "box_caption": "Paper 0.006", "scores": {"class_score": 0.005672454833984375}, "domain": "pixel"}, {"position": {"minX": 901.0, "minY": 1024.0, "maxX": 990.0, "maxY": 1040.0}, "class_id": 1, "box_caption": "Paper 0.006", "scores": {"class_score": 0.005649566650390625}, "domain": "pixel"}, {"position": {"minX": 865.5, "minY": 997.0, "maxX": 1044.0, "maxY": 1053.0}, "class_id": 1, "box_caption": "Paper 0.006", "scores": {"class_score": 0.00563812255859375}, "domain": "pixel"}, {"position": {"minX": 225.0, "minY": 940.0, "maxX": 427.5, "maxY": 1038.0}, "class_id": 0, "box_caption": "General trash 0.005", "scores": {"class_score": 0.005474090576171875}, "domain": "pixel"}, {"position": {"minX": 312.0, "minY": 228.25, "maxX": 401.5, "maxY": 287.25}, "class_id": 6, "box_caption": "Styrofoam 0.005", "scores": {"class_score": 0.005462646484375}, "domain": "pixel"}, {"position": {"minX": 644.5, "minY": 255.625, "maxX": 729.5, "maxY": 297.5}, "class_id": 5, "box_caption": "Plastic 0.005", "scores": {"class_score": 0.005443572998046875}, "domain": "pixel"}, {"position": {"minX": 243.0, "minY": 993.0, "maxX": 299.5, "maxY": 1037.0}, "class_id": 7, "box_caption": "Plastic bag 0.005", "scores": {"class_score": 0.005340576171875}, "domain": "pixel"}, {"position": {"minX": 236.0, "minY": 419.25, "maxX": 430.0, "maxY": 586.0}, "class_id": 6, "box_caption": "Styrofoam 0.005", "scores": {"class_score": 0.005336761474609375}, "domain": "pixel"}, {"position": {"minX": 531.5, "minY": 172.25, "maxX": 594.5, "maxY": 349.25}, "class_id": 1, "box_caption": "Paper 0.005", "scores": {"class_score": 0.0053253173828125}, "domain": "pixel"}, {"position": {"minX": 244.375, "minY": 529.0, "maxX": 292.5, "maxY": 568.0}, "class_id": 5, "box_caption": "Plastic 0.005", "scores": {"class_score": 0.005306243896484375}, "domain": "pixel"}, {"position": {"minX": 200.625, "minY": 152.125, "maxX": 418.5, "maxY": 264.25}, "class_id": 1, "box_caption": "Paper 0.005", "scores": {"class_score": 0.005275726318359375}, "domain": "pixel"}, {"position": {"minX": 284.5, "minY": 998.0, "maxX": 365.0, "maxY": 1039.0}, "class_id": 4, "box_caption": "Glass 0.005", "scores": {"class_score": 0.00524139404296875}, "domain": "pixel"}, {"position": {"minX": 312.75, "minY": 228.625, "maxX": 403.75, "maxY": 286.5}, "class_id": 2, "box_caption": "Paper pack 0.005", "scores": {"class_score": 0.00519561767578125}, "domain": "pixel"}, {"position": {"minX": 261.25, "minY": 994.0, "maxX": 410.25, "maxY": 1039.0}, "class_id": 4, "box_caption": "Glass 0.005", "scores": {"class_score": 0.005123138427734375}, "domain": "pixel"}, {"position": {"minX": 572.5, "minY": 229.0, "maxX": 788.5, "maxY": 440.5}, "class_id": 6, "box_caption": "Styrofoam 0.005", "scores": {"class_score": 0.005092620849609375}, "domain": "pixel"}, {"position": {"minX": 937.0, "minY": 1012.0, "maxX": 1032.0, "maxY": 1040.0}, "class_id": 0, "box_caption": "General trash 0.005", "scores": {"class_score": 0.00508880615234375}, "domain": "pixel"}, {"position": {"minX": 501.0, "minY": 62.75, "maxX": 592.0, "maxY": 144.625}, "class_id": 1, "box_caption": "Paper 0.005", "scores": {"class_score": 0.005031585693359375}, "domain": "pixel"}, {"position": {"minX": 489.25, "minY": 105.125, "maxX": 585.0, "maxY": 149.25}, "class_id": 1, "box_caption": "Paper 0.005", "scores": {"class_score": 0.005023956298828125}, "domain": "pixel"}, {"position": {"minX": 376.25, "minY": 136.25, "maxX": 414.25, "maxY": 157.0}, "class_id": 1, "box_caption": "Paper 0.005", "scores": {"class_score": 0.005016326904296875}, "domain": "pixel"}, {"position": {"minX": 398.0, "minY": 596.0, "maxX": 441.0, "maxY": 633.0}, "class_id": 0, "box_caption": "General trash 0.005", "scores": {"class_score": 0.005016326904296875}, "domain": "pixel"}, {"position": {"minX": 219.25, "minY": 105.375, "maxX": 293.75, "maxY": 173.875}, "class_id": 1, "box_caption": "Paper 0.005", "scores": {"class_score": 0.005001068115234375}, "domain": "pixel"}, {"position": {"minX": 585.5, "minY": 233.375, "maxX": 737.5, "maxY": 392.0}, "class_id": 0, "box_caption": "General trash 0.005", "scores": {"class_score": 0.0049591064453125}, "domain": "pixel"}, {"position": {"minX": 311.5, "minY": 562.5, "maxX": 401.0, "maxY": 636.5}, "class_id": 0, "box_caption": "General trash 0.005", "scores": {"class_score": 0.004940032958984375}, "domain": "pixel"}, {"position": {"minX": 247.25, "minY": 124.125, "maxX": 320.75, "maxY": 184.625}, "class_id": 1, "box_caption": "Paper 0.005", "scores": {"class_score": 0.004940032958984375}, "domain": "pixel"}, {"position": {"minX": 209.0, "minY": 140.5, "maxX": 401.0, "maxY": 235.25}, "class_id": 0, "box_caption": "General trash 0.005", "scores": {"class_score": 0.004913330078125}, "domain": "pixel"}, {"position": {"minX": 756.0, "minY": 1009.0, "maxX": 890.0, "maxY": 1041.0}, "class_id": 1, "box_caption": "Paper 0.005", "scores": {"class_score": 0.00489044189453125}, "domain": "pixel"}, {"position": {"minX": 543.5, "minY": 13.4296875, "maxX": 619.5, "maxY": 38.5}, "class_id": 1, "box_caption": "Paper 0.005", "scores": {"class_score": 0.004878997802734375}, "domain": "pixel"}, {"position": {"minX": 296.0, "minY": 193.125, "maxX": 423.0, "maxY": 301.5}, "class_id": 1, "box_caption": "Paper 0.005", "scores": {"class_score": 0.00487518310546875}, "domain": "pixel"}, {"position": {"minX": 467.0, "minY": 79.75, "maxX": 516.5, "maxY": 120.375}, "class_id": 1, "box_caption": "Paper 0.005", "scores": {"class_score": 0.004871368408203125}, "domain": "pixel"}, {"position": {"minX": 380.25, "minY": 214.75, "maxX": 562.0, "maxY": 314.75}, "class_id": 0, "box_caption": "General trash 0.005", "scores": {"class_score": 0.004852294921875}, "domain": "pixel"}, {"position": {"minX": 919.0, "minY": 992.5, "maxX": 1043.0, "maxY": 1015.5}, "class_id": 1, "box_caption": "Paper 0.005", "scores": {"class_score": 0.004848480224609375}, "domain": "pixel"}, {"position": {"minX": 460.5, "minY": 18.46875, "maxX": 578.5, "maxY": 105.25}, "class_id": 1, "box_caption": "Paper 0.005", "scores": {"class_score": 0.00484466552734375}, "domain": "pixel"}, {"position": {"minX": 839.0, "minY": 935.5, "maxX": 1044.0, "maxY": 1042.0}, "class_id": 1, "box_caption": "Paper 0.005", "scores": {"class_score": 0.00482177734375}, "domain": "pixel"}, {"position": {"minX": 439.75, "minY": 92.0, "maxX": 493.25, "maxY": 114.0}, "class_id": 1, "box_caption": "Paper 0.005", "scores": {"class_score": 0.00478363037109375}, "domain": "pixel"}], "class_labels": {"0": "General trash", "1": "Paper", "2": "Paper pack", "3": "Metal", "4": "Glass", "5": "Plastic", "6": "Styrofoam", "7": "Plastic bag", "8": "Battery", "9": "Clothing"}}