{"box_data": [{"position": {"minX": 88.0, "minY": 347.75, "maxX": 716.5, "maxY": 1011.0}, "class_id": 9, "box_caption": "Clothing 0.236", "scores": {"class_score": 0.2357177734375}, "domain": "pixel"}, {"position": {"minX": 286.0, "minY": 171.5, "maxX": 659.5, "maxY": 427.5}, "class_id": 6, "box_caption": "Styrofoam 0.111", "scores": {"class_score": 0.11065673828125}, "domain": "pixel"}, {"position": {"minX": 93.0, "minY": 195.25, "maxX": 705.5, "maxY": 936.0}, "class_id": 5, "box_caption": "Plastic 0.060", "scores": {"class_score": 0.06048583984375}, "domain": "pixel"}, {"position": {"minX": 735.5, "minY": 735.5, "maxX": 928.5, "maxY": 1036.0}, "class_id": 0, "box_caption": "General trash 0.048", "scores": {"class_score": 0.048248291015625}, "domain": "pixel"}, {"position": {"minX": 88.0, "minY": 347.75, "maxX": 716.5, "maxY": 1011.0}, "class_id": 0, "box_caption": "General trash 0.037", "scores": {"class_score": 0.0367431640625}, "domain": "pixel"}, {"position": {"minX": 191.75, "minY": 806.0, "maxX": 609.0, "maxY": 999.0}, "class_id": 9, "box_caption": "Clothing 0.034", "scores": {"class_score": 0.03387451171875}, "domain": "pixel"}, {"position": {"minX": 51.1875, "minY": 673.5, "maxX": 153.0, "maxY": 871.5}, "class_id": 7, "box_caption": "Plastic bag 0.031", "scores": {"class_score": 0.0308685302734375}, "domain": "pixel"}, {"position": {"minX": 276.75, "minY": 100.375, "maxX": 663.0, "maxY": 554.5}, "class_id": 6, "box_caption": "Styrofoam 0.030", "scores": {"class_score": 0.030303955078125}, "domain": "pixel"}, {"position": {"minX": 731.0, "minY": 735.0, "maxX": 930.0, "maxY": 1038.0}, "class_id": 7, "box_caption": "Plastic bag 0.027", "scores": {"class_score": 0.027069091796875}, "domain": "pixel"}, {"position": {"minX": 93.0, "minY": 195.25, "maxX": 705.5, "maxY": 936.0}, "class_id": 1, "box_caption": "Paper 0.023", "scores": {"class_score": 0.0229339599609375}, "domain": "pixel"}, {"position": {"minX": 51.1875, "minY": 673.5, "maxX": 153.0, "maxY": 871.5}, "class_id": 0, "box_caption": "General trash 0.017", "scores": {"class_score": 0.01654052734375}, "domain": "pixel"}, {"position": {"minX": 514.0, "minY": 20.1875, "maxX": 1055.0, "maxY": 249.0}, "class_id": 0, "box_caption": "General trash 0.011", "scores": {"class_score": 0.0109100341796875}, "domain": "pixel"}, {"position": {"minX": 93.0, "minY": 195.25, "maxX": 705.5, "maxY": 936.0}, "class_id": 6, "box_caption": "Styrofoam 0.010", "scores": {"class_score": 0.00963592529296875}, "domain": "pixel"}, {"position": {"minX": 191.75, "minY": 806.0, "maxX": 609.0, "maxY": 999.0}, "class_id": 0, "box_caption": "General trash 0.009", "scores": {"class_score": 0.00910186767578125}, "domain": "pixel"}, {"position": {"minX": 27.15625, "minY": 632.0, "maxX": 145.375, "maxY": 886.0}, "class_id": 0, "box_caption": "General trash 0.009", "scores": {"class_score": 0.00855255126953125}, "domain": "pixel"}, {"position": {"minX": 286.0, "minY": 171.5, "maxX": 659.5, "maxY": 427.5}, "class_id": 1, "box_caption": "Paper 0.008", "scores": {"class_score": 0.0083770751953125}, "domain": "pixel"}, {"position": {"minX": 93.0, "minY": 195.25, "maxX": 705.5, "maxY": 936.0}, "class_id": 3, "box_caption": "Metal 0.008", "scores": {"class_score": 0.00812530517578125}, "domain": "pixel"}, {"position": {"minX": 14.375, "minY": 15.296875, "maxX": 60.375, "maxY": 54.375}, "class_id": 0, "box_caption": "General trash 0.008", "scores": {"class_score": 0.007625579833984375}, "domain": "pixel"}, {"position": {"minX": 286.0, "minY": 171.5, "maxX": 659.5, "maxY": 427.5}, "class_id": 0, "box_caption": "General trash 0.007", "scores": {"class_score": 0.006999969482421875}, "domain": "pixel"}, {"position": {"minX": 139.0, "minY": 20.0, "maxX": 681.5, "maxY": 586.0}, "class_id": 6, "box_caption": "Styrofoam 0.007", "scores": {"class_score": 0.00677490234375}, "domain": "pixel"}, {"position": {"minX": 589.0, "minY": 915.5, "maxX": 705.0, "maxY": 1039.0}, "class_id": 5, "box_caption": "Plastic 0.007", "scores": {"class_score": 0.0067291259765625}, "domain": "pixel"}, {"position": {"minX": 27.15625, "minY": 632.0, "maxX": 145.375, "maxY": 886.0}, "class_id": 7, "box_caption": "Plastic bag 0.006", "scores": {"class_score": 0.006160736083984375}, "domain": "pixel"}, {"position": {"minX": 121.5, "minY": 104.5, "maxX": 681.5, "maxY": 905.5}, "class_id": 9, "box_caption": "Clothing 0.005", "scores": {"class_score": 0.0052032470703125}, "domain": "pixel"}, {"position": {"minX": 93.0, "minY": 195.25, "maxX": 705.5, "maxY": 936.0}, "class_id": 2, "box_caption": "Paper pack 0.005", "scores": {"class_score": 0.005031585693359375}, "domain": "pixel"}, {"position": {"minX": 578.0, "minY": 738.0, "maxX": 941.0, "maxY": 1053.0}, "class_id": 0, "box_caption": "General trash 0.005", "scores": {"class_score": 0.004756927490234375}, "domain": "pixel"}, {"position": {"minX": 93.0, "minY": 195.25, "maxX": 705.5, "maxY": 936.0}, "class_id": 7, "box_caption": "Plastic bag 0.005", "scores": {"class_score": 0.004695892333984375}, "domain": "pixel"}, {"position": {"minX": 41.0, "minY": 658.0, "maxX": 197.125, "maxY": 893.0}, "class_id": 7, "box_caption": "Plastic bag 0.005", "scores": {"class_score": 0.004512786865234375}, "domain": "pixel"}, {"position": {"minX": 41.0, "minY": 658.0, "maxX": 197.125, "maxY": 893.0}, "class_id": 0, "box_caption": "General trash 0.004", "scores": {"class_score": 0.0042266845703125}, "domain": "pixel"}, {"position": {"minX": 345.25, "minY": 15.125, "maxX": 987.0, "maxY": 162.875}, "class_id": 7, "box_caption": "Plastic bag 0.004", "scores": {"class_score": 0.003936767578125}, "domain": "pixel"}, {"position": {"minX": 93.0, "minY": 195.25, "maxX": 705.5, "maxY": 936.0}, "class_id": 4, "box_caption": "Glass 0.004", "scores": {"class_score": 0.003849029541015625}, "domain": "pixel"}, {"position": {"minX": 121.5, "minY": 104.5, "maxX": 681.5, "maxY": 905.5}, "class_id": 0, "box_caption": "General trash 0.003", "scores": {"class_score": 0.003498077392578125}, "domain": "pixel"}, {"position": {"minX": 254.25, "minY": 57.25, "maxX": 669.0, "maxY": 752.0}, "class_id": 9, "box_caption": "Clothing 0.003", "scores": {"class_score": 0.003398895263671875}, "domain": "pixel"}, {"position": {"minX": 254.25, "minY": 57.25, "maxX": 669.0, "maxY": 752.0}, "class_id": 5, "box_caption": "Plastic 0.003", "scores": {"class_score": 0.002925872802734375}, "domain": "pixel"}, {"position": {"minX": 142.75, "minY": 15.5, "maxX": 675.0, "maxY": 537.5}, "class_id": 0, "box_caption": "General trash 0.003", "scores": {"class_score": 0.00284576416015625}, "domain": "pixel"}, {"position": {"minX": 286.0, "minY": 171.75, "maxX": 660.0, "maxY": 426.25}, "class_id": 5, "box_caption": "Plastic 0.003", "scores": {"class_score": 0.002727508544921875}, "domain": "pixel"}, {"position": {"minX": 191.75, "minY": 806.0, "maxX": 609.0, "maxY": 999.0}, "class_id": 5, "box_caption": "Plastic 0.003", "scores": {"class_score": 0.0026683807373046875}, "domain": "pixel"}, {"position": {"minX": 37.25, "minY": 778.0, "maxX": 660.0, "maxY": 1005.0}, "class_id": 9, "box_caption": "Clothing 0.002", "scores": {"class_score": 0.002468109130859375}, "domain": "pixel"}, {"position": {"minX": 271.5, "minY": 18.25, "maxX": 680.5, "maxY": 798.0}, "class_id": 6, "box_caption": "Styrofoam 0.002", "scores": {"class_score": 0.0023326873779296875}, "domain": "pixel"}, {"position": {"minX": 350.75, "minY": 16.0, "maxX": 974.0, "maxY": 184.25}, "class_id": 0, "box_caption": "General trash 0.002", "scores": {"class_score": 0.00218963623046875}, "domain": "pixel"}, {"position": {"minX": 731.5, "minY": 732.5, "maxX": 860.5, "maxY": 954.5}, "class_id": 0, "box_caption": "General trash 0.002", "scores": {"class_score": 0.002162933349609375}, "domain": "pixel"}, {"position": {"minX": 729.0, "minY": 732.5, "maxX": 863.0, "maxY": 984.5}, "class_id": 7, "box_caption": "Plastic bag 0.002", "scores": {"class_score": 0.0020656585693359375}, "domain": "pixel"}, {"position": {"minX": 257.0, "minY": 9.625, "maxX": 871.0, "maxY": 130.125}, "class_id": 7, "box_caption": "Plastic bag 0.002", "scores": {"class_score": 0.001964569091796875}, "domain": "pixel"}, {"position": {"minX": 741.5, "minY": 711.5, "maxX": 1030.0, "maxY": 1023.5}, "class_id": 0, "box_caption": "General trash 0.002", "scores": {"class_score": 0.0019407272338867188}, "domain": "pixel"}, {"position": {"minX": 14.890625, "minY": 16.8125, "maxX": 60.875, "maxY": 56.8125}, "class_id": 1, "box_caption": "Paper 0.002", "scores": {"class_score": 0.0019378662109375}, "domain": "pixel"}, {"position": {"minX": 519.0, "minY": 18.625, "maxX": 1047.0, "maxY": 223.125}, "class_id": 7, "box_caption": "Plastic bag 0.002", "scores": {"class_score": 0.0019245147705078125}, "domain": "pixel"}, {"position": {"minX": 142.75, "minY": 130.25, "maxX": 669.0, "maxY": 595.0}, "class_id": 9, "box_caption": "Clothing 0.002", "scores": {"class_score": 0.0017986297607421875}, "domain": "pixel"}, {"position": {"minX": 276.75, "minY": 100.375, "maxX": 663.0, "maxY": 554.5}, "class_id": 1, "box_caption": "Paper 0.002", "scores": {"class_score": 0.0017938613891601562}, "domain": "pixel"}, {"position": {"minX": 585.0, "minY": 790.5, "maxX": 761.0, "maxY": 1037.0}, "class_id": 0, "box_caption": "General trash 0.002", "scores": {"class_score": 0.00176239013671875}, "domain": "pixel"}, {"position": {"minX": 191.75, "minY": 806.0, "maxX": 609.0, "maxY": 999.0}, "class_id": 1, "box_caption": "Paper 0.002", "scores": {"class_score": 0.0016326904296875}, "domain": "pixel"}, {"position": {"minX": 51.5, "minY": 595.0, "maxX": 685.5, "maxY": 1017.0}, "class_id": 9, "box_caption": "Clothing 0.002", "scores": {"class_score": 0.001613616943359375}, "domain": "pixel"}, {"position": {"minX": 257.0, "minY": 9.625, "maxX": 871.0, "maxY": 130.125}, "class_id": 0, "box_caption": "General trash 0.002", "scores": {"class_score": 0.0016040802001953125}, "domain": "pixel"}, {"position": {"minX": -78.25, "minY": 223.25, "maxX": 778.0, "maxY": 1037.0}, "class_id": 9, "box_caption": "Clothing 0.002", "scores": {"class_score": 0.0015611648559570312}, "domain": "pixel"}, {"position": {"minX": 271.5, "minY": 18.25, "maxX": 680.5, "maxY": 798.0}, "class_id": 0, "box_caption": "General trash 0.002", "scores": {"class_score": 0.0015439987182617188}, "domain": "pixel"}, {"position": {"minX": 610.0, "minY": 734.0, "maxX": 918.0, "maxY": 1035.0}, "class_id": 7, "box_caption": "Plastic bag 0.001", "scores": {"class_score": 0.0014858245849609375}, "domain": "pixel"}, {"position": {"minX": 58.25, "minY": 825.5, "maxX": 148.0, "maxY": 865.5}, "class_id": 7, "box_caption": "Plastic bag 0.001", "scores": {"class_score": 0.0013990402221679688}, "domain": "pixel"}, {"position": {"minX": -84.75, "minY": 213.75, "maxX": 781.0, "maxY": 972.0}, "class_id": 0, "box_caption": "General trash 0.001", "scores": {"class_score": 0.0013990402221679688}, "domain": "pixel"}, {"position": {"minX": 276.75, "minY": 100.375, "maxX": 663.0, "maxY": 554.5}, "class_id": 0, "box_caption": "General trash 0.001", "scores": {"class_score": 0.0013818740844726562}, "domain": "pixel"}, {"position": {"minX": 277.5, "minY": 42.0, "maxX": 661.0, "maxY": 399.5}, "class_id": 6, "box_caption": "Styrofoam 0.001", "scores": {"class_score": 0.0013294219970703125}, "domain": "pixel"}, {"position": {"minX": 287.0, "minY": 172.5, "maxX": 658.5, "maxY": 424.0}, "class_id": 7, "box_caption": "Plastic bag 0.001", "scores": {"class_score": 0.0013151168823242188}, "domain": "pixel"}, {"position": {"minX": 16.453125, "minY": 16.453125, "maxX": 60.4375, "maxY": 56.8125}, "class_id": 7, "box_caption": "Plastic bag 0.001", "scores": {"class_score": 0.0012598037719726562}, "domain": "pixel"}, {"position": {"minX": 137.5, "minY": 8.625, "maxX": 675.5, "maxY": 293.5}, "class_id": 0, "box_caption": "General trash 0.001", "scores": {"class_score": 0.001209259033203125}, "domain": "pixel"}, {"position": {"minX": 28.5625, "minY": 543.0, "maxX": 174.0, "maxY": 897.0}, "class_id": 0, "box_caption": "General trash 0.001", "scores": {"class_score": 0.00119781494140625}, "domain": "pixel"}, {"position": {"minX": 482.0, "minY": 638.5, "maxX": 899.0, "maxY": 1061.0}, "class_id": 0, "box_caption": "General trash 0.001", "scores": {"class_score": 0.0011548995971679688}, "domain": "pixel"}, {"position": {"minX": 588.5, "minY": 835.5, "maxX": 731.5, "maxY": 1032.0}, "class_id": 5, "box_caption": "Plastic 0.001", "scores": {"class_score": 0.0011472702026367188}, "domain": "pixel"}, {"position": {"minX": 16.15625, "minY": 15.328125, "maxX": 58.78125, "maxY": 54.5625}, "class_id": 6, "box_caption": "Styrofoam 0.001", "scores": {"class_score": 0.0010747909545898438}, "domain": "pixel"}, {"position": {"minX": 191.75, "minY": 806.0, "maxX": 609.0, "maxY": 999.0}, "class_id": 7, "box_caption": "Plastic bag 0.001", "scores": {"class_score": 0.0010700225830078125}, "domain": "pixel"}, {"position": {"minX": 286.0, "minY": 171.75, "maxX": 660.0, "maxY": 426.25}, "class_id": 9, "box_caption": "Clothing 0.001", "scores": {"class_score": 0.0010576248168945312}, "domain": "pixel"}, {"position": {"minX": 191.75, "minY": 806.0, "maxX": 609.0, "maxY": 999.0}, "class_id": 4, "box_caption": "Glass 0.001", "scores": {"class_score": 0.0010175704956054688}, "domain": "pixel"}], "class_labels": {"0": "General trash", "1": "Paper", "2": "Paper pack", "3": "Metal", "4": "Glass", "5": "Plastic", "6": "Styrofoam", "7": "Plastic bag", "8": "Battery", "9": "Clothing"}}