{"box_data": [{"position": {"minX": 543.0, "minY": 389.75, "maxX": 716.0, "maxY": 517.0}, "class_id": 1, "box_caption": "Paper 0.307", "scores": {"class_score": 0.30712890625}, "domain": "pixel"}, {"position": {"minX": 392.25, "minY": 373.25, "maxX": 583.5, "maxY": 547.0}, "class_id": 1, "box_caption": "Paper 0.284", "scores": {"class_score": 0.2841796875}, "domain": "pixel"}, {"position": {"minX": 368.0, "minY": 390.0, "maxX": 762.0, "maxY": 577.0}, "class_id": 1, "box_caption": "Paper 0.249", "scores": {"class_score": 0.2489013671875}, "domain": "pixel"}, {"position": {"minX": 525.5, "minY": 363.0, "maxX": 698.5, "maxY": 551.0}, "class_id": 1, "box_caption": "Paper 0.231", "scores": {"class_score": 0.2305908203125}, "domain": "pixel"}, {"position": {"minX": 437.25, "minY": 395.0, "maxX": 570.5, "maxY": 524.5}, "class_id": 1, "box_caption": "Paper 0.192", "scores": {"class_score": 0.192138671875}, "domain": "pixel"}, {"position": {"minX": 383.0, "minY": 410.0, "maxX": 604.5, "maxY": 520.0}, "class_id": 1, "box_caption": "Paper 0.173", "scores": {"class_score": 0.1732177734375}, "domain": "pixel"}, {"position": {"minX": 392.25, "minY": 373.25, "maxX": 583.5, "maxY": 547.0}, "class_id": 0, "box_caption": "General trash 0.159", "scores": {"class_score": 0.15869140625}, "domain": "pixel"}, {"position": {"minX": 394.75, "minY": 392.5, "maxX": 739.0, "maxY": 604.0}, "class_id": 7, "box_caption": "Plastic bag 0.148", "scores": {"class_score": 0.14794921875}, "domain": "pixel"}, {"position": {"minX": 383.0, "minY": 410.0, "maxX": 604.5, "maxY": 520.0}, "class_id": 7, "box_caption": "Plastic bag 0.145", "scores": {"class_score": 0.1446533203125}, "domain": "pixel"}, {"position": {"minX": 392.25, "minY": 373.25, "maxX": 583.5, "maxY": 547.0}, "class_id": 7, "box_caption": "Plastic bag 0.132", "scores": {"class_score": 0.1322021484375}, "domain": "pixel"}, {"position": {"minX": 404.5, "minY": 390.5, "maxX": 579.5, "maxY": 484.0}, "class_id": 1, "box_caption": "Paper 0.121", "scores": {"class_score": 0.12139892578125}, "domain": "pixel"}, {"position": {"minX": 424.5, "minY": 397.5, "maxX": 775.5, "maxY": 524.5}, "class_id": 1, "box_caption": "Paper 0.109", "scores": {"class_score": 0.10931396484375}, "domain": "pixel"}, {"position": {"minX": 395.5, "minY": 442.5, "maxX": 734.5, "maxY": 607.5}, "class_id": 1, "box_caption": "Paper 0.107", "scores": {"class_score": 0.10748291015625}, "domain": "pixel"}, {"position": {"minX": 354.0, "minY": 401.0, "maxX": 777.0, "maxY": 536.0}, "class_id": 7, "box_caption": "Plastic bag 0.105", "scores": {"class_score": 0.1046142578125}, "domain": "pixel"}, {"position": {"minX": 543.0, "minY": 389.75, "maxX": 716.0, "maxY": 517.0}, "class_id": 3, "box_caption": "Metal 0.103", "scores": {"class_score": 0.10296630859375}, "domain": "pixel"}, {"position": {"minX": 320.0, "minY": 819.0, "maxX": 419.0, "maxY": 1001.0}, "class_id": 7, "box_caption": "Plastic bag 0.099", "scores": {"class_score": 0.09912109375}, "domain": "pixel"}, {"position": {"minX": 437.25, "minY": 395.0, "maxX": 570.5, "maxY": 524.5}, "class_id": 0, "box_caption": "General trash 0.095", "scores": {"class_score": 0.094970703125}, "domain": "pixel"}, {"position": {"minX": 525.5, "minY": 363.0, "maxX": 698.5, "maxY": 551.0}, "class_id": 6, "box_caption": "Styrofoam 0.093", "scores": {"class_score": 0.09307861328125}, "domain": "pixel"}, {"position": {"minX": 425.75, "minY": 501.0, "maxX": 759.0, "maxY": 601.0}, "class_id": 1, "box_caption": "Paper 0.091", "scores": {"class_score": 0.090576171875}, "domain": "pixel"}, {"position": {"minX": 392.25, "minY": 373.25, "maxX": 583.5, "maxY": 547.0}, "class_id": 5, "box_caption": "Plastic 0.089", "scores": {"class_score": 0.0888671875}, "domain": "pixel"}, {"position": {"minX": 383.0, "minY": 371.5, "maxX": 749.0, "maxY": 620.0}, "class_id": 0, "box_caption": "General trash 0.080", "scores": {"class_score": 0.07958984375}, "domain": "pixel"}, {"position": {"minX": 517.0, "minY": 377.5, "maxX": 743.0, "maxY": 597.5}, "class_id": 1, "box_caption": "Paper 0.078", "scores": {"class_score": 0.0775146484375}, "domain": "pixel"}, {"position": {"minX": 437.25, "minY": 395.0, "maxX": 570.5, "maxY": 524.5}, "class_id": 7, "box_caption": "Plastic bag 0.074", "scores": {"class_score": 0.07366943359375}, "domain": "pixel"}, {"position": {"minX": 397.0, "minY": 408.75, "maxX": 784.0, "maxY": 572.0}, "class_id": 0, "box_caption": "General trash 0.072", "scores": {"class_score": 0.07232666015625}, "domain": "pixel"}, {"position": {"minX": 543.0, "minY": 389.75, "maxX": 716.0, "maxY": 517.0}, "class_id": 7, "box_caption": "Plastic bag 0.071", "scores": {"class_score": 0.07147216796875}, "domain": "pixel"}, {"position": {"minX": 525.5, "minY": 363.0, "maxX": 698.5, "maxY": 551.0}, "class_id": 3, "box_caption": "Metal 0.069", "scores": {"class_score": 0.068603515625}, "domain": "pixel"}, {"position": {"minX": 404.5, "minY": 390.5, "maxX": 579.5, "maxY": 484.0}, "class_id": 7, "box_caption": "Plastic bag 0.068", "scores": {"class_score": 0.0679931640625}, "domain": "pixel"}, {"position": {"minX": 543.0, "minY": 389.75, "maxX": 716.0, "maxY": 517.0}, "class_id": 6, "box_caption": "Styrofoam 0.068", "scores": {"class_score": 0.06787109375}, "domain": "pixel"}, {"position": {"minX": 383.0, "minY": 371.5, "maxX": 749.0, "maxY": 620.0}, "class_id": 5, "box_caption": "Plastic 0.067", "scores": {"class_score": 0.06695556640625}, "domain": "pixel"}, {"position": {"minX": 397.0, "minY": 408.75, "maxX": 784.0, "maxY": 572.0}, "class_id": 5, "box_caption": "Plastic 0.066", "scores": {"class_score": 0.06597900390625}, "domain": "pixel"}, {"position": {"minX": 543.0, "minY": 389.75, "maxX": 716.0, "maxY": 517.0}, "class_id": 0, "box_caption": "General trash 0.066", "scores": {"class_score": 0.06585693359375}, "domain": "pixel"}, {"position": {"minX": 525.5, "minY": 363.0, "maxX": 698.5, "maxY": 551.0}, "class_id": 0, "box_caption": "General trash 0.063", "scores": {"class_score": 0.06298828125}, "domain": "pixel"}, {"position": {"minX": 304.75, "minY": 776.0, "maxX": 429.25, "maxY": 1045.0}, "class_id": 5, "box_caption": "Plastic 0.062", "scores": {"class_score": 0.062286376953125}, "domain": "pixel"}, {"position": {"minX": 525.5, "minY": 363.0, "maxX": 698.5, "maxY": 551.0}, "class_id": 7, "box_caption": "Plastic bag 0.062", "scores": {"class_score": 0.06201171875}, "domain": "pixel"}, {"position": {"minX": 536.5, "minY": 389.0, "maxX": 720.5, "maxY": 508.0}, "class_id": 2, "box_caption": "Paper pack 0.060", "scores": {"class_score": 0.05975341796875}, "domain": "pixel"}, {"position": {"minX": 394.75, "minY": 392.5, "maxX": 739.0, "maxY": 604.0}, "class_id": 9, "box_caption": "Clothing 0.059", "scores": {"class_score": 0.05938720703125}, "domain": "pixel"}, {"position": {"minX": 390.0, "minY": 380.75, "maxX": 581.5, "maxY": 558.5}, "class_id": 3, "box_caption": "Metal 0.057", "scores": {"class_score": 0.057373046875}, "domain": "pixel"}, {"position": {"minX": 383.0, "minY": 410.0, "maxX": 604.5, "maxY": 520.0}, "class_id": 9, "box_caption": "Clothing 0.057", "scores": {"class_score": 0.057159423828125}, "domain": "pixel"}, {"position": {"minX": 383.0, "minY": 371.5, "maxX": 749.0, "maxY": 620.0}, "class_id": 3, "box_caption": "Metal 0.056", "scores": {"class_score": 0.056488037109375}, "domain": "pixel"}, {"position": {"minX": 424.25, "minY": 398.75, "maxX": 576.0, "maxY": 505.75}, "class_id": 2, "box_caption": "Paper pack 0.056", "scores": {"class_score": 0.05633544921875}, "domain": "pixel"}, {"position": {"minX": 461.5, "minY": 363.0, "maxX": 572.5, "maxY": 562.5}, "class_id": 1, "box_caption": "Paper 0.055", "scores": {"class_score": 0.055084228515625}, "domain": "pixel"}, {"position": {"minX": 536.5, "minY": 389.0, "maxX": 720.5, "maxY": 508.0}, "class_id": 4, "box_caption": "Glass 0.053", "scores": {"class_score": 0.052703857421875}, "domain": "pixel"}, {"position": {"minX": 371.5, "minY": 463.5, "maxX": 741.5, "maxY": 576.5}, "class_id": 7, "box_caption": "Plastic bag 0.052", "scores": {"class_score": 0.052337646484375}, "domain": "pixel"}, {"position": {"minX": 519.0, "minY": 402.5, "maxX": 789.0, "maxY": 578.5}, "class_id": 7, "box_caption": "Plastic bag 0.051", "scores": {"class_score": 0.05078125}, "domain": "pixel"}, {"position": {"minX": 392.25, "minY": 373.25, "maxX": 583.5, "maxY": 547.0}, "class_id": 2, "box_caption": "Paper pack 0.050", "scores": {"class_score": 0.050079345703125}, "domain": "pixel"}, {"position": {"minX": 381.0, "minY": 399.0, "maxX": 563.5, "maxY": 589.5}, "class_id": 0, "box_caption": "General trash 0.050", "scores": {"class_score": 0.04986572265625}, "domain": "pixel"}, {"position": {"minX": 381.0, "minY": 399.0, "maxX": 563.5, "maxY": 589.5}, "class_id": 1, "box_caption": "Paper 0.046", "scores": {"class_score": 0.04620361328125}, "domain": "pixel"}, {"position": {"minX": 517.0, "minY": 377.5, "maxX": 743.0, "maxY": 597.5}, "class_id": 0, "box_caption": "General trash 0.046", "scores": {"class_score": 0.046112060546875}, "domain": "pixel"}, {"position": {"minX": 437.25, "minY": 395.0, "maxX": 570.5, "maxY": 524.5}, "class_id": 3, "box_caption": "Metal 0.045", "scores": {"class_score": 0.044769287109375}, "domain": "pixel"}, {"position": {"minX": 394.75, "minY": 392.5, "maxX": 739.0, "maxY": 604.0}, "class_id": 8, "box_caption": "Battery 0.044", "scores": {"class_score": 0.044097900390625}, "domain": "pixel"}, {"position": {"minX": 404.5, "minY": 390.5, "maxX": 579.5, "maxY": 484.0}, "class_id": 0, "box_caption": "General trash 0.043", "scores": {"class_score": 0.042633056640625}, "domain": "pixel"}, {"position": {"minX": 313.0, "minY": 792.5, "maxX": 427.0, "maxY": 1024.0}, "class_id": 1, "box_caption": "Paper 0.042", "scores": {"class_score": 0.042205810546875}, "domain": "pixel"}, {"position": {"minX": 383.0, "minY": 410.0, "maxX": 604.5, "maxY": 520.0}, "class_id": 5, "box_caption": "Plastic 0.042", "scores": {"class_score": 0.04180908203125}, "domain": "pixel"}, {"position": {"minX": 311.5, "minY": 778.0, "maxX": 454.5, "maxY": 1043.0}, "class_id": 7, "box_caption": "Plastic bag 0.042", "scores": {"class_score": 0.04168701171875}, "domain": "pixel"}, {"position": {"minX": 504.25, "minY": 397.0, "maxX": 757.5, "maxY": 519.0}, "class_id": 5, "box_caption": "Plastic 0.041", "scores": {"class_score": 0.040863037109375}, "domain": "pixel"}, {"position": {"minX": 427.75, "minY": 275.5, "maxX": 540.0, "maxY": 383.0}, "class_id": 0, "box_caption": "General trash 0.040", "scores": {"class_score": 0.0404052734375}, "domain": "pixel"}, {"position": {"minX": 432.25, "minY": 274.5, "maxX": 539.0, "maxY": 384.0}, "class_id": 1, "box_caption": "Paper 0.040", "scores": {"class_score": 0.040283203125}, "domain": "pixel"}, {"position": {"minX": 383.0, "minY": 410.0, "maxX": 604.5, "maxY": 520.0}, "class_id": 8, "box_caption": "Battery 0.038", "scores": {"class_score": 0.038055419921875}, "domain": "pixel"}, {"position": {"minX": 390.0, "minY": 421.5, "maxX": 660.0, "maxY": 562.0}, "class_id": 1, "box_caption": "Paper 0.037", "scores": {"class_score": 0.03704833984375}, "domain": "pixel"}, {"position": {"minX": 397.5, "minY": 514.5, "maxX": 738.5, "maxY": 575.5}, "class_id": 1, "box_caption": "Paper 0.036", "scores": {"class_score": 0.035797119140625}, "domain": "pixel"}, {"position": {"minX": 368.0, "minY": 390.0, "maxX": 762.0, "maxY": 577.0}, "class_id": 2, "box_caption": "Paper pack 0.035", "scores": {"class_score": 0.035430908203125}, "domain": "pixel"}, {"position": {"minX": 433.0, "minY": 371.75, "maxX": 623.0, "maxY": 515.0}, "class_id": 1, "box_caption": "Paper 0.034", "scores": {"class_score": 0.034454345703125}, "domain": "pixel"}, {"position": {"minX": 432.25, "minY": 274.5, "maxX": 539.0, "maxY": 384.0}, "class_id": 7, "box_caption": "Plastic bag 0.034", "scores": {"class_score": 0.034454345703125}, "domain": "pixel"}, {"position": {"minX": 383.0, "minY": 410.0, "maxX": 604.5, "maxY": 520.0}, "class_id": 4, "box_caption": "Glass 0.034", "scores": {"class_score": 0.034423828125}, "domain": "pixel"}, {"position": {"minX": 320.0, "minY": 819.0, "maxX": 419.0, "maxY": 1001.0}, "class_id": 5, "box_caption": "Plastic 0.034", "scores": {"class_score": 0.03369140625}, "domain": "pixel"}, {"position": {"minX": 468.5, "minY": 361.75, "maxX": 729.5, "maxY": 560.0}, "class_id": 5, "box_caption": "Plastic 0.033", "scores": {"class_score": 0.03326416015625}, "domain": "pixel"}, {"position": {"minX": 424.25, "minY": 398.75, "maxX": 576.0, "maxY": 505.75}, "class_id": 5, "box_caption": "Plastic 0.033", "scores": {"class_score": 0.033233642578125}, "domain": "pixel"}, {"position": {"minX": 425.75, "minY": 501.0, "maxX": 759.0, "maxY": 601.0}, "class_id": 0, "box_caption": "General trash 0.033", "scores": {"class_score": 0.032867431640625}, "domain": "pixel"}, {"position": {"minX": 436.0, "minY": 381.75, "maxX": 763.0, "maxY": 535.0}, "class_id": 0, "box_caption": "General trash 0.033", "scores": {"class_score": 0.032745361328125}, "domain": "pixel"}, {"position": {"minX": 404.0, "minY": 389.0, "maxX": 573.0, "maxY": 519.0}, "class_id": 6, "box_caption": "Styrofoam 0.032", "scores": {"class_score": 0.032135009765625}, "domain": "pixel"}, {"position": {"minX": 498.25, "minY": 371.25, "maxX": 643.0, "maxY": 519.5}, "class_id": 1, "box_caption": "Paper 0.032", "scores": {"class_score": 0.031951904296875}, "domain": "pixel"}, {"position": {"minX": 425.75, "minY": 501.0, "maxX": 759.0, "maxY": 601.0}, "class_id": 7, "box_caption": "Plastic bag 0.031", "scores": {"class_score": 0.031280517578125}, "domain": "pixel"}, {"position": {"minX": 371.5, "minY": 463.5, "maxX": 741.5, "maxY": 576.5}, "class_id": 0, "box_caption": "General trash 0.031", "scores": {"class_score": 0.0308380126953125}, "domain": "pixel"}, {"position": {"minX": 398.5, "minY": 448.5, "maxX": 738.5, "maxY": 598.5}, "class_id": 5, "box_caption": "Plastic 0.030", "scores": {"class_score": 0.0297698974609375}, "domain": "pixel"}, {"position": {"minX": 313.0, "minY": 792.5, "maxX": 427.0, "maxY": 1024.0}, "class_id": 0, "box_caption": "General trash 0.030", "scores": {"class_score": 0.0297393798828125}, "domain": "pixel"}, {"position": {"minX": 392.0, "minY": 378.0, "maxX": 584.0, "maxY": 594.0}, "class_id": 6, "box_caption": "Styrofoam 0.030", "scores": {"class_score": 0.0296478271484375}, "domain": "pixel"}, {"position": {"minX": 383.0, "minY": 410.0, "maxX": 604.5, "maxY": 520.0}, "class_id": 3, "box_caption": "Metal 0.029", "scores": {"class_score": 0.0294189453125}, "domain": "pixel"}, {"position": {"minX": 394.75, "minY": 392.5, "maxX": 739.0, "maxY": 604.0}, "class_id": 6, "box_caption": "Styrofoam 0.029", "scores": {"class_score": 0.0285186767578125}, "domain": "pixel"}, {"position": {"minX": 320.0, "minY": 819.0, "maxX": 419.0, "maxY": 1001.0}, "class_id": 3, "box_caption": "Metal 0.027", "scores": {"class_score": 0.0268096923828125}, "domain": "pixel"}, {"position": {"minX": 354.0, "minY": 401.0, "maxX": 777.0, "maxY": 536.0}, "class_id": 8, "box_caption": "Battery 0.027", "scores": {"class_score": 0.026702880859375}, "domain": "pixel"}, {"position": {"minX": 427.75, "minY": 275.5, "maxX": 540.0, "maxY": 383.0}, "class_id": 5, "box_caption": "Plastic 0.026", "scores": {"class_score": 0.026153564453125}, "domain": "pixel"}, {"position": {"minX": 424.5, "minY": 397.5, "maxX": 775.5, "maxY": 524.5}, "class_id": 3, "box_caption": "Metal 0.026", "scores": {"class_score": 0.0259857177734375}, "domain": "pixel"}, {"position": {"minX": 392.25, "minY": 373.25, "maxX": 583.5, "maxY": 547.0}, "class_id": 4, "box_caption": "Glass 0.026", "scores": {"class_score": 0.0257415771484375}, "domain": "pixel"}, {"position": {"minX": 354.0, "minY": 401.0, "maxX": 777.0, "maxY": 536.0}, "class_id": 9, "box_caption": "Clothing 0.025", "scores": {"class_score": 0.024993896484375}, "domain": "pixel"}, {"position": {"minX": 521.5, "minY": 399.5, "maxX": 732.5, "maxY": 472.0}, "class_id": 1, "box_caption": "Paper 0.025", "scores": {"class_score": 0.024871826171875}, "domain": "pixel"}, {"position": {"minX": 320.0, "minY": 819.0, "maxX": 419.0, "maxY": 1001.0}, "class_id": 8, "box_caption": "Battery 0.025", "scores": {"class_score": 0.0247802734375}, "domain": "pixel"}, {"position": {"minX": 517.0, "minY": 377.5, "maxX": 743.0, "maxY": 597.5}, "class_id": 3, "box_caption": "Metal 0.025", "scores": {"class_score": 0.0246124267578125}, "domain": "pixel"}, {"position": {"minX": 320.0, "minY": 819.0, "maxX": 419.0, "maxY": 1001.0}, "class_id": 6, "box_caption": "Styrofoam 0.025", "scores": {"class_score": 0.02459716796875}, "domain": "pixel"}, {"position": {"minX": 504.5, "minY": 531.0, "maxX": 684.5, "maxY": 573.0}, "class_id": 1, "box_caption": "Paper 0.024", "scores": {"class_score": 0.0244903564453125}, "domain": "pixel"}, {"position": {"minX": 19.28125, "minY": 602.5, "maxX": 79.25, "maxY": 849.5}, "class_id": 5, "box_caption": "Plastic 0.024", "scores": {"class_score": 0.024444580078125}, "domain": "pixel"}, {"position": {"minX": 421.75, "minY": 231.0, "maxX": 516.5, "maxY": 373.5}, "class_id": 1, "box_caption": "Paper 0.024", "scores": {"class_score": 0.024078369140625}, "domain": "pixel"}, {"position": {"minX": 424.25, "minY": 398.75, "maxX": 576.0, "maxY": 505.75}, "class_id": 4, "box_caption": "Glass 0.024", "scores": {"class_score": 0.023956298828125}, "domain": "pixel"}, {"position": {"minX": 425.75, "minY": 501.0, "maxX": 759.0, "maxY": 601.0}, "class_id": 3, "box_caption": "Metal 0.024", "scores": {"class_score": 0.0239105224609375}, "domain": "pixel"}, {"position": {"minX": 521.0, "minY": 503.0, "maxX": 705.0, "maxY": 595.0}, "class_id": 0, "box_caption": "General trash 0.024", "scores": {"class_score": 0.0238800048828125}, "domain": "pixel"}, {"position": {"minX": 594.0, "minY": 381.5, "maxX": 727.0, "maxY": 574.0}, "class_id": 1, "box_caption": "Paper 0.024", "scores": {"class_score": 0.0235595703125}, "domain": "pixel"}, {"position": {"minX": 383.0, "minY": 410.0, "maxX": 604.5, "maxY": 520.0}, "class_id": 2, "box_caption": "Paper pack 0.023", "scores": {"class_score": 0.0233001708984375}, "domain": "pixel"}, {"position": {"minX": 521.0, "minY": 503.0, "maxX": 705.0, "maxY": 595.0}, "class_id": 1, "box_caption": "Paper 0.023", "scores": {"class_score": 0.02301025390625}, "domain": "pixel"}, {"position": {"minX": 520.5, "minY": 408.5, "maxX": 579.5, "maxY": 517.5}, "class_id": 1, "box_caption": "Paper 0.023", "scores": {"class_score": 0.0226898193359375}, "domain": "pixel"}, {"position": {"minX": 320.0, "minY": 819.0, "maxX": 419.0, "maxY": 1001.0}, "class_id": 9, "box_caption": "Clothing 0.023", "scores": {"class_score": 0.0225677490234375}, "domain": "pixel"}, {"position": {"minX": 369.0, "minY": 406.5, "maxX": 581.5, "maxY": 569.0}, "class_id": 9, "box_caption": "Clothing 0.021", "scores": {"class_score": 0.0214996337890625}, "domain": "pixel"}, {"position": {"minX": 421.75, "minY": 231.0, "maxX": 516.5, "maxY": 373.5}, "class_id": 7, "box_caption": "Plastic bag 0.021", "scores": {"class_score": 0.021453857421875}, "domain": "pixel"}, {"position": {"minX": 523.0, "minY": 405.75, "maxX": 746.0, "maxY": 518.5}, "class_id": 9, "box_caption": "Clothing 0.021", "scores": {"class_score": 0.0205535888671875}, "domain": "pixel"}, {"position": {"minX": 538.5, "minY": 369.0, "maxX": 622.5, "maxY": 550.5}, "class_id": 1, "box_caption": "Paper 0.020", "scores": {"class_score": 0.02044677734375}, "domain": "pixel"}, {"position": {"minX": 469.5, "minY": 377.75, "maxX": 555.5, "maxY": 493.25}, "class_id": 1, "box_caption": "Paper 0.020", "scores": {"class_score": 0.020233154296875}, "domain": "pixel"}, {"position": {"minX": 534.0, "minY": 355.75, "maxX": 727.0, "maxY": 586.0}, "class_id": 2, "box_caption": "Paper pack 0.020", "scores": {"class_score": 0.020172119140625}, "domain": "pixel"}, {"position": {"minX": 544.0, "minY": 394.75, "maxX": 589.0, "maxY": 524.5}, "class_id": 1, "box_caption": "Paper 0.020", "scores": {"class_score": 0.01995849609375}, "domain": "pixel"}, {"position": {"minX": 424.0, "minY": 357.25, "maxX": 602.0, "maxY": 592.0}, "class_id": 1, "box_caption": "Paper 0.020", "scores": {"class_score": 0.01983642578125}, "domain": "pixel"}, {"position": {"minX": 391.5, "minY": 736.0, "maxX": 471.5, "maxY": 829.0}, "class_id": 1, "box_caption": "Paper 0.020", "scores": {"class_score": 0.01983642578125}, "domain": "pixel"}, {"position": {"minX": 369.0, "minY": 406.5, "maxX": 581.5, "maxY": 569.0}, "class_id": 8, "box_caption": "Battery 0.020", "scores": {"class_score": 0.019683837890625}, "domain": "pixel"}, {"position": {"minX": 461.5, "minY": 363.0, "maxX": 572.5, "maxY": 562.5}, "class_id": 0, "box_caption": "General trash 0.020", "scores": {"class_score": 0.0196075439453125}, "domain": "pixel"}, {"position": {"minX": 424.5, "minY": 397.5, "maxX": 775.5, "maxY": 524.5}, "class_id": 4, "box_caption": "Glass 0.020", "scores": {"class_score": 0.01959228515625}, "domain": "pixel"}, {"position": {"minX": 304.75, "minY": 776.0, "maxX": 429.25, "maxY": 1045.0}, "class_id": 8, "box_caption": "Battery 0.019", "scores": {"class_score": 0.019195556640625}, "domain": "pixel"}, {"position": {"minX": 397.0, "minY": 397.0, "maxX": 794.0, "maxY": 598.0}, "class_id": 4, "box_caption": "Glass 0.019", "scores": {"class_score": 0.0191497802734375}, "domain": "pixel"}, {"position": {"minX": 25.78125, "minY": 574.5, "maxX": 87.25, "maxY": 853.5}, "class_id": 7, "box_caption": "Plastic bag 0.019", "scores": {"class_score": 0.0188751220703125}, "domain": "pixel"}, {"position": {"minX": 378.0, "minY": 401.5, "maxX": 612.5, "maxY": 483.0}, "class_id": 9, "box_caption": "Clothing 0.019", "scores": {"class_score": 0.0185699462890625}, "domain": "pixel"}, {"position": {"minX": 378.0, "minY": 401.5, "maxX": 612.5, "maxY": 483.0}, "class_id": 4, "box_caption": "Glass 0.019", "scores": {"class_score": 0.0185394287109375}, "domain": "pixel"}, {"position": {"minX": 417.5, "minY": 301.0, "maxX": 573.5, "maxY": 368.0}, "class_id": 1, "box_caption": "Paper 0.018", "scores": {"class_score": 0.018402099609375}, "domain": "pixel"}, {"position": {"minX": 461.5, "minY": 363.0, "maxX": 572.5, "maxY": 562.5}, "class_id": 7, "box_caption": "Plastic bag 0.018", "scores": {"class_score": 0.018096923828125}, "domain": "pixel"}, {"position": {"minX": 114.0, "minY": -4.75, "maxX": 295.25, "maxY": 353.75}, "class_id": 7, "box_caption": "Plastic bag 0.018", "scores": {"class_score": 0.018096923828125}, "domain": "pixel"}, {"position": {"minX": 371.5, "minY": 463.5, "maxX": 741.5, "maxY": 576.5}, "class_id": 2, "box_caption": "Paper pack 0.018", "scores": {"class_score": 0.018096923828125}, "domain": "pixel"}, {"position": {"minX": 397.5, "minY": 514.5, "maxX": 738.5, "maxY": 575.5}, "class_id": 7, "box_caption": "Plastic bag 0.018", "scores": {"class_score": 0.01788330078125}, "domain": "pixel"}, {"position": {"minX": 544.5, "minY": 385.0, "maxX": 567.5, "maxY": 512.5}, "class_id": 1, "box_caption": "Paper 0.018", "scores": {"class_score": 0.017852783203125}, "domain": "pixel"}, {"position": {"minX": 540.0, "minY": 372.75, "maxX": 752.0, "maxY": 602.5}, "class_id": 5, "box_caption": "Plastic 0.018", "scores": {"class_score": 0.017547607421875}, "domain": "pixel"}, {"position": {"minX": 523.0, "minY": 405.75, "maxX": 746.0, "maxY": 518.5}, "class_id": 8, "box_caption": "Battery 0.017", "scores": {"class_score": 0.01739501953125}, "domain": "pixel"}, {"position": {"minX": 398.5, "minY": 448.5, "maxX": 738.5, "maxY": 598.5}, "class_id": 3, "box_caption": "Metal 0.017", "scores": {"class_score": 0.0173492431640625}, "domain": "pixel"}, {"position": {"minX": 525.5, "minY": 363.0, "maxX": 698.5, "maxY": 551.0}, "class_id": 9, "box_caption": "Clothing 0.017", "scores": {"class_score": 0.0172119140625}, "domain": "pixel"}, {"position": {"minX": 492.0, "minY": 386.0, "maxX": 576.0, "maxY": 517.5}, "class_id": 1, "box_caption": "Paper 0.017", "scores": {"class_score": 0.01715087890625}, "domain": "pixel"}, {"position": {"minX": 433.0, "minY": 371.75, "maxX": 623.0, "maxY": 515.0}, "class_id": 0, "box_caption": "General trash 0.017", "scores": {"class_score": 0.0171356201171875}, "domain": "pixel"}, {"position": {"minX": 416.5, "minY": 263.25, "maxX": 574.0, "maxY": 356.25}, "class_id": 1, "box_caption": "Paper 0.017", "scores": {"class_score": 0.0166778564453125}, "domain": "pixel"}, {"position": {"minX": 406.25, "minY": 517.5, "maxX": 565.0, "maxY": 588.5}, "class_id": 1, "box_caption": "Paper 0.017", "scores": {"class_score": 0.0166015625}, "domain": "pixel"}, {"position": {"minX": 330.25, "minY": 777.0, "maxX": 443.75, "maxY": 982.0}, "class_id": 1, "box_caption": "Paper 0.017", "scores": {"class_score": 0.016510009765625}, "domain": "pixel"}, {"position": {"minX": 387.5, "minY": 525.5, "maxX": 592.5, "maxY": 582.5}, "class_id": 0, "box_caption": "General trash 0.016", "scores": {"class_score": 0.0164794921875}, "domain": "pixel"}, {"position": {"minX": 390.0, "minY": 421.5, "maxX": 660.0, "maxY": 562.0}, "class_id": 7, "box_caption": "Plastic bag 0.016", "scores": {"class_score": 0.0164337158203125}, "domain": "pixel"}, {"position": {"minX": 383.0, "minY": 410.0, "maxX": 604.5, "maxY": 520.0}, "class_id": 0, "box_caption": "General trash 0.016", "scores": {"class_score": 0.016387939453125}, "domain": "pixel"}, {"position": {"minX": 378.0, "minY": 401.5, "maxX": 612.5, "maxY": 483.0}, "class_id": 3, "box_caption": "Metal 0.016", "scores": {"class_score": 0.016357421875}, "domain": "pixel"}, {"position": {"minX": 19.28125, "minY": 602.5, "maxX": 79.25, "maxY": 849.5}, "class_id": 1, "box_caption": "Paper 0.016", "scores": {"class_score": 0.0158843994140625}, "domain": "pixel"}, {"position": {"minX": 304.75, "minY": 776.0, "maxX": 429.25, "maxY": 1045.0}, "class_id": 6, "box_caption": "Styrofoam 0.016", "scores": {"class_score": 0.0158538818359375}, "domain": "pixel"}, {"position": {"minX": 412.0, "minY": 259.25, "maxX": 555.5, "maxY": 371.25}, "class_id": 7, "box_caption": "Plastic bag 0.016", "scores": {"class_score": 0.0157470703125}, "domain": "pixel"}, {"position": {"minX": 525.0, "minY": 369.5, "maxX": 697.0, "maxY": 502.5}, "class_id": 5, "box_caption": "Plastic 0.016", "scores": {"class_score": 0.0157012939453125}, "domain": "pixel"}, {"position": {"minX": 313.0, "minY": 792.5, "maxX": 427.0, "maxY": 1024.0}, "class_id": 2, "box_caption": "Paper pack 0.016", "scores": {"class_score": 0.015625}, "domain": "pixel"}, {"position": {"minX": 459.75, "minY": 395.0, "maxX": 805.0, "maxY": 578.0}, "class_id": 3, "box_caption": "Metal 0.016", "scores": {"class_score": 0.01558685302734375}, "domain": "pixel"}, {"position": {"minX": 378.0, "minY": 401.5, "maxX": 612.5, "maxY": 483.0}, "class_id": 5, "box_caption": "Plastic 0.016", "scores": {"class_score": 0.0155487060546875}, "domain": "pixel"}, {"position": {"minX": 534.0, "minY": 355.75, "maxX": 727.0, "maxY": 586.0}, "class_id": 4, "box_caption": "Glass 0.016", "scores": {"class_score": 0.0155029296875}, "domain": "pixel"}, {"position": {"minX": 404.0, "minY": 373.0, "maxX": 659.0, "maxY": 545.5}, "class_id": 3, "box_caption": "Metal 0.015", "scores": {"class_score": 0.0153961181640625}, "domain": "pixel"}, {"position": {"minX": 530.5, "minY": 379.0, "maxX": 595.5, "maxY": 513.5}, "class_id": 1, "box_caption": "Paper 0.015", "scores": {"class_score": 0.01529693603515625}, "domain": "pixel"}, {"position": {"minX": 441.75, "minY": 246.5, "maxX": 533.0, "maxY": 371.5}, "class_id": 0, "box_caption": "General trash 0.015", "scores": {"class_score": 0.0149078369140625}, "domain": "pixel"}, {"position": {"minX": 399.5, "minY": 253.625, "maxX": 534.0, "maxY": 375.5}, "class_id": 5, "box_caption": "Plastic 0.015", "scores": {"class_score": 0.0148773193359375}, "domain": "pixel"}, {"position": {"minX": 391.5, "minY": 736.0, "maxX": 471.5, "maxY": 829.0}, "class_id": 7, "box_caption": "Plastic bag 0.015", "scores": {"class_score": 0.014739990234375}, "domain": "pixel"}, {"position": {"minX": 517.0, "minY": 377.5, "maxX": 743.0, "maxY": 597.5}, "class_id": 6, "box_caption": "Styrofoam 0.015", "scores": {"class_score": 0.0146331787109375}, "domain": "pixel"}, {"position": {"minX": 498.0, "minY": 388.5, "maxX": 697.0, "maxY": 487.0}, "class_id": 1, "box_caption": "Paper 0.015", "scores": {"class_score": 0.01456451416015625}, "domain": "pixel"}, {"position": {"minX": 507.0, "minY": 495.75, "maxX": 710.0, "maxY": 583.5}, "class_id": 5, "box_caption": "Plastic 0.015", "scores": {"class_score": 0.0145416259765625}, "domain": "pixel"}, {"position": {"minX": 309.25, "minY": 823.0, "maxX": 473.25, "maxY": 933.0}, "class_id": 7, "box_caption": "Plastic bag 0.015", "scores": {"class_score": 0.01450347900390625}, "domain": "pixel"}, {"position": {"minX": 417.0, "minY": 512.5, "maxX": 777.0, "maxY": 577.5}, "class_id": 5, "box_caption": "Plastic 0.014", "scores": {"class_score": 0.0141448974609375}, "domain": "pixel"}, {"position": {"minX": 521.5, "minY": 399.5, "maxX": 732.5, "maxY": 472.0}, "class_id": 7, "box_caption": "Plastic bag 0.014", "scores": {"class_score": 0.013824462890625}, "domain": "pixel"}, {"position": {"minX": 333.5, "minY": 778.5, "maxX": 435.5, "maxY": 992.5}, "class_id": 7, "box_caption": "Plastic bag 0.014", "scores": {"class_score": 0.01374053955078125}, "domain": "pixel"}, {"position": {"minX": 417.5, "minY": 301.0, "maxX": 573.5, "maxY": 368.0}, "class_id": 7, "box_caption": "Plastic bag 0.014", "scores": {"class_score": 0.01372528076171875}, "domain": "pixel"}, {"position": {"minX": 330.25, "minY": 777.0, "maxX": 443.75, "maxY": 982.0}, "class_id": 0, "box_caption": "General trash 0.014", "scores": {"class_score": 0.0135955810546875}, "domain": "pixel"}, {"position": {"minX": 424.5, "minY": 397.5, "maxX": 775.5, "maxY": 524.5}, "class_id": 2, "box_caption": "Paper pack 0.013", "scores": {"class_score": 0.01349639892578125}, "domain": "pixel"}, {"position": {"minX": 416.0, "minY": 537.0, "maxX": 594.0, "maxY": 593.0}, "class_id": 0, "box_caption": "General trash 0.013", "scores": {"class_score": 0.01320648193359375}, "domain": "pixel"}, {"position": {"minX": 403.0, "minY": 387.5, "maxX": 647.0, "maxY": 533.5}, "class_id": 9, "box_caption": "Clothing 0.013", "scores": {"class_score": 0.013153076171875}, "domain": "pixel"}, {"position": {"minX": 574.5, "minY": 387.5, "maxX": 712.5, "maxY": 514.5}, "class_id": 5, "box_caption": "Plastic 0.013", "scores": {"class_score": 0.0130767822265625}, "domain": "pixel"}, {"position": {"minX": 624.0, "minY": 807.5, "maxX": 791.0, "maxY": 950.5}, "class_id": 1, "box_caption": "Paper 0.013", "scores": {"class_score": 0.01300048828125}, "domain": "pixel"}, {"position": {"minX": 433.0, "minY": 371.75, "maxX": 623.0, "maxY": 515.0}, "class_id": 7, "box_caption": "Plastic bag 0.013", "scores": {"class_score": 0.0128936767578125}, "domain": "pixel"}, {"position": {"minX": 387.5, "minY": 525.5, "maxX": 592.5, "maxY": 582.5}, "class_id": 5, "box_caption": "Plastic 0.013", "scores": {"class_score": 0.0126190185546875}, "domain": "pixel"}, {"position": {"minX": 498.25, "minY": 371.25, "maxX": 643.0, "maxY": 519.5}, "class_id": 0, "box_caption": "General trash 0.012", "scores": {"class_score": 0.012359619140625}, "domain": "pixel"}, {"position": {"minX": 519.0, "minY": 402.5, "maxX": 789.0, "maxY": 578.5}, "class_id": 9, "box_caption": "Clothing 0.012", "scores": {"class_score": 0.01219940185546875}, "domain": "pixel"}, {"position": {"minX": 403.0, "minY": 387.5, "maxX": 647.0, "maxY": 533.5}, "class_id": 8, "box_caption": "Battery 0.012", "scores": {"class_score": 0.012176513671875}, "domain": "pixel"}, {"position": {"minX": 354.0, "minY": 401.0, "maxX": 777.0, "maxY": 536.0}, "class_id": 6, "box_caption": "Styrofoam 0.012", "scores": {"class_score": 0.012176513671875}, "domain": "pixel"}, {"position": {"minX": 451.75, "minY": 526.0, "maxX": 554.0, "maxY": 603.0}, "class_id": 1, "box_caption": "Paper 0.012", "scores": {"class_score": 0.012054443359375}, "domain": "pixel"}, {"position": {"minX": 381.0, "minY": 399.0, "maxX": 563.5, "maxY": 589.5}, "class_id": 5, "box_caption": "Plastic 0.012", "scores": {"class_score": 0.01194000244140625}, "domain": "pixel"}, {"position": {"minX": 469.5, "minY": 377.75, "maxX": 555.5, "maxY": 493.25}, "class_id": 0, "box_caption": "General trash 0.012", "scores": {"class_score": 0.011932373046875}, "domain": "pixel"}, {"position": {"minX": 461.5, "minY": 363.0, "maxX": 572.5, "maxY": 562.5}, "class_id": 5, "box_caption": "Plastic 0.012", "scores": {"class_score": 0.01181793212890625}, "domain": "pixel"}, {"position": {"minX": 19.28125, "minY": 602.5, "maxX": 79.25, "maxY": 849.5}, "class_id": 0, "box_caption": "General trash 0.012", "scores": {"class_score": 0.01180267333984375}, "domain": "pixel"}, {"position": {"minX": 356.25, "minY": 780.0, "maxX": 433.25, "maxY": 1033.0}, "class_id": 1, "box_caption": "Paper 0.012", "scores": {"class_score": 0.01171875}, "domain": "pixel"}, {"position": {"minX": 404.0, "minY": 373.0, "maxX": 659.0, "maxY": 545.5}, "class_id": 6, "box_caption": "Styrofoam 0.012", "scores": {"class_score": 0.01171875}, "domain": "pixel"}, {"position": {"minX": 411.5, "minY": 624.5, "maxX": 513.0, "maxY": 749.5}, "class_id": 7, "box_caption": "Plastic bag 0.012", "scores": {"class_score": 0.011627197265625}, "domain": "pixel"}, {"position": {"minX": 426.0, "minY": 364.25, "maxX": 715.0, "maxY": 566.0}, "class_id": 4, "box_caption": "Glass 0.012", "scores": {"class_score": 0.0116119384765625}, "domain": "pixel"}, {"position": {"minX": 378.0, "minY": 401.5, "maxX": 612.5, "maxY": 483.0}, "class_id": 2, "box_caption": "Paper pack 0.012", "scores": {"class_score": 0.0115814208984375}, "domain": "pixel"}, {"position": {"minX": 498.25, "minY": 371.25, "maxX": 643.0, "maxY": 519.5}, "class_id": 7, "box_caption": "Plastic bag 0.011", "scores": {"class_score": 0.0114593505859375}, "domain": "pixel"}, {"position": {"minX": 507.0, "minY": 495.75, "maxX": 710.0, "maxY": 583.5}, "class_id": 2, "box_caption": "Paper pack 0.011", "scores": {"class_score": 0.01122283935546875}, "domain": "pixel"}, {"position": {"minX": 411.5, "minY": 461.5, "maxX": 788.5, "maxY": 587.5}, "class_id": 9, "box_caption": "Clothing 0.011", "scores": {"class_score": 0.0112152099609375}, "domain": "pixel"}, {"position": {"minX": 506.5, "minY": 364.75, "maxX": 587.5, "maxY": 532.5}, "class_id": 1, "box_caption": "Paper 0.011", "scores": {"class_score": 0.01116943359375}, "domain": "pixel"}, {"position": {"minX": 320.0, "minY": 819.0, "maxX": 419.0, "maxY": 1001.0}, "class_id": 4, "box_caption": "Glass 0.011", "scores": {"class_score": 0.01114654541015625}, "domain": "pixel"}, {"position": {"minX": 409.0, "minY": 504.25, "maxX": 727.0, "maxY": 599.5}, "class_id": 9, "box_caption": "Clothing 0.011", "scores": {"class_score": 0.011077880859375}, "domain": "pixel"}, {"position": {"minX": 382.0, "minY": 747.5, "maxX": 472.0, "maxY": 851.5}, "class_id": 5, "box_caption": "Plastic 0.011", "scores": {"class_score": 0.01105499267578125}, "domain": "pixel"}, {"position": {"minX": 378.0, "minY": 401.5, "maxX": 612.5, "maxY": 483.0}, "class_id": 8, "box_caption": "Battery 0.011", "scores": {"class_score": 0.0109100341796875}, "domain": "pixel"}, {"position": {"minX": 405.0, "minY": 640.5, "maxX": 522.5, "maxY": 762.5}, "class_id": 1, "box_caption": "Paper 0.011", "scores": {"class_score": 0.01085662841796875}, "domain": "pixel"}, {"position": {"minX": 504.5, "minY": 531.0, "maxX": 684.5, "maxY": 573.0}, "class_id": 6, "box_caption": "Styrofoam 0.011", "scores": {"class_score": 0.0108184814453125}, "domain": "pixel"}, {"position": {"minX": 598.5, "minY": 796.0, "maxX": 839.5, "maxY": 1032.0}, "class_id": 7, "box_caption": "Plastic bag 0.011", "scores": {"class_score": 0.01067352294921875}, "domain": "pixel"}, {"position": {"minX": 427.75, "minY": 275.5, "maxX": 540.0, "maxY": 383.0}, "class_id": 6, "box_caption": "Styrofoam 0.010", "scores": {"class_score": 0.010406494140625}, "domain": "pixel"}, {"position": {"minX": 516.0, "minY": 371.5, "maxX": 678.0, "maxY": 519.5}, "class_id": 2, "box_caption": "Paper pack 0.010", "scores": {"class_score": 0.01038360595703125}, "domain": "pixel"}, {"position": {"minX": 311.5, "minY": 778.0, "maxX": 454.5, "maxY": 1043.0}, "class_id": 9, "box_caption": "Clothing 0.010", "scores": {"class_score": 0.0103607177734375}, "domain": "pixel"}, {"position": {"minX": 427.75, "minY": 275.5, "maxX": 540.0, "maxY": 383.0}, "class_id": 2, "box_caption": "Paper pack 0.010", "scores": {"class_score": 0.01027679443359375}, "domain": "pixel"}, {"position": {"minX": 272.5, "minY": 528.0, "maxX": 380.5, "maxY": 580.0}, "class_id": 1, "box_caption": "Paper 0.010", "scores": {"class_score": 0.01027679443359375}, "domain": "pixel"}, {"position": {"minX": 311.5, "minY": 778.0, "maxX": 454.5, "maxY": 1043.0}, "class_id": 3, "box_caption": "Metal 0.010", "scores": {"class_score": 0.01015472412109375}, "domain": "pixel"}, {"position": {"minX": 431.5, "minY": 310.25, "maxX": 499.0, "maxY": 393.25}, "class_id": 0, "box_caption": "General trash 0.010", "scores": {"class_score": 0.0101165771484375}, "domain": "pixel"}, {"position": {"minX": 397.5, "minY": 514.5, "maxX": 738.5, "maxY": 575.5}, "class_id": 0, "box_caption": "General trash 0.010", "scores": {"class_score": 0.01003265380859375}, "domain": "pixel"}, {"position": {"minX": 411.5, "minY": 461.5, "maxX": 788.5, "maxY": 587.5}, "class_id": 4, "box_caption": "Glass 0.010", "scores": {"class_score": 0.01001739501953125}, "domain": "pixel"}, {"position": {"minX": 381.0, "minY": 399.0, "maxX": 563.5, "maxY": 589.5}, "class_id": 7, "box_caption": "Plastic bag 0.010", "scores": {"class_score": 0.0098419189453125}, "domain": "pixel"}, {"position": {"minX": 387.5, "minY": 525.5, "maxX": 592.5, "maxY": 582.5}, "class_id": 2, "box_caption": "Paper pack 0.010", "scores": {"class_score": 0.00966644287109375}, "domain": "pixel"}, {"position": {"minX": 431.5, "minY": 310.25, "maxX": 499.0, "maxY": 393.25}, "class_id": 1, "box_caption": "Paper 0.010", "scores": {"class_score": 0.0096588134765625}, "domain": "pixel"}, {"position": {"minX": 443.25, "minY": 314.5, "maxX": 528.0, "maxY": 389.0}, "class_id": 7, "box_caption": "Plastic bag 0.010", "scores": {"class_score": 0.0096588134765625}, "domain": "pixel"}, {"position": {"minX": 425.75, "minY": 501.0, "maxX": 759.0, "maxY": 601.0}, "class_id": 6, "box_caption": "Styrofoam 0.010", "scores": {"class_score": 0.00952911376953125}, "domain": "pixel"}, {"position": {"minX": 330.25, "minY": 777.0, "maxX": 443.75, "maxY": 982.0}, "class_id": 5, "box_caption": "Plastic 0.009", "scores": {"class_score": 0.00948333740234375}, "domain": "pixel"}, {"position": {"minX": 477.0, "minY": 288.75, "maxX": 537.0, "maxY": 363.75}, "class_id": 1, "box_caption": "Paper 0.009", "scores": {"class_score": 0.009429931640625}, "domain": "pixel"}, {"position": {"minX": 437.25, "minY": 395.0, "maxX": 570.5, "maxY": 524.5}, "class_id": 9, "box_caption": "Clothing 0.009", "scores": {"class_score": 0.00942230224609375}, "domain": "pixel"}, {"position": {"minX": 272.5, "minY": 528.0, "maxX": 380.5, "maxY": 580.0}, "class_id": 0, "box_caption": "General trash 0.009", "scores": {"class_score": 0.0094146728515625}, "domain": "pixel"}, {"position": {"minX": 417.5, "minY": 301.0, "maxX": 573.5, "maxY": 368.0}, "class_id": 8, "box_caption": "Battery 0.009", "scores": {"class_score": 0.00934600830078125}, "domain": "pixel"}, {"position": {"minX": 519.0, "minY": 402.5, "maxX": 789.0, "maxY": 578.5}, "class_id": 2, "box_caption": "Paper pack 0.009", "scores": {"class_score": 0.00933074951171875}, "domain": "pixel"}, {"position": {"minX": 30.796875, "minY": 515.0, "maxX": 78.4375, "maxY": 665.0}, "class_id": 1, "box_caption": "Paper 0.009", "scores": {"class_score": 0.0092620849609375}, "domain": "pixel"}, {"position": {"minX": 594.0, "minY": 381.5, "maxX": 727.0, "maxY": 574.0}, "class_id": 0, "box_caption": "General trash 0.009", "scores": {"class_score": 0.00923919677734375}, "domain": "pixel"}, {"position": {"minX": 521.0, "minY": 503.0, "maxX": 705.0, "maxY": 595.0}, "class_id": 4, "box_caption": "Glass 0.009", "scores": {"class_score": 0.0091705322265625}, "domain": "pixel"}, {"position": {"minX": 375.5, "minY": 506.75, "maxX": 946.5, "maxY": 605.5}, "class_id": 1, "box_caption": "Paper 0.009", "scores": {"class_score": 0.0091705322265625}, "domain": "pixel"}, {"position": {"minX": 538.5, "minY": 369.0, "maxX": 622.5, "maxY": 550.5}, "class_id": 0, "box_caption": "General trash 0.009", "scores": {"class_score": 0.0091552734375}, "domain": "pixel"}, {"position": {"minX": 390.0, "minY": 421.5, "maxX": 660.0, "maxY": 562.0}, "class_id": 9, "box_caption": "Clothing 0.009", "scores": {"class_score": 0.0091094970703125}, "domain": "pixel"}, {"position": {"minX": 53.90625, "minY": 39.75, "maxX": 180.375, "maxY": 103.5}, "class_id": 1, "box_caption": "Paper 0.009", "scores": {"class_score": 0.00899505615234375}, "domain": "pixel"}, {"position": {"minX": 432.25, "minY": 274.5, "maxX": 539.0, "maxY": 384.0}, "class_id": 3, "box_caption": "Metal 0.009", "scores": {"class_score": 0.00896453857421875}, "domain": "pixel"}, {"position": {"minX": 417.5, "minY": 301.0, "maxX": 573.5, "maxY": 368.0}, "class_id": 3, "box_caption": "Metal 0.009", "scores": {"class_score": 0.0089569091796875}, "domain": "pixel"}, {"position": {"minX": 114.0, "minY": -4.75, "maxX": 295.25, "maxY": 353.75}, "class_id": 1, "box_caption": "Paper 0.009", "scores": {"class_score": 0.00894927978515625}, "domain": "pixel"}, {"position": {"minX": 497.5, "minY": 367.0, "maxX": 722.5, "maxY": 624.5}, "class_id": 7, "box_caption": "Plastic bag 0.009", "scores": {"class_score": 0.00890350341796875}, "domain": "pixel"}, {"position": {"minX": 356.25, "minY": 780.0, "maxX": 433.25, "maxY": 1033.0}, "class_id": 0, "box_caption": "General trash 0.009", "scores": {"class_score": 0.008880615234375}, "domain": "pixel"}, {"position": {"minX": 427.75, "minY": 275.5, "maxX": 540.0, "maxY": 383.0}, "class_id": 4, "box_caption": "Glass 0.009", "scores": {"class_score": 0.00887298583984375}, "domain": "pixel"}, {"position": {"minX": 309.25, "minY": 823.0, "maxX": 473.25, "maxY": 933.0}, "class_id": 1, "box_caption": "Paper 0.009", "scores": {"class_score": 0.00885772705078125}, "domain": "pixel"}, {"position": {"minX": 594.0, "minY": 381.5, "maxX": 727.0, "maxY": 574.0}, "class_id": 7, "box_caption": "Plastic bag 0.009", "scores": {"class_score": 0.00885009765625}, "domain": "pixel"}, {"position": {"minX": 468.5, "minY": 361.75, "maxX": 729.5, "maxY": 560.0}, "class_id": 8, "box_caption": "Battery 0.009", "scores": {"class_score": 0.0088043212890625}, "domain": "pixel"}, {"position": {"minX": 114.0, "minY": -4.75, "maxX": 295.25, "maxY": 353.75}, "class_id": 5, "box_caption": "Plastic 0.009", "scores": {"class_score": 0.0087432861328125}, "domain": "pixel"}, {"position": {"minX": 19.28125, "minY": 602.5, "maxX": 79.25, "maxY": 849.5}, "class_id": 6, "box_caption": "Styrofoam 0.009", "scores": {"class_score": 0.008697509765625}, "domain": "pixel"}, {"position": {"minX": 379.5, "minY": 383.0, "maxX": 561.0, "maxY": 499.0}, "class_id": 5, "box_caption": "Plastic 0.009", "scores": {"class_score": 0.0086517333984375}, "domain": "pixel"}, {"position": {"minX": 399.5, "minY": 429.0, "maxX": 595.0, "maxY": 570.0}, "class_id": 0, "box_caption": "General trash 0.009", "scores": {"class_score": 0.00860595703125}, "domain": "pixel"}, {"position": {"minX": 305.5, "minY": 507.0, "maxX": 402.0, "maxY": 572.0}, "class_id": 0, "box_caption": "General trash 0.009", "scores": {"class_score": 0.0085296630859375}, "domain": "pixel"}, {"position": {"minX": 305.5, "minY": 507.0, "maxX": 402.0, "maxY": 572.0}, "class_id": 1, "box_caption": "Paper 0.009", "scores": {"class_score": 0.008514404296875}, "domain": "pixel"}, {"position": {"minX": 424.0, "minY": 357.25, "maxX": 602.0, "maxY": 592.0}, "class_id": 0, "box_caption": "General trash 0.008", "scores": {"class_score": 0.0084991455078125}, "domain": "pixel"}, {"position": {"minX": 521.0, "minY": 503.0, "maxX": 705.0, "maxY": 595.0}, "class_id": 7, "box_caption": "Plastic bag 0.008", "scores": {"class_score": 0.0084381103515625}, "domain": "pixel"}, {"position": {"minX": 32.0625, "minY": 849.5, "maxX": 186.0, "maxY": 1026.0}, "class_id": 7, "box_caption": "Plastic bag 0.008", "scores": {"class_score": 0.008392333984375}, "domain": "pixel"}, {"position": {"minX": 30.796875, "minY": 515.0, "maxX": 78.4375, "maxY": 665.0}, "class_id": 7, "box_caption": "Plastic bag 0.008", "scores": {"class_score": 0.00836181640625}, "domain": "pixel"}, {"position": {"minX": 391.5, "minY": 736.0, "maxX": 471.5, "maxY": 829.0}, "class_id": 0, "box_caption": "General trash 0.008", "scores": {"class_score": 0.0083160400390625}, "domain": "pixel"}, {"position": {"minX": 498.0, "minY": 388.5, "maxX": 697.0, "maxY": 487.0}, "class_id": 7, "box_caption": "Plastic bag 0.008", "scores": {"class_score": 0.00830841064453125}, "domain": "pixel"}, {"position": {"minX": 431.5, "minY": 310.25, "maxX": 499.0, "maxY": 393.25}, "class_id": 7, "box_caption": "Plastic bag 0.008", "scores": {"class_score": 0.008270263671875}, "domain": "pixel"}, {"position": {"minX": 596.0, "minY": 405.0, "maxX": 716.0, "maxY": 528.0}, "class_id": 0, "box_caption": "General trash 0.008", "scores": {"class_score": 0.0082244873046875}, "domain": "pixel"}, {"position": {"minX": 433.0, "minY": 371.75, "maxX": 623.0, "maxY": 515.0}, "class_id": 5, "box_caption": "Plastic 0.008", "scores": {"class_score": 0.00818634033203125}, "domain": "pixel"}, {"position": {"minX": 416.5, "minY": 263.25, "maxX": 574.0, "maxY": 356.25}, "class_id": 5, "box_caption": "Plastic 0.008", "scores": {"class_score": 0.00818634033203125}, "domain": "pixel"}, {"position": {"minX": 416.5, "minY": 263.25, "maxX": 574.0, "maxY": 356.25}, "class_id": 3, "box_caption": "Metal 0.008", "scores": {"class_score": 0.0081634521484375}, "domain": "pixel"}, {"position": {"minX": 529.0, "minY": 520.5, "maxX": 727.0, "maxY": 586.5}, "class_id": 2, "box_caption": "Paper pack 0.008", "scores": {"class_score": 0.00815582275390625}, "domain": "pixel"}, {"position": {"minX": 521.5, "minY": 399.5, "maxX": 732.5, "maxY": 472.0}, "class_id": 4, "box_caption": "Glass 0.008", "scores": {"class_score": 0.00815582275390625}, "domain": "pixel"}, {"position": {"minX": 438.5, "minY": 504.25, "maxX": 758.5, "maxY": 606.5}, "class_id": 5, "box_caption": "Plastic 0.008", "scores": {"class_score": 0.00814056396484375}, "domain": "pixel"}, {"position": {"minX": 538.5, "minY": 369.0, "maxX": 622.5, "maxY": 550.5}, "class_id": 7, "box_caption": "Plastic bag 0.008", "scores": {"class_score": 0.0081329345703125}, "domain": "pixel"}, {"position": {"minX": 13.09375, "minY": 570.0, "maxX": 97.625, "maxY": 827.0}, "class_id": 1, "box_caption": "Paper 0.008", "scores": {"class_score": 0.0081329345703125}, "domain": "pixel"}, {"position": {"minX": 381.0, "minY": 399.0, "maxX": 563.5, "maxY": 589.5}, "class_id": 2, "box_caption": "Paper pack 0.008", "scores": {"class_score": 0.00812530517578125}, "domain": "pixel"}, {"position": {"minX": 443.25, "minY": 314.5, "maxX": 528.0, "maxY": 389.0}, "class_id": 0, "box_caption": "General trash 0.008", "scores": {"class_score": 0.00811767578125}, "domain": "pixel"}, {"position": {"minX": 544.5, "minY": 385.0, "maxX": 567.5, "maxY": 512.5}, "class_id": 0, "box_caption": "General trash 0.008", "scores": {"class_score": 0.00809478759765625}, "domain": "pixel"}, {"position": {"minX": 544.0, "minY": 394.75, "maxX": 589.0, "maxY": 524.5}, "class_id": 3, "box_caption": "Metal 0.008", "scores": {"class_score": 0.00801849365234375}, "domain": "pixel"}, {"position": {"minX": 624.0, "minY": 807.5, "maxX": 791.0, "maxY": 950.5}, "class_id": 7, "box_caption": "Plastic bag 0.008", "scores": {"class_score": 0.00801849365234375}, "domain": "pixel"}, {"position": {"minX": 528.0, "minY": 405.0, "maxX": 715.0, "maxY": 551.0}, "class_id": 5, "box_caption": "Plastic 0.008", "scores": {"class_score": 0.0080108642578125}, "domain": "pixel"}, {"position": {"minX": 304.75, "minY": 776.0, "maxX": 429.25, "maxY": 1045.0}, "class_id": 4, "box_caption": "Glass 0.008", "scores": {"class_score": 0.0079803466796875}, "domain": "pixel"}, {"position": {"minX": 453.25, "minY": 248.75, "maxX": 532.0, "maxY": 374.75}, "class_id": 1, "box_caption": "Paper 0.008", "scores": {"class_score": 0.00794219970703125}, "domain": "pixel"}, {"position": {"minX": 416.0, "minY": 537.0, "maxX": 594.0, "maxY": 593.0}, "class_id": 1, "box_caption": "Paper 0.008", "scores": {"class_score": 0.0079193115234375}, "domain": "pixel"}, {"position": {"minX": 18.0625, "minY": 544.0, "maxX": 82.4375, "maxY": 655.0}, "class_id": 5, "box_caption": "Plastic 0.008", "scores": {"class_score": 0.00791168212890625}, "domain": "pixel"}, {"position": {"minX": 584.0, "minY": 397.0, "maxX": 736.0, "maxY": 491.5}, "class_id": 1, "box_caption": "Paper 0.008", "scores": {"class_score": 0.00785064697265625}, "domain": "pixel"}, {"position": {"minX": 424.0, "minY": 357.25, "maxX": 602.0, "maxY": 592.0}, "class_id": 7, "box_caption": "Plastic bag 0.008", "scores": {"class_score": 0.00785064697265625}, "domain": "pixel"}, {"position": {"minX": 18.0625, "minY": 544.0, "maxX": 82.4375, "maxY": 655.0}, "class_id": 1, "box_caption": "Paper 0.008", "scores": {"class_score": 0.00783538818359375}, "domain": "pixel"}, {"position": {"minX": 430.0, "minY": 493.25, "maxX": 574.5, "maxY": 550.0}, "class_id": 1, "box_caption": "Paper 0.008", "scores": {"class_score": 0.0078277587890625}, "domain": "pixel"}, {"position": {"minX": 26.015625, "minY": 627.5, "maxX": 73.125, "maxY": 875.5}, "class_id": 7, "box_caption": "Plastic bag 0.008", "scores": {"class_score": 0.007770538330078125}, "domain": "pixel"}, {"position": {"minX": 446.0, "minY": 381.25, "maxX": 747.0, "maxY": 477.75}, "class_id": 1, "box_caption": "Paper 0.008", "scores": {"class_score": 0.007770538330078125}, "domain": "pixel"}, {"position": {"minX": 452.75, "minY": 300.25, "maxX": 496.25, "maxY": 387.25}, "class_id": 1, "box_caption": "Paper 0.008", "scores": {"class_score": 0.007740020751953125}, "domain": "pixel"}, {"position": {"minX": 264.5, "minY": 501.5, "maxX": 391.0, "maxY": 577.5}, "class_id": 1, "box_caption": "Paper 0.008", "scores": {"class_score": 0.00772857666015625}, "domain": "pixel"}, {"position": {"minX": 418.0, "minY": 525.5, "maxX": 619.0, "maxY": 580.5}, "class_id": 1, "box_caption": "Paper 0.008", "scores": {"class_score": 0.007717132568359375}, "domain": "pixel"}, {"position": {"minX": 411.5, "minY": 461.5, "maxX": 788.5, "maxY": 587.5}, "class_id": 8, "box_caption": "Battery 0.008", "scores": {"class_score": 0.007694244384765625}, "domain": "pixel"}, {"position": {"minX": 387.5, "minY": 525.5, "maxX": 592.5, "maxY": 582.5}, "class_id": 6, "box_caption": "Styrofoam 0.008", "scores": {"class_score": 0.0076904296875}, "domain": "pixel"}, {"position": {"minX": 399.5, "minY": 253.625, "maxX": 534.0, "maxY": 375.5}, "class_id": 2, "box_caption": "Paper pack 0.008", "scores": {"class_score": 0.007686614990234375}, "domain": "pixel"}, {"position": {"minX": 624.0, "minY": 807.5, "maxX": 791.0, "maxY": 950.5}, "class_id": 5, "box_caption": "Plastic 0.008", "scores": {"class_score": 0.007663726806640625}, "domain": "pixel"}, {"position": {"minX": 443.25, "minY": 314.5, "maxX": 528.0, "maxY": 389.0}, "class_id": 1, "box_caption": "Paper 0.008", "scores": {"class_score": 0.007656097412109375}, "domain": "pixel"}, {"position": {"minX": 498.25, "minY": 371.25, "maxX": 643.0, "maxY": 519.5}, "class_id": 3, "box_caption": "Metal 0.008", "scores": {"class_score": 0.00762939453125}, "domain": "pixel"}, {"position": {"minX": 390.0, "minY": 421.5, "maxX": 660.0, "maxY": 562.0}, "class_id": 8, "box_caption": "Battery 0.008", "scores": {"class_score": 0.007617950439453125}, "domain": "pixel"}, {"position": {"minX": 499.25, "minY": 409.75, "maxX": 712.0, "maxY": 552.0}, "class_id": 2, "box_caption": "Paper pack 0.008", "scores": {"class_score": 0.007564544677734375}, "domain": "pixel"}, {"position": {"minX": 381.0, "minY": 479.0, "maxX": 1013.0, "maxY": 644.0}, "class_id": 1, "box_caption": "Paper 0.008", "scores": {"class_score": 0.007549285888671875}, "domain": "pixel"}, {"position": {"minX": 521.0, "minY": 503.0, "maxX": 705.0, "maxY": 595.0}, "class_id": 6, "box_caption": "Styrofoam 0.008", "scores": {"class_score": 0.007534027099609375}, "domain": "pixel"}, {"position": {"minX": 433.0, "minY": 371.75, "maxX": 623.0, "maxY": 515.0}, "class_id": 2, "box_caption": "Paper pack 0.007", "scores": {"class_score": 0.00748443603515625}, "domain": "pixel"}, {"position": {"minX": 325.0, "minY": 805.0, "maxX": 422.5, "maxY": 962.0}, "class_id": 2, "box_caption": "Paper pack 0.007", "scores": {"class_score": 0.00748443603515625}, "domain": "pixel"}, {"position": {"minX": 552.0, "minY": 410.5, "maxX": 587.0, "maxY": 498.0}, "class_id": 1, "box_caption": "Paper 0.007", "scores": {"class_score": 0.007465362548828125}, "domain": "pixel"}, {"position": {"minX": 416.0, "minY": 537.0, "maxX": 594.0, "maxY": 593.0}, "class_id": 2, "box_caption": "Paper pack 0.007", "scores": {"class_score": 0.007427215576171875}, "domain": "pixel"}, {"position": {"minX": 18.0625, "minY": 544.0, "maxX": 82.4375, "maxY": 655.0}, "class_id": 0, "box_caption": "General trash 0.007", "scores": {"class_score": 0.007381439208984375}, "domain": "pixel"}, {"position": {"minX": 71.75, "minY": 465.5, "maxX": 541.0, "maxY": 855.5}, "class_id": 1, "box_caption": "Paper 0.007", "scores": {"class_score": 0.007381439208984375}, "domain": "pixel"}, {"position": {"minX": 416.5, "minY": 263.25, "maxX": 574.0, "maxY": 356.25}, "class_id": 8, "box_caption": "Battery 0.007", "scores": {"class_score": 0.007343292236328125}, "domain": "pixel"}, {"position": {"minX": 521.5, "minY": 399.5, "maxX": 732.5, "maxY": 472.0}, "class_id": 3, "box_caption": "Metal 0.007", "scores": {"class_score": 0.007343292236328125}, "domain": "pixel"}, {"position": {"minX": 53.90625, "minY": 39.75, "maxX": 180.375, "maxY": 103.5}, "class_id": 7, "box_caption": "Plastic bag 0.007", "scores": {"class_score": 0.0073394775390625}, "domain": "pixel"}, {"position": {"minX": 519.0, "minY": 402.5, "maxX": 789.0, "maxY": 578.5}, "class_id": 8, "box_caption": "Battery 0.007", "scores": {"class_score": 0.0073394775390625}, "domain": "pixel"}, {"position": {"minX": 400.0, "minY": 547.0, "maxX": 579.0, "maxY": 586.0}, "class_id": 5, "box_caption": "Plastic 0.007", "scores": {"class_score": 0.0072784423828125}, "domain": "pixel"}, {"position": {"minX": 101.75, "minY": 430.75, "maxX": 172.25, "maxY": 572.0}, "class_id": 1, "box_caption": "Paper 0.007", "scores": {"class_score": 0.0072479248046875}, "domain": "pixel"}, {"position": {"minX": 529.0, "minY": 520.5, "maxX": 727.0, "maxY": 586.5}, "class_id": 5, "box_caption": "Plastic 0.007", "scores": {"class_score": 0.007213592529296875}, "domain": "pixel"}, {"position": {"minX": 492.0, "minY": 386.0, "maxX": 576.0, "maxY": 517.5}, "class_id": 0, "box_caption": "General trash 0.007", "scores": {"class_score": 0.007198333740234375}, "domain": "pixel"}, {"position": {"minX": 645.0, "minY": 823.0, "maxX": 776.0, "maxY": 925.0}, "class_id": 7, "box_caption": "Plastic bag 0.007", "scores": {"class_score": 0.007190704345703125}, "domain": "pixel"}, {"position": {"minX": 461.5, "minY": 363.0, "maxX": 572.5, "maxY": 562.5}, "class_id": 3, "box_caption": "Metal 0.007", "scores": {"class_score": 0.007160186767578125}, "domain": "pixel"}, {"position": {"minX": 340.5, "minY": 794.0, "maxX": 429.0, "maxY": 946.0}, "class_id": 1, "box_caption": "Paper 0.007", "scores": {"class_score": 0.007144927978515625}, "domain": "pixel"}, {"position": {"minX": 417.0, "minY": 436.0, "maxX": 778.0, "maxY": 624.0}, "class_id": 2, "box_caption": "Paper pack 0.007", "scores": {"class_score": 0.007122039794921875}, "domain": "pixel"}, {"position": {"minX": 515.5, "minY": 400.25, "maxX": 666.5, "maxY": 523.5}, "class_id": 6, "box_caption": "Styrofoam 0.007", "scores": {"class_score": 0.00708770751953125}, "domain": "pixel"}, {"position": {"minX": 25.78125, "minY": 574.5, "maxX": 87.25, "maxY": 853.5}, "class_id": 3, "box_caption": "Metal 0.007", "scores": {"class_score": 0.007083892822265625}, "domain": "pixel"}, {"position": {"minX": 705.5, "minY": 361.5, "maxX": 843.5, "maxY": 420.5}, "class_id": 1, "box_caption": "Paper 0.007", "scores": {"class_score": 0.007061004638671875}, "domain": "pixel"}, {"position": {"minX": 114.0, "minY": -4.75, "maxX": 295.25, "maxY": 353.75}, "class_id": 0, "box_caption": "General trash 0.007", "scores": {"class_score": 0.00702667236328125}, "domain": "pixel"}, {"position": {"minX": 264.5, "minY": 501.5, "maxX": 391.0, "maxY": 577.5}, "class_id": 5, "box_caption": "Plastic 0.007", "scores": {"class_score": 0.006992340087890625}, "domain": "pixel"}, {"position": {"minX": 438.5, "minY": 504.25, "maxX": 758.5, "maxY": 606.5}, "class_id": 8, "box_caption": "Battery 0.007", "scores": {"class_score": 0.006923675537109375}, "domain": "pixel"}], "class_labels": {"0": "General trash", "1": "Paper", "2": "Paper pack", "3": "Metal", "4": "Glass", "5": "Plastic", "6": "Styrofoam", "7": "Plastic bag", "8": "Battery", "9": "Clothing"}}