{"box_data": [{"position": {"minX": 391.25, "minY": 364.0, "maxX": 674.0, "maxY": 780.0}, "class_id": 0, "box_caption": "General trash 0.260", "scores": {"class_score": 0.26025390625}, "domain": "pixel"}, {"position": {"minX": 393.5, "minY": 361.5, "maxX": 677.5, "maxY": 784.5}, "class_id": 5, "box_caption": "Plastic 0.156", "scores": {"class_score": 0.1558837890625}, "domain": "pixel"}, {"position": {"minX": 391.25, "minY": 364.0, "maxX": 674.0, "maxY": 780.0}, "class_id": 7, "box_caption": "Plastic bag 0.087", "scores": {"class_score": 0.0869140625}, "domain": "pixel"}, {"position": {"minX": 386.25, "minY": 366.5, "maxX": 678.0, "maxY": 776.5}, "class_id": 3, "box_caption": "Metal 0.074", "scores": {"class_score": 0.074462890625}, "domain": "pixel"}, {"position": {"minX": 391.25, "minY": 364.0, "maxX": 674.0, "maxY": 780.0}, "class_id": 2, "box_caption": "Paper pack 0.062", "scores": {"class_score": 0.062286376953125}, "domain": "pixel"}, {"position": {"minX": 391.25, "minY": 364.0, "maxX": 674.0, "maxY": 780.0}, "class_id": 1, "box_caption": "Paper 0.060", "scores": {"class_score": 0.059539794921875}, "domain": "pixel"}, {"position": {"minX": 493.5, "minY": 639.0, "maxX": 607.5, "maxY": 794.0}, "class_id": 1, "box_caption": "Paper 0.053", "scores": {"class_score": 0.0531005859375}, "domain": "pixel"}, {"position": {"minX": 489.5, "minY": 638.0, "maxX": 605.5, "maxY": 797.0}, "class_id": 0, "box_caption": "General trash 0.040", "scores": {"class_score": 0.040313720703125}, "domain": "pixel"}, {"position": {"minX": 489.5, "minY": 638.0, "maxX": 605.5, "maxY": 797.0}, "class_id": 7, "box_caption": "Plastic bag 0.020", "scores": {"class_score": 0.019805908203125}, "domain": "pixel"}, {"position": {"minX": 17.3125, "minY": 268.25, "maxX": 150.5, "maxY": 403.75}, "class_id": 3, "box_caption": "Metal 0.017", "scores": {"class_score": 0.016693115234375}, "domain": "pixel"}, {"position": {"minX": 391.25, "minY": 364.0, "maxX": 674.0, "maxY": 780.0}, "class_id": 9, "box_caption": "Clothing 0.017", "scores": {"class_score": 0.0166015625}, "domain": "pixel"}, {"position": {"minX": 393.5, "minY": 361.5, "maxX": 677.5, "maxY": 784.5}, "class_id": 4, "box_caption": "Glass 0.015", "scores": {"class_score": 0.015045166015625}, "domain": "pixel"}, {"position": {"minX": 787.5, "minY": 892.0, "maxX": 948.5, "maxY": 1047.0}, "class_id": 7, "box_caption": "Plastic bag 0.015", "scores": {"class_score": 0.0146484375}, "domain": "pixel"}, {"position": {"minX": 787.5, "minY": 892.0, "maxX": 948.5, "maxY": 1047.0}, "class_id": 5, "box_caption": "Plastic 0.014", "scores": {"class_score": 0.0140228271484375}, "domain": "pixel"}, {"position": {"minX": 786.0, "minY": 891.0, "maxX": 949.0, "maxY": 1047.0}, "class_id": 0, "box_caption": "General trash 0.014", "scores": {"class_score": 0.0139007568359375}, "domain": "pixel"}, {"position": {"minX": 386.25, "minY": 366.5, "maxX": 678.0, "maxY": 776.5}, "class_id": 6, "box_caption": "Styrofoam 0.012", "scores": {"class_score": 0.01189422607421875}, "domain": "pixel"}, {"position": {"minX": 489.5, "minY": 638.0, "maxX": 605.5, "maxY": 797.0}, "class_id": 3, "box_caption": "Metal 0.011", "scores": {"class_score": 0.0106353759765625}, "domain": "pixel"}, {"position": {"minX": 21.3125, "minY": 254.5, "maxX": 185.0, "maxY": 409.0}, "class_id": 5, "box_caption": "Plastic 0.010", "scores": {"class_score": 0.01041412353515625}, "domain": "pixel"}, {"position": {"minX": 794.0, "minY": 889.0, "maxX": 934.0, "maxY": 1043.0}, "class_id": 3, "box_caption": "Metal 0.010", "scores": {"class_score": 0.00981903076171875}, "domain": "pixel"}, {"position": {"minX": 627.5, "minY": 1016.0, "maxX": 824.5, "maxY": 1040.0}, "class_id": 7, "box_caption": "Plastic bag 0.009", "scores": {"class_score": 0.00872802734375}, "domain": "pixel"}, {"position": {"minX": 898.5, "minY": 769.0, "maxX": 1038.0, "maxY": 876.0}, "class_id": 0, "box_caption": "General trash 0.008", "scores": {"class_score": 0.0076446533203125}, "domain": "pixel"}, {"position": {"minX": 489.5, "minY": 638.0, "maxX": 605.5, "maxY": 797.0}, "class_id": 5, "box_caption": "Plastic 0.008", "scores": {"class_score": 0.007572174072265625}, "domain": "pixel"}, {"position": {"minX": 489.5, "minY": 638.0, "maxX": 605.5, "maxY": 797.0}, "class_id": 4, "box_caption": "Glass 0.007", "scores": {"class_score": 0.0071563720703125}, "domain": "pixel"}, {"position": {"minX": 782.5, "minY": 819.5, "maxX": 1051.0, "maxY": 1048.0}, "class_id": 5, "box_caption": "Plastic 0.007", "scores": {"class_score": 0.006786346435546875}, "domain": "pixel"}, {"position": {"minX": 493.5, "minY": 639.0, "maxX": 607.5, "maxY": 794.0}, "class_id": 2, "box_caption": "Paper pack 0.007", "scores": {"class_score": 0.00669097900390625}, "domain": "pixel"}, {"position": {"minX": 46.03125, "minY": 342.0, "maxX": 138.75, "maxY": 397.5}, "class_id": 3, "box_caption": "Metal 0.006", "scores": {"class_score": 0.006473541259765625}, "domain": "pixel"}, {"position": {"minX": 781.0, "minY": 868.0, "maxX": 947.0, "maxY": 1037.0}, "class_id": 4, "box_caption": "Glass 0.006", "scores": {"class_score": 0.006465911865234375}, "domain": "pixel"}, {"position": {"minX": 386.25, "minY": 366.5, "maxX": 678.0, "maxY": 776.5}, "class_id": 8, "box_caption": "Battery 0.006", "scores": {"class_score": 0.006214141845703125}, "domain": "pixel"}, {"position": {"minX": 786.0, "minY": 891.0, "maxX": 949.0, "maxY": 1047.0}, "class_id": 9, "box_caption": "Clothing 0.006", "scores": {"class_score": 0.0060882568359375}, "domain": "pixel"}, {"position": {"minX": 70.625, "minY": 14.5, "maxX": 159.0, "maxY": 54.0625}, "class_id": 3, "box_caption": "Metal 0.006", "scores": {"class_score": 0.005756378173828125}, "domain": "pixel"}, {"position": {"minX": 433.0, "minY": 477.75, "maxX": 470.5, "maxY": 505.75}, "class_id": 3, "box_caption": "Metal 0.006", "scores": {"class_score": 0.005645751953125}, "domain": "pixel"}, {"position": {"minX": 747.5, "minY": 801.0, "maxX": 943.5, "maxY": 1045.0}, "class_id": 0, "box_caption": "General trash 0.005", "scores": {"class_score": 0.005401611328125}, "domain": "pixel"}, {"position": {"minX": 438.75, "minY": 486.0, "maxX": 467.25, "maxY": 515.0}, "class_id": 3, "box_caption": "Metal 0.005", "scores": {"class_score": 0.005374908447265625}, "domain": "pixel"}, {"position": {"minX": 761.0, "minY": 721.0, "maxX": 1050.0, "maxY": 1051.0}, "class_id": 0, "box_caption": "General trash 0.005", "scores": {"class_score": 0.005207061767578125}, "domain": "pixel"}, {"position": {"minX": 253.125, "minY": 358.5, "maxX": 647.0, "maxY": 761.5}, "class_id": 7, "box_caption": "Plastic bag 0.005", "scores": {"class_score": 0.004993438720703125}, "domain": "pixel"}, {"position": {"minX": 253.125, "minY": 358.5, "maxX": 647.0, "maxY": 761.5}, "class_id": 3, "box_caption": "Metal 0.005", "scores": {"class_score": 0.00481414794921875}, "domain": "pixel"}, {"position": {"minX": 491.25, "minY": 644.0, "maxX": 608.5, "maxY": 796.0}, "class_id": 9, "box_caption": "Clothing 0.005", "scores": {"class_score": 0.004741668701171875}, "domain": "pixel"}, {"position": {"minX": 62.53125, "minY": 336.75, "maxX": 144.75, "maxY": 392.25}, "class_id": 5, "box_caption": "Plastic 0.005", "scores": {"class_score": 0.0045928955078125}, "domain": "pixel"}, {"position": {"minX": 627.5, "minY": 1016.0, "maxX": 824.5, "maxY": 1040.0}, "class_id": 5, "box_caption": "Plastic 0.004", "scores": {"class_score": 0.004116058349609375}, "domain": "pixel"}, {"position": {"minX": 489.5, "minY": 638.0, "maxX": 605.5, "maxY": 797.0}, "class_id": 8, "box_caption": "Battery 0.004", "scores": {"class_score": 0.004108428955078125}, "domain": "pixel"}, {"position": {"minX": 30.75, "minY": 292.5, "maxX": 181.25, "maxY": 416.0}, "class_id": 3, "box_caption": "Metal 0.004", "scores": {"class_score": 0.004032135009765625}, "domain": "pixel"}, {"position": {"minX": 430.75, "minY": 538.5, "maxX": 444.75, "maxY": 573.5}, "class_id": 3, "box_caption": "Metal 0.004", "scores": {"class_score": 0.004024505615234375}, "domain": "pixel"}, {"position": {"minX": 909.0, "minY": 783.0, "maxX": 1037.0, "maxY": 873.0}, "class_id": 3, "box_caption": "Metal 0.004", "scores": {"class_score": 0.00392913818359375}, "domain": "pixel"}, {"position": {"minX": 409.75, "minY": 574.5, "maxX": 431.25, "maxY": 632.5}, "class_id": 3, "box_caption": "Metal 0.004", "scores": {"class_score": 0.003910064697265625}, "domain": "pixel"}, {"position": {"minX": 747.5, "minY": 801.0, "maxX": 943.5, "maxY": 1045.0}, "class_id": 7, "box_caption": "Plastic bag 0.004", "scores": {"class_score": 0.0038623809814453125}, "domain": "pixel"}, {"position": {"minX": 430.75, "minY": 538.5, "maxX": 444.75, "maxY": 573.5}, "class_id": 5, "box_caption": "Plastic 0.004", "scores": {"class_score": 0.0038585662841796875}, "domain": "pixel"}, {"position": {"minX": 601.0, "minY": 1017.5, "maxX": 804.0, "maxY": 1044.0}, "class_id": 3, "box_caption": "Metal 0.004", "scores": {"class_score": 0.0038299560546875}, "domain": "pixel"}, {"position": {"minX": 895.5, "minY": 731.0, "maxX": 1041.0, "maxY": 959.0}, "class_id": 0, "box_caption": "General trash 0.004", "scores": {"class_score": 0.00382232666015625}, "domain": "pixel"}, {"position": {"minX": 756.5, "minY": 971.5, "maxX": 834.5, "maxY": 1036.0}, "class_id": 5, "box_caption": "Plastic 0.004", "scores": {"class_score": 0.003570556640625}, "domain": "pixel"}, {"position": {"minX": 253.125, "minY": 358.5, "maxX": 647.0, "maxY": 761.5}, "class_id": 0, "box_caption": "General trash 0.004", "scores": {"class_score": 0.003505706787109375}, "domain": "pixel"}, {"position": {"minX": 388.5, "minY": 618.5, "maxX": 590.5, "maxY": 760.5}, "class_id": 4, "box_caption": "Glass 0.003", "scores": {"class_score": 0.0033931732177734375}, "domain": "pixel"}, {"position": {"minX": 440.0, "minY": 487.5, "maxX": 466.5, "maxY": 514.0}, "class_id": 5, "box_caption": "Plastic 0.003", "scores": {"class_score": 0.003387451171875}, "domain": "pixel"}, {"position": {"minX": 46.25, "minY": 321.25, "maxX": 179.75, "maxY": 405.75}, "class_id": 5, "box_caption": "Plastic 0.003", "scores": {"class_score": 0.0032444000244140625}, "domain": "pixel"}, {"position": {"minX": 410.75, "minY": 631.0, "maxX": 597.0, "maxY": 790.0}, "class_id": 1, "box_caption": "Paper 0.003", "scores": {"class_score": 0.00323486328125}, "domain": "pixel"}, {"position": {"minX": 747.5, "minY": 801.0, "maxX": 943.5, "maxY": 1045.0}, "class_id": 3, "box_caption": "Metal 0.003", "scores": {"class_score": 0.0032253265380859375}, "domain": "pixel"}, {"position": {"minX": 388.0, "minY": 512.0, "maxX": 607.5, "maxY": 809.0}, "class_id": 3, "box_caption": "Metal 0.003", "scores": {"class_score": 0.003063201904296875}, "domain": "pixel"}, {"position": {"minX": 629.0, "minY": 1016.0, "maxX": 802.0, "maxY": 1042.0}, "class_id": 0, "box_caption": "General trash 0.003", "scores": {"class_score": 0.00296783447265625}, "domain": "pixel"}, {"position": {"minX": 308.0, "minY": 754.0, "maxX": 339.0, "maxY": 836.0}, "class_id": 5, "box_caption": "Plastic 0.003", "scores": {"class_score": 0.002819061279296875}, "domain": "pixel"}, {"position": {"minX": 241.875, "minY": 822.0, "maxX": 348.0, "maxY": 890.0}, "class_id": 4, "box_caption": "Glass 0.003", "scores": {"class_score": 0.0027561187744140625}, "domain": "pixel"}, {"position": {"minX": 446.0, "minY": 625.5, "maxX": 521.5, "maxY": 728.5}, "class_id": 4, "box_caption": "Glass 0.003", "scores": {"class_score": 0.0027408599853515625}, "domain": "pixel"}, {"position": {"minX": -51.75, "minY": 5.25, "maxX": 736.0, "maxY": 790.0}, "class_id": 3, "box_caption": "Metal 0.003", "scores": {"class_score": 0.0026836395263671875}, "domain": "pixel"}, {"position": {"minX": 446.5, "minY": 487.0, "maxX": 472.0, "maxY": 516.5}, "class_id": 3, "box_caption": "Metal 0.003", "scores": {"class_score": 0.00267791748046875}, "domain": "pixel"}, {"position": {"minX": 410.75, "minY": 631.0, "maxX": 597.0, "maxY": 790.0}, "class_id": 0, "box_caption": "General trash 0.003", "scores": {"class_score": 0.0026607513427734375}, "domain": "pixel"}, {"position": {"minX": 70.625, "minY": 14.5, "maxX": 159.0, "maxY": 54.0625}, "class_id": 5, "box_caption": "Plastic 0.003", "scores": {"class_score": 0.00263214111328125}, "domain": "pixel"}, {"position": {"minX": 440.25, "minY": 631.5, "maxX": 529.0, "maxY": 740.5}, "class_id": 3, "box_caption": "Metal 0.003", "scores": {"class_score": 0.002582550048828125}, "domain": "pixel"}, {"position": {"minX": 19.21875, "minY": 268.5, "maxX": 138.125, "maxY": 394.5}, "class_id": 5, "box_caption": "Plastic 0.003", "scores": {"class_score": 0.002544403076171875}, "domain": "pixel"}, {"position": {"minX": 535.0, "minY": 640.0, "maxX": 607.0, "maxY": 787.0}, "class_id": 1, "box_caption": "Paper 0.003", "scores": {"class_score": 0.002506256103515625}, "domain": "pixel"}, {"position": {"minX": 903.0, "minY": 778.0, "maxX": 1042.0, "maxY": 875.0}, "class_id": 5, "box_caption": "Plastic 0.002", "scores": {"class_score": 0.0024852752685546875}, "domain": "pixel"}, {"position": {"minX": 982.5, "minY": 12.4140625, "maxX": 1041.0, "maxY": 39.9375}, "class_id": 1, "box_caption": "Paper 0.002", "scores": {"class_score": 0.0024814605712890625}, "domain": "pixel"}, {"position": {"minX": 413.75, "minY": 558.0, "maxX": 434.75, "maxY": 622.0}, "class_id": 3, "box_caption": "Metal 0.002", "scores": {"class_score": 0.00244903564453125}, "domain": "pixel"}, {"position": {"minX": 489.5, "minY": 638.0, "maxX": 605.5, "maxY": 797.0}, "class_id": 6, "box_caption": "Styrofoam 0.002", "scores": {"class_score": 0.002429962158203125}, "domain": "pixel"}, {"position": {"minX": 16.765625, "minY": 240.125, "maxX": 32.125, "maxY": 312.25}, "class_id": 3, "box_caption": "Metal 0.002", "scores": {"class_score": 0.0024089813232421875}, "domain": "pixel"}, {"position": {"minX": 185.0, "minY": 261.25, "maxX": 698.5, "maxY": 817.0}, "class_id": 3, "box_caption": "Metal 0.002", "scores": {"class_score": 0.002353668212890625}, "domain": "pixel"}, {"position": {"minX": 432.75, "minY": 533.0, "maxX": 446.75, "maxY": 568.0}, "class_id": 3, "box_caption": "Metal 0.002", "scores": {"class_score": 0.002353668212890625}, "domain": "pixel"}, {"position": {"minX": 57.1875, "minY": 331.5, "maxX": 168.75, "maxY": 397.0}, "class_id": 3, "box_caption": "Metal 0.002", "scores": {"class_score": 0.00234222412109375}, "domain": "pixel"}, {"position": {"minX": 21.75, "minY": 229.5, "maxX": 189.0, "maxY": 406.5}, "class_id": 3, "box_caption": "Metal 0.002", "scores": {"class_score": 0.0023345947265625}, "domain": "pixel"}, {"position": {"minX": 230.5, "minY": 247.5, "maxX": 301.0, "maxY": 293.5}, "class_id": 3, "box_caption": "Metal 0.002", "scores": {"class_score": 0.002330780029296875}, "domain": "pixel"}, {"position": {"minX": 440.25, "minY": 631.5, "maxX": 529.0, "maxY": 740.5}, "class_id": 0, "box_caption": "General trash 0.002", "scores": {"class_score": 0.0023097991943359375}, "domain": "pixel"}, {"position": {"minX": 432.75, "minY": 533.0, "maxX": 446.75, "maxY": 568.0}, "class_id": 5, "box_caption": "Plastic 0.002", "scores": {"class_score": 0.0022525787353515625}, "domain": "pixel"}, {"position": {"minX": 795.5, "minY": 186.0, "maxX": 859.5, "maxY": 250.5}, "class_id": 0, "box_caption": "General trash 0.002", "scores": {"class_score": 0.0022296905517578125}, "domain": "pixel"}, {"position": {"minX": 416.5, "minY": 546.0, "maxX": 442.0, "maxY": 576.0}, "class_id": 3, "box_caption": "Metal 0.002", "scores": {"class_score": 0.00213623046875}, "domain": "pixel"}, {"position": {"minX": -51.75, "minY": 5.25, "maxX": 736.0, "maxY": 790.0}, "class_id": 5, "box_caption": "Plastic 0.002", "scores": {"class_score": 0.0021209716796875}, "domain": "pixel"}, {"position": {"minX": 906.5, "minY": 787.0, "maxX": 1004.5, "maxY": 869.0}, "class_id": 0, "box_caption": "General trash 0.002", "scores": {"class_score": 0.0021076202392578125}, "domain": "pixel"}, {"position": {"minX": 787.5, "minY": 827.0, "maxX": 1050.0, "maxY": 1047.0}, "class_id": 3, "box_caption": "Metal 0.002", "scores": {"class_score": 0.00208282470703125}, "domain": "pixel"}, {"position": {"minX": 17.5, "minY": 251.5, "maxX": 123.875, "maxY": 369.0}, "class_id": 3, "box_caption": "Metal 0.002", "scores": {"class_score": 0.0020771026611328125}, "domain": "pixel"}, {"position": {"minX": 17.3125, "minY": 268.25, "maxX": 150.5, "maxY": 403.75}, "class_id": 4, "box_caption": "Glass 0.002", "scores": {"class_score": 0.0020580291748046875}, "domain": "pixel"}, {"position": {"minX": 416.25, "minY": 578.5, "maxX": 428.75, "maxY": 618.5}, "class_id": 3, "box_caption": "Metal 0.002", "scores": {"class_score": 0.0020465850830078125}, "domain": "pixel"}, {"position": {"minX": 19.21875, "minY": 266.0, "maxX": 143.375, "maxY": 404.0}, "class_id": 0, "box_caption": "General trash 0.002", "scores": {"class_score": 0.00203704833984375}, "domain": "pixel"}, {"position": {"minX": 901.5, "minY": 763.0, "maxX": 1035.0, "maxY": 910.0}, "class_id": 3, "box_caption": "Metal 0.002", "scores": {"class_score": 0.002025604248046875}, "domain": "pixel"}, {"position": {"minX": 393.75, "minY": 467.5, "maxX": 442.75, "maxY": 516.0}, "class_id": 3, "box_caption": "Metal 0.002", "scores": {"class_score": 0.00201416015625}, "domain": "pixel"}, {"position": {"minX": 794.0, "minY": 188.125, "maxX": 861.0, "maxY": 252.125}, "class_id": 7, "box_caption": "Plastic bag 0.002", "scores": {"class_score": 0.0020084381103515625}, "domain": "pixel"}, {"position": {"minX": 731.0, "minY": 714.0, "maxX": 1049.0, "maxY": 1047.0}, "class_id": 5, "box_caption": "Plastic 0.002", "scores": {"class_score": 0.002002716064453125}, "domain": "pixel"}, {"position": {"minX": 253.125, "minY": 358.5, "maxX": 647.0, "maxY": 761.5}, "class_id": 5, "box_caption": "Plastic 0.002", "scores": {"class_score": 0.0019626617431640625}, "domain": "pixel"}, {"position": {"minX": 480.75, "minY": 700.0, "maxX": 598.0, "maxY": 784.0}, "class_id": 0, "box_caption": "General trash 0.002", "scores": {"class_score": 0.0018863677978515625}, "domain": "pixel"}, {"position": {"minX": 787.5, "minY": 827.0, "maxX": 1050.0, "maxY": 1047.0}, "class_id": 7, "box_caption": "Plastic bag 0.002", "scores": {"class_score": 0.001880645751953125}, "domain": "pixel"}, {"position": {"minX": 407.5, "minY": 613.5, "maxX": 599.0, "maxY": 773.5}, "class_id": 3, "box_caption": "Metal 0.002", "scores": {"class_score": 0.0018672943115234375}, "domain": "pixel"}, {"position": {"minX": 19.875, "minY": 267.25, "maxX": 112.0, "maxY": 347.75}, "class_id": 3, "box_caption": "Metal 0.002", "scores": {"class_score": 0.0018339157104492188}, "domain": "pixel"}, {"position": {"minX": 411.0, "minY": 542.0, "maxX": 435.5, "maxY": 637.0}, "class_id": 3, "box_caption": "Metal 0.002", "scores": {"class_score": 0.0018262863159179688}, "domain": "pixel"}, {"position": {"minX": 421.0, "minY": 474.75, "maxX": 472.0, "maxY": 509.75}, "class_id": 3, "box_caption": "Metal 0.002", "scores": {"class_score": 0.0018138885498046875}, "domain": "pixel"}, {"position": {"minX": 239.375, "minY": 16.0, "maxX": 344.5, "maxY": 57.8125}, "class_id": 0, "box_caption": "General trash 0.002", "scores": {"class_score": 0.0018024444580078125}, "domain": "pixel"}, {"position": {"minX": 443.25, "minY": 488.5, "maxX": 465.75, "maxY": 522.5}, "class_id": 3, "box_caption": "Metal 0.002", "scores": {"class_score": 0.0017910003662109375}, "domain": "pixel"}, {"position": {"minX": 70.5, "minY": 14.859375, "maxX": 148.625, "maxY": 54.0}, "class_id": 0, "box_caption": "General trash 0.002", "scores": {"class_score": 0.0017881393432617188}, "domain": "pixel"}, {"position": {"minX": 388.0, "minY": 512.0, "maxX": 607.5, "maxY": 809.0}, "class_id": 4, "box_caption": "Glass 0.002", "scores": {"class_score": 0.0017719268798828125}, "domain": "pixel"}, {"position": {"minX": 593.5, "minY": 1021.0, "maxX": 800.5, "maxY": 1053.0}, "class_id": 5, "box_caption": "Plastic 0.002", "scores": {"class_score": 0.0017633438110351562}, "domain": "pixel"}, {"position": {"minX": 403.5, "minY": 469.25, "maxX": 470.5, "maxY": 515.0}, "class_id": 3, "box_caption": "Metal 0.002", "scores": {"class_score": 0.0017518997192382812}, "domain": "pixel"}, {"position": {"minX": 253.125, "minY": 358.5, "maxX": 647.0, "maxY": 761.5}, "class_id": 1, "box_caption": "Paper 0.002", "scores": {"class_score": 0.001743316650390625}, "domain": "pixel"}, {"position": {"minX": 601.0, "minY": 1017.5, "maxX": 804.0, "maxY": 1044.0}, "class_id": 4, "box_caption": "Glass 0.002", "scores": {"class_score": 0.001708984375}, "domain": "pixel"}, {"position": {"minX": 227.5, "minY": 247.75, "maxX": 302.5, "maxY": 286.25}, "class_id": 0, "box_caption": "General trash 0.002", "scores": {"class_score": 0.0017032623291015625}, "domain": "pixel"}, {"position": {"minX": 898.5, "minY": 769.0, "maxX": 1038.0, "maxY": 876.0}, "class_id": 7, "box_caption": "Plastic bag 0.002", "scores": {"class_score": 0.0016956329345703125}, "domain": "pixel"}, {"position": {"minX": 1000.5, "minY": 13.5859375, "maxX": 1040.0, "maxY": 37.4375}, "class_id": 1, "box_caption": "Paper 0.002", "scores": {"class_score": 0.0016431808471679688}, "domain": "pixel"}, {"position": {"minX": 873.5, "minY": 666.0, "maxX": 1037.0, "maxY": 904.0}, "class_id": 0, "box_caption": "General trash 0.002", "scores": {"class_score": 0.0016422271728515625}, "domain": "pixel"}, {"position": {"minX": 787.5, "minY": 892.0, "maxX": 948.5, "maxY": 1047.0}, "class_id": 1, "box_caption": "Paper 0.002", "scores": {"class_score": 0.0016164779663085938}, "domain": "pixel"}, {"position": {"minX": 899.5, "minY": 751.0, "maxX": 1039.0, "maxY": 1017.0}, "class_id": 3, "box_caption": "Metal 0.002", "scores": {"class_score": 0.0016031265258789062}, "domain": "pixel"}, {"position": {"minX": 409.25, "minY": 651.5, "maxX": 600.0, "maxY": 796.5}, "class_id": 4, "box_caption": "Glass 0.002", "scores": {"class_score": 0.001590728759765625}, "domain": "pixel"}, {"position": {"minX": 414.75, "minY": 556.0, "maxX": 440.25, "maxY": 586.0}, "class_id": 3, "box_caption": "Metal 0.002", "scores": {"class_score": 0.0015869140625}, "domain": "pixel"}, {"position": {"minX": 260.75, "minY": 832.0, "maxX": 347.25, "maxY": 880.0}, "class_id": 4, "box_caption": "Glass 0.002", "scores": {"class_score": 0.0015811920166015625}, "domain": "pixel"}, {"position": {"minX": 235.5, "minY": 520.5, "maxX": 268.25, "maxY": 583.5}, "class_id": 3, "box_caption": "Metal 0.002", "scores": {"class_score": 0.0015630722045898438}, "domain": "pixel"}, {"position": {"minX": 797.0, "minY": 181.875, "maxX": 856.0, "maxY": 233.375}, "class_id": 7, "box_caption": "Plastic bag 0.002", "scores": {"class_score": 0.0015554428100585938}, "domain": "pixel"}, {"position": {"minX": 743.0, "minY": 727.0, "maxX": 864.0, "maxY": 773.0}, "class_id": 0, "box_caption": "General trash 0.002", "scores": {"class_score": 0.0015544891357421875}, "domain": "pixel"}, {"position": {"minX": 560.0, "minY": 1020.0, "maxX": 790.0, "maxY": 1054.0}, "class_id": 3, "box_caption": "Metal 0.002", "scores": {"class_score": 0.0015478134155273438}, "domain": "pixel"}, {"position": {"minX": 744.0, "minY": 795.5, "maxX": 945.0, "maxY": 1046.0}, "class_id": 5, "box_caption": "Plastic 0.002", "scores": {"class_score": 0.0015268325805664062}, "domain": "pixel"}, {"position": {"minX": 434.5, "minY": 522.0, "maxX": 449.5, "maxY": 558.0}, "class_id": 5, "box_caption": "Plastic 0.002", "scores": {"class_score": 0.0015268325805664062}, "domain": "pixel"}, {"position": {"minX": 16.6875, "minY": 287.25, "maxX": 136.25, "maxY": 454.25}, "class_id": 3, "box_caption": "Metal 0.002", "scores": {"class_score": 0.00151824951171875}, "domain": "pixel"}, {"position": {"minX": 447.75, "minY": 478.5, "maxX": 471.75, "maxY": 505.0}, "class_id": 3, "box_caption": "Metal 0.002", "scores": {"class_score": 0.0015048980712890625}, "domain": "pixel"}, {"position": {"minX": 487.75, "minY": 700.5, "maxX": 604.5, "maxY": 784.5}, "class_id": 1, "box_caption": "Paper 0.001", "scores": {"class_score": 0.0014810562133789062}, "domain": "pixel"}, {"position": {"minX": 386.75, "minY": 476.5, "maxX": 439.25, "maxY": 525.0}, "class_id": 3, "box_caption": "Metal 0.001", "scores": {"class_score": 0.0014629364013671875}, "domain": "pixel"}, {"position": {"minX": 185.0, "minY": 261.25, "maxX": 698.5, "maxY": 817.0}, "class_id": 7, "box_caption": "Plastic bag 0.001", "scores": {"class_score": 0.0014467239379882812}, "domain": "pixel"}, {"position": {"minX": 388.0, "minY": 512.0, "maxX": 607.5, "maxY": 809.0}, "class_id": 1, "box_caption": "Paper 0.001", "scores": {"class_score": 0.0014400482177734375}, "domain": "pixel"}, {"position": {"minX": 449.0, "minY": 487.75, "maxX": 469.5, "maxY": 515.5}, "class_id": 5, "box_caption": "Plastic 0.001", "scores": {"class_score": 0.0014247894287109375}, "domain": "pixel"}, {"position": {"minX": 308.0, "minY": 754.0, "maxX": 339.0, "maxY": 836.0}, "class_id": 4, "box_caption": "Glass 0.001", "scores": {"class_score": 0.0014238357543945312}, "domain": "pixel"}, {"position": {"minX": 62.53125, "minY": 336.75, "maxX": 144.75, "maxY": 392.25}, "class_id": 4, "box_caption": "Glass 0.001", "scores": {"class_score": 0.0014219284057617188}, "domain": "pixel"}, {"position": {"minX": 451.0, "minY": 617.0, "maxX": 519.0, "maxY": 720.0}, "class_id": 3, "box_caption": "Metal 0.001", "scores": {"class_score": 0.00141143798828125}, "domain": "pixel"}, {"position": {"minX": 856.0, "minY": 743.5, "maxX": 1044.0, "maxY": 1066.0}, "class_id": 5, "box_caption": "Plastic 0.001", "scores": {"class_score": 0.0014104843139648438}, "domain": "pixel"}, {"position": {"minX": 710.0, "minY": 881.5, "maxX": 935.0, "maxY": 1046.0}, "class_id": 0, "box_caption": "General trash 0.001", "scores": {"class_score": 0.00138092041015625}, "domain": "pixel"}, {"position": {"minX": 654.0, "minY": 1016.0, "maxX": 793.0, "maxY": 1046.0}, "class_id": 5, "box_caption": "Plastic 0.001", "scores": {"class_score": 0.0013799667358398438}, "domain": "pixel"}, {"position": {"minX": 731.0, "minY": 714.0, "maxX": 1049.0, "maxY": 1047.0}, "class_id": 7, "box_caption": "Plastic bag 0.001", "scores": {"class_score": 0.00136566162109375}, "domain": "pixel"}, {"position": {"minX": 423.0, "minY": 543.0, "maxX": 444.5, "maxY": 572.0}, "class_id": 3, "box_caption": "Metal 0.001", "scores": {"class_score": 0.001361846923828125}, "domain": "pixel"}, {"position": {"minX": 535.0, "minY": 640.0, "maxX": 607.0, "maxY": 787.0}, "class_id": 3, "box_caption": "Metal 0.001", "scores": {"class_score": 0.0013608932495117188}, "domain": "pixel"}, {"position": {"minX": 710.0, "minY": 881.5, "maxX": 935.0, "maxY": 1046.0}, "class_id": 7, "box_caption": "Plastic bag 0.001", "scores": {"class_score": 0.0013532638549804688}, "domain": "pixel"}, {"position": {"minX": 408.25, "minY": 584.5, "maxX": 426.75, "maxY": 639.5}, "class_id": 3, "box_caption": "Metal 0.001", "scores": {"class_score": 0.0013494491577148438}, "domain": "pixel"}, {"position": {"minX": 633.0, "minY": 1020.0, "maxX": 810.0, "maxY": 1048.0}, "class_id": 7, "box_caption": "Plastic bag 0.001", "scores": {"class_score": 0.001338958740234375}, "domain": "pixel"}, {"position": {"minX": 495.5, "minY": 763.0, "maxX": 566.5, "maxY": 823.0}, "class_id": 4, "box_caption": "Glass 0.001", "scores": {"class_score": 0.0013284683227539062}, "domain": "pixel"}, {"position": {"minX": 17.3125, "minY": 268.25, "maxX": 150.5, "maxY": 403.75}, "class_id": 8, "box_caption": "Battery 0.001", "scores": {"class_score": 0.0013265609741210938}, "domain": "pixel"}, {"position": {"minX": 756.5, "minY": 971.5, "maxX": 834.5, "maxY": 1036.0}, "class_id": 0, "box_caption": "General trash 0.001", "scores": {"class_score": 0.001323699951171875}, "domain": "pixel"}, {"position": {"minX": 739.5, "minY": 765.0, "maxX": 850.5, "maxY": 857.0}, "class_id": 4, "box_caption": "Glass 0.001", "scores": {"class_score": 0.0013189315795898438}, "domain": "pixel"}, {"position": {"minX": 16.765625, "minY": 240.125, "maxX": 32.125, "maxY": 312.25}, "class_id": 5, "box_caption": "Plastic 0.001", "scores": {"class_score": 0.0013065338134765625}, "domain": "pixel"}, {"position": {"minX": 415.5, "minY": 564.0, "maxX": 434.0, "maxY": 594.0}, "class_id": 3, "box_caption": "Metal 0.001", "scores": {"class_score": 0.0013036727905273438}, "domain": "pixel"}, {"position": {"minX": 416.5, "minY": 537.0, "maxX": 449.0, "maxY": 572.0}, "class_id": 3, "box_caption": "Metal 0.001", "scores": {"class_score": 0.0013027191162109375}, "domain": "pixel"}, {"position": {"minX": 325.75, "minY": 393.25, "maxX": 398.25, "maxY": 436.75}, "class_id": 3, "box_caption": "Metal 0.001", "scores": {"class_score": 0.0012912750244140625}, "domain": "pixel"}, {"position": {"minX": -51.75, "minY": 5.25, "maxX": 736.0, "maxY": 790.0}, "class_id": 7, "box_caption": "Plastic bag 0.001", "scores": {"class_score": 0.0012903213500976562}, "domain": "pixel"}, {"position": {"minX": 394.75, "minY": 498.25, "maxX": 614.5, "maxY": 807.0}, "class_id": 0, "box_caption": "General trash 0.001", "scores": {"class_score": 0.0012788772583007812}, "domain": "pixel"}, {"position": {"minX": 32.4375, "minY": 273.5, "maxX": 228.5, "maxY": 444.0}, "class_id": 3, "box_caption": "Metal 0.001", "scores": {"class_score": 0.0012760162353515625}, "domain": "pixel"}, {"position": {"minX": 46.6875, "minY": 291.5, "maxX": 217.0, "maxY": 429.5}, "class_id": 5, "box_caption": "Plastic 0.001", "scores": {"class_score": 0.001262664794921875}, "domain": "pixel"}, {"position": {"minX": 811.0, "minY": 893.5, "maxX": 1048.0, "maxY": 1046.0}, "class_id": 5, "box_caption": "Plastic 0.001", "scores": {"class_score": 0.0012521743774414062}, "domain": "pixel"}, {"position": {"minX": 14.9921875, "minY": 128.75, "maxX": 45.6875, "maxY": 173.25}, "class_id": 3, "box_caption": "Metal 0.001", "scores": {"class_score": 0.001247406005859375}, "domain": "pixel"}, {"position": {"minX": 593.5, "minY": 1021.0, "maxX": 800.5, "maxY": 1053.0}, "class_id": 0, "box_caption": "General trash 0.001", "scores": {"class_score": 0.0012235641479492188}, "domain": "pixel"}, {"position": {"minX": 236.125, "minY": 816.0, "maxX": 353.0, "maxY": 895.0}, "class_id": 3, "box_caption": "Metal 0.001", "scores": {"class_score": 0.0012187957763671875}, "domain": "pixel"}, {"position": {"minX": 759.5, "minY": 682.5, "maxX": 1049.0, "maxY": 1036.0}, "class_id": 3, "box_caption": "Metal 0.001", "scores": {"class_score": 0.0011949539184570312}, "domain": "pixel"}, {"position": {"minX": 74.0, "minY": 15.9375, "maxX": 124.625, "maxY": 54.3125}, "class_id": 3, "box_caption": "Metal 0.001", "scores": {"class_score": 0.0011835098266601562}, "domain": "pixel"}, {"position": {"minX": 388.0, "minY": 512.0, "maxX": 607.5, "maxY": 809.0}, "class_id": 5, "box_caption": "Plastic 0.001", "scores": {"class_score": 0.0011653900146484375}, "domain": "pixel"}, {"position": {"minX": 535.0, "minY": 640.0, "maxX": 607.0, "maxY": 787.0}, "class_id": 5, "box_caption": "Plastic 0.001", "scores": {"class_score": 0.0011568069458007812}, "domain": "pixel"}, {"position": {"minX": 902.5, "minY": 722.0, "maxX": 1040.0, "maxY": 885.0}, "class_id": 5, "box_caption": "Plastic 0.001", "scores": {"class_score": 0.0011568069458007812}, "domain": "pixel"}, {"position": {"minX": 416.25, "minY": 578.5, "maxX": 428.75, "maxY": 618.5}, "class_id": 5, "box_caption": "Plastic 0.001", "scores": {"class_score": 0.0011548995971679688}, "domain": "pixel"}, {"position": {"minX": 416.5, "minY": 546.0, "maxX": 442.0, "maxY": 576.0}, "class_id": 5, "box_caption": "Plastic 0.001", "scores": {"class_score": 0.0011510848999023438}, "domain": "pixel"}, {"position": {"minX": 15.5, "minY": -4.75, "maxX": 334.5, "maxY": 550.0}, "class_id": 5, "box_caption": "Plastic 0.001", "scores": {"class_score": 0.001140594482421875}, "domain": "pixel"}, {"position": {"minX": 535.0, "minY": 640.0, "maxX": 607.0, "maxY": 787.0}, "class_id": 0, "box_caption": "General trash 0.001", "scores": {"class_score": 0.001140594482421875}, "domain": "pixel"}, {"position": {"minX": 799.5, "minY": 578.0, "maxX": 1040.0, "maxY": 913.0}, "class_id": 0, "box_caption": "General trash 0.001", "scores": {"class_score": 0.0011377334594726562}, "domain": "pixel"}, {"position": {"minX": 710.0, "minY": 881.5, "maxX": 935.0, "maxY": 1046.0}, "class_id": 3, "box_caption": "Metal 0.001", "scores": {"class_score": 0.00113677978515625}, "domain": "pixel"}, {"position": {"minX": 483.25, "minY": 729.5, "maxX": 555.5, "maxY": 781.5}, "class_id": 4, "box_caption": "Glass 0.001", "scores": {"class_score": 0.0011358261108398438}, "domain": "pixel"}, {"position": {"minX": 15.015625, "minY": 244.875, "maxX": 33.5, "maxY": 292.25}, "class_id": 5, "box_caption": "Plastic 0.001", "scores": {"class_score": 0.0011320114135742188}, "domain": "pixel"}, {"position": {"minX": 404.75, "minY": 537.5, "maxX": 436.25, "maxY": 571.5}, "class_id": 3, "box_caption": "Metal 0.001", "scores": {"class_score": 0.0011310577392578125}, "domain": "pixel"}, {"position": {"minX": 18.875, "minY": 305.0, "maxX": 130.875, "maxY": 408.5}, "class_id": 3, "box_caption": "Metal 0.001", "scores": {"class_score": 0.001129150390625}, "domain": "pixel"}, {"position": {"minX": 409.75, "minY": 574.5, "maxX": 431.25, "maxY": 632.5}, "class_id": 5, "box_caption": "Plastic 0.001", "scores": {"class_score": 0.0011272430419921875}, "domain": "pixel"}, {"position": {"minX": 489.5, "minY": 717.5, "maxX": 594.5, "maxY": 791.5}, "class_id": 4, "box_caption": "Glass 0.001", "scores": {"class_score": 0.0011234283447265625}, "domain": "pixel"}, {"position": {"minX": 861.0, "minY": 736.0, "maxX": 1045.0, "maxY": 1038.0}, "class_id": 0, "box_caption": "General trash 0.001", "scores": {"class_score": 0.0011224746704101562}, "domain": "pixel"}, {"position": {"minX": 15.375, "minY": 886.5, "maxX": 60.0, "maxY": 926.5}, "class_id": 3, "box_caption": "Metal 0.001", "scores": {"class_score": 0.0011081695556640625}, "domain": "pixel"}, {"position": {"minX": 411.75, "minY": 512.0, "maxX": 447.25, "maxY": 609.0}, "class_id": 3, "box_caption": "Metal 0.001", "scores": {"class_score": 0.00110626220703125}, "domain": "pixel"}, {"position": {"minX": 185.0, "minY": 261.25, "maxX": 698.5, "maxY": 817.0}, "class_id": 5, "box_caption": "Plastic 0.001", "scores": {"class_score": 0.0011034011840820312}, "domain": "pixel"}, {"position": {"minX": 430.75, "minY": 538.5, "maxX": 444.75, "maxY": 573.5}, "class_id": 4, "box_caption": "Glass 0.001", "scores": {"class_score": 0.0010986328125}, "domain": "pixel"}, {"position": {"minX": 405.0, "minY": 550.5, "maxX": 438.0, "maxY": 575.5}, "class_id": 3, "box_caption": "Metal 0.001", "scores": {"class_score": 0.0010976791381835938}, "domain": "pixel"}, {"position": {"minX": 952.5, "minY": 5.296875, "maxX": 1040.0, "maxY": 41.9375}, "class_id": 1, "box_caption": "Paper 0.001", "scores": {"class_score": 0.001094818115234375}, "domain": "pixel"}, {"position": {"minX": 502.75, "minY": 382.5, "maxX": 523.0, "maxY": 426.5}, "class_id": 3, "box_caption": "Metal 0.001", "scores": {"class_score": 0.0010929107666015625}, "domain": "pixel"}, {"position": {"minX": 185.25, "minY": 836.5, "maxX": 354.75, "maxY": 903.5}, "class_id": 4, "box_caption": "Glass 0.001", "scores": {"class_score": 0.0010833740234375}, "domain": "pixel"}, {"position": {"minX": 19.21875, "minY": 266.0, "maxX": 143.375, "maxY": 404.0}, "class_id": 7, "box_caption": "Plastic bag 0.001", "scores": {"class_score": 0.001079559326171875}, "domain": "pixel"}, {"position": {"minX": 411.5, "minY": 558.0, "maxX": 435.5, "maxY": 580.0}, "class_id": 3, "box_caption": "Metal 0.001", "scores": {"class_score": 0.0010747909545898438}, "domain": "pixel"}, {"position": {"minX": 395.0, "minY": 460.0, "maxX": 463.0, "maxY": 509.0}, "class_id": 3, "box_caption": "Metal 0.001", "scores": {"class_score": 0.001071929931640625}, "domain": "pixel"}, {"position": {"minX": 42.8125, "minY": 326.25, "maxX": 195.5, "maxY": 450.75}, "class_id": 5, "box_caption": "Plastic 0.001", "scores": {"class_score": 0.0010700225830078125}, "domain": "pixel"}, {"position": {"minX": 780.0, "minY": 182.25, "maxX": 850.0, "maxY": 240.5}, "class_id": 0, "box_caption": "General trash 0.001", "scores": {"class_score": 0.0010623931884765625}, "domain": "pixel"}, {"position": {"minX": 434.5, "minY": 522.0, "maxX": 449.5, "maxY": 558.0}, "class_id": 3, "box_caption": "Metal 0.001", "scores": {"class_score": 0.0010585784912109375}, "domain": "pixel"}, {"position": {"minX": 903.0, "minY": 778.0, "maxX": 1042.0, "maxY": 875.0}, "class_id": 1, "box_caption": "Paper 0.001", "scores": {"class_score": 0.0010585784912109375}, "domain": "pixel"}, {"position": {"minX": 421.0, "minY": 474.75, "maxX": 472.0, "maxY": 509.75}, "class_id": 5, "box_caption": "Plastic 0.001", "scores": {"class_score": 0.0010538101196289062}, "domain": "pixel"}, {"position": {"minX": -51.75, "minY": 5.25, "maxX": 736.0, "maxY": 790.0}, "class_id": 1, "box_caption": "Paper 0.001", "scores": {"class_score": 0.0010509490966796875}, "domain": "pixel"}, {"position": {"minX": 48.375, "minY": 323.75, "maxX": 184.875, "maxY": 414.25}, "class_id": 4, "box_caption": "Glass 0.001", "scores": {"class_score": 0.001049041748046875}, "domain": "pixel"}, {"position": {"minX": 803.0, "minY": 896.5, "maxX": 997.0, "maxY": 1047.0}, "class_id": 4, "box_caption": "Glass 0.001", "scores": {"class_score": 0.0010480880737304688}, "domain": "pixel"}, {"position": {"minX": 414.0, "minY": 363.75, "maxX": 505.5, "maxY": 414.75}, "class_id": 3, "box_caption": "Metal 0.001", "scores": {"class_score": 0.0010471343994140625}, "domain": "pixel"}, {"position": {"minX": 769.0, "minY": 193.5, "maxX": 857.0, "maxY": 260.75}, "class_id": 0, "box_caption": "General trash 0.001", "scores": {"class_score": 0.0010328292846679688}, "domain": "pixel"}, {"position": {"minX": 149.875, "minY": 1018.5, "maxX": 215.125, "maxY": 1041.0}, "class_id": 3, "box_caption": "Metal 0.001", "scores": {"class_score": 0.0010280609130859375}, "domain": "pixel"}, {"position": {"minX": 403.5, "minY": 469.25, "maxX": 470.5, "maxY": 515.0}, "class_id": 5, "box_caption": "Plastic 0.001", "scores": {"class_score": 0.0010271072387695312}, "domain": "pixel"}, {"position": {"minX": 15.015625, "minY": 244.875, "maxX": 33.5, "maxY": 292.25}, "class_id": 3, "box_caption": "Metal 0.001", "scores": {"class_score": 0.0010242462158203125}, "domain": "pixel"}, {"position": {"minX": 795.0, "minY": 880.5, "maxX": 1029.0, "maxY": 1046.0}, "class_id": 0, "box_caption": "General trash 0.001", "scores": {"class_score": 0.0010213851928710938}, "domain": "pixel"}, {"position": {"minX": 385.75, "minY": 455.75, "maxX": 433.25, "maxY": 504.75}, "class_id": 3, "box_caption": "Metal 0.001", "scores": {"class_score": 0.0010175704956054688}, "domain": "pixel"}, {"position": {"minX": 392.25, "minY": 640.0, "maxX": 595.5, "maxY": 780.0}, "class_id": 5, "box_caption": "Plastic 0.001", "scores": {"class_score": 0.0010166168212890625}, "domain": "pixel"}, {"position": {"minX": 492.5, "minY": 759.5, "maxX": 555.5, "maxY": 826.5}, "class_id": 3, "box_caption": "Metal 0.001", "scores": {"class_score": 0.0010118484497070312}, "domain": "pixel"}, {"position": {"minX": 30.75, "minY": 292.5, "maxX": 181.25, "maxY": 416.0}, "class_id": 0, "box_caption": "General trash 0.001", "scores": {"class_score": 0.0010013580322265625}, "domain": "pixel"}], "class_labels": {"0": "General trash", "1": "Paper", "2": "Paper pack", "3": "Metal", "4": "Glass", "5": "Plastic", "6": "Styrofoam", "7": "Plastic bag", "8": "Battery", "9": "Clothing"}}