{"box_data": [{"position": {"minX": 342.0, "minY": 246.0, "maxX": 813.0, "maxY": 749.5}, "class_id": 0, "box_caption": "General trash 0.492", "scores": {"class_score": 0.491943359375}, "domain": "pixel"}, {"position": {"minX": 342.0, "minY": 246.0, "maxX": 813.0, "maxY": 749.5}, "class_id": 7, "box_caption": "Plastic bag 0.241", "scores": {"class_score": 0.241455078125}, "domain": "pixel"}, {"position": {"minX": 342.0, "minY": 246.0, "maxX": 813.0, "maxY": 749.5}, "class_id": 1, "box_caption": "Paper 0.095", "scores": {"class_score": 0.0950927734375}, "domain": "pixel"}, {"position": {"minX": 341.0, "minY": 260.5, "maxX": 816.0, "maxY": 739.0}, "class_id": 2, "box_caption": "Paper pack 0.038", "scores": {"class_score": 0.037933349609375}, "domain": "pixel"}, {"position": {"minX": 375.75, "minY": 931.5, "maxX": 418.75, "maxY": 971.5}, "class_id": 4, "box_caption": "Glass 0.024", "scores": {"class_score": 0.0238800048828125}, "domain": "pixel"}, {"position": {"minX": 288.75, "minY": 432.5, "maxX": 343.25, "maxY": 473.5}, "class_id": 7, "box_caption": "Plastic bag 0.021", "scores": {"class_score": 0.0209197998046875}, "domain": "pixel"}, {"position": {"minX": 218.25, "minY": 571.5, "maxX": 271.5, "maxY": 604.5}, "class_id": 7, "box_caption": "Plastic bag 0.016", "scores": {"class_score": 0.0164031982421875}, "domain": "pixel"}, {"position": {"minX": 859.5, "minY": 308.75, "maxX": 904.5, "maxY": 348.75}, "class_id": 7, "box_caption": "Plastic bag 0.015", "scores": {"class_score": 0.0147247314453125}, "domain": "pixel"}, {"position": {"minX": 298.0, "minY": 372.75, "maxX": 352.5, "maxY": 411.25}, "class_id": 7, "box_caption": "Plastic bag 0.012", "scores": {"class_score": 0.0118408203125}, "domain": "pixel"}, {"position": {"minX": 150.75, "minY": 15.859375, "maxX": 164.0, "maxY": 64.5625}, "class_id": 0, "box_caption": "General trash 0.010", "scores": {"class_score": 0.00994110107421875}, "domain": "pixel"}, {"position": {"minX": 341.0, "minY": 260.5, "maxX": 816.0, "maxY": 739.0}, "class_id": 3, "box_caption": "Metal 0.007", "scores": {"class_score": 0.007305145263671875}, "domain": "pixel"}, {"position": {"minX": 395.75, "minY": 228.75, "maxX": 1009.0, "maxY": 763.0}, "class_id": 0, "box_caption": "General trash 0.006", "scores": {"class_score": 0.00597381591796875}, "domain": "pixel"}, {"position": {"minX": 341.0, "minY": 260.5, "maxX": 816.0, "maxY": 739.0}, "class_id": 5, "box_caption": "Plastic 0.005", "scores": {"class_score": 0.004978179931640625}, "domain": "pixel"}, {"position": {"minX": 341.0, "minY": 260.5, "maxX": 816.0, "maxY": 739.0}, "class_id": 6, "box_caption": "Styrofoam 0.005", "scores": {"class_score": 0.004863739013671875}, "domain": "pixel"}, {"position": {"minX": 279.75, "minY": 425.75, "maxX": 345.25, "maxY": 484.25}, "class_id": 7, "box_caption": "Plastic bag 0.004", "scores": {"class_score": 0.003875732421875}, "domain": "pixel"}, {"position": {"minX": 276.5, "minY": 431.0, "maxX": 331.0, "maxY": 476.0}, "class_id": 7, "box_caption": "Plastic bag 0.003", "scores": {"class_score": 0.0032958984375}, "domain": "pixel"}, {"position": {"minX": 341.0, "minY": 260.5, "maxX": 816.0, "maxY": 739.0}, "class_id": 9, "box_caption": "Clothing 0.003", "scores": {"class_score": 0.0032444000244140625}, "domain": "pixel"}, {"position": {"minX": 883.0, "minY": 833.5, "maxX": 949.0, "maxY": 871.5}, "class_id": 7, "box_caption": "Plastic bag 0.003", "scores": {"class_score": 0.00323486328125}, "domain": "pixel"}, {"position": {"minX": 378.75, "minY": 928.0, "maxX": 416.75, "maxY": 970.0}, "class_id": 3, "box_caption": "Metal 0.003", "scores": {"class_score": 0.0027561187744140625}, "domain": "pixel"}, {"position": {"minX": 296.5, "minY": 385.75, "maxX": 351.5, "maxY": 419.75}, "class_id": 7, "box_caption": "Plastic bag 0.002", "scores": {"class_score": 0.00238037109375}, "domain": "pixel"}, {"position": {"minX": 341.0, "minY": 260.5, "maxX": 816.0, "maxY": 739.0}, "class_id": 4, "box_caption": "Glass 0.002", "scores": {"class_score": 0.0022411346435546875}, "domain": "pixel"}, {"position": {"minX": 207.5, "minY": 574.0, "maxX": 272.25, "maxY": 616.0}, "class_id": 7, "box_caption": "Plastic bag 0.002", "scores": {"class_score": 0.0022296905517578125}, "domain": "pixel"}, {"position": {"minX": 395.75, "minY": 228.75, "maxX": 1009.0, "maxY": 763.0}, "class_id": 7, "box_caption": "Plastic bag 0.002", "scores": {"class_score": 0.0021915435791015625}, "domain": "pixel"}, {"position": {"minX": 378.75, "minY": 930.0, "maxX": 419.75, "maxY": 973.0}, "class_id": 7, "box_caption": "Plastic bag 0.002", "scores": {"class_score": 0.00211334228515625}, "domain": "pixel"}, {"position": {"minX": 300.5, "minY": 359.25, "maxX": 356.5, "maxY": 421.75}, "class_id": 7, "box_caption": "Plastic bag 0.002", "scores": {"class_score": 0.0020503997802734375}, "domain": "pixel"}, {"position": {"minX": 273.0, "minY": 657.0, "maxX": 345.5, "maxY": 700.0}, "class_id": 7, "box_caption": "Plastic bag 0.002", "scores": {"class_score": 0.0020084381103515625}, "domain": "pixel"}, {"position": {"minX": 299.5, "minY": 428.0, "maxX": 358.0, "maxY": 464.5}, "class_id": 7, "box_caption": "Plastic bag 0.002", "scores": {"class_score": 0.0019989013671875}, "domain": "pixel"}, {"position": {"minX": 896.0, "minY": 474.5, "maxX": 961.0, "maxY": 520.0}, "class_id": 7, "box_caption": "Plastic bag 0.002", "scores": {"class_score": 0.001987457275390625}, "domain": "pixel"}, {"position": {"minX": 318.75, "minY": 496.75, "maxX": 387.75, "maxY": 538.5}, "class_id": 7, "box_caption": "Plastic bag 0.002", "scores": {"class_score": 0.0017652511596679688}, "domain": "pixel"}, {"position": {"minX": 222.75, "minY": 324.0, "maxX": 278.0, "maxY": 358.5}, "class_id": 7, "box_caption": "Plastic bag 0.002", "scores": {"class_score": 0.0016584396362304688}, "domain": "pixel"}, {"position": {"minX": 341.0, "minY": 260.5, "maxX": 816.0, "maxY": 739.0}, "class_id": 8, "box_caption": "Battery 0.002", "scores": {"class_score": 0.0016546249389648438}, "domain": "pixel"}, {"position": {"minX": 378.0, "minY": 932.5, "maxX": 417.5, "maxY": 969.5}, "class_id": 5, "box_caption": "Plastic 0.002", "scores": {"class_score": 0.0015420913696289062}, "domain": "pixel"}, {"position": {"minX": 482.0, "minY": 275.5, "maxX": 865.0, "maxY": 735.5}, "class_id": 0, "box_caption": "General trash 0.001", "scores": {"class_score": 0.0013933181762695312}, "domain": "pixel"}, {"position": {"minX": 373.75, "minY": 935.0, "maxX": 404.75, "maxY": 967.0}, "class_id": 4, "box_caption": "Glass 0.001", "scores": {"class_score": 0.001392364501953125}, "domain": "pixel"}, {"position": {"minX": 150.75, "minY": 15.859375, "maxX": 164.0, "maxY": 64.5625}, "class_id": 5, "box_caption": "Plastic 0.001", "scores": {"class_score": 0.0013484954833984375}, "domain": "pixel"}, {"position": {"minX": 722.5, "minY": 307.0, "maxX": 775.5, "maxY": 326.5}, "class_id": 7, "box_caption": "Plastic bag 0.001", "scores": {"class_score": 0.0013399124145507812}, "domain": "pixel"}, {"position": {"minX": 820.5, "minY": 367.25, "maxX": 881.5, "maxY": 408.75}, "class_id": 7, "box_caption": "Plastic bag 0.001", "scores": {"class_score": 0.0012998580932617188}, "domain": "pixel"}, {"position": {"minX": 285.75, "minY": 432.5, "maxX": 356.75, "maxY": 500.5}, "class_id": 7, "box_caption": "Plastic bag 0.001", "scores": {"class_score": 0.0012569427490234375}, "domain": "pixel"}, {"position": {"minX": 897.0, "minY": 648.0, "maxX": 949.0, "maxY": 685.0}, "class_id": 7, "box_caption": "Plastic bag 0.001", "scores": {"class_score": 0.0012111663818359375}, "domain": "pixel"}, {"position": {"minX": 276.0, "minY": 943.0, "maxX": 370.0, "maxY": 985.0}, "class_id": 4, "box_caption": "Glass 0.001", "scores": {"class_score": 0.0011548995971679688}, "domain": "pixel"}, {"position": {"minX": 352.0, "minY": 421.5, "maxX": 792.0, "maxY": 737.5}, "class_id": 0, "box_caption": "General trash 0.001", "scores": {"class_score": 0.0011463165283203125}, "domain": "pixel"}, {"position": {"minX": 395.75, "minY": 228.75, "maxX": 1009.0, "maxY": 763.0}, "class_id": 1, "box_caption": "Paper 0.001", "scores": {"class_score": 0.0010862350463867188}, "domain": "pixel"}, {"position": {"minX": 264.25, "minY": 911.0, "maxX": 315.25, "maxY": 949.0}, "class_id": 4, "box_caption": "Glass 0.001", "scores": {"class_score": 0.0010290145874023438}, "domain": "pixel"}], "class_labels": {"0": "General trash", "1": "Paper", "2": "Paper pack", "3": "Metal", "4": "Glass", "5": "Plastic", "6": "Styrofoam", "7": "Plastic bag", "8": "Battery", "9": "Clothing"}}